Workbook
Name Subassembly: 'Top Assy'!$A$91:$I$103
Name Year: 'Top Assy'!$B$9

Sheet Top Assy
A2: CUSTOMER:
A3: P/N: | D3: NSN #: | F3: Yield %: | G3: 0.95
A4: REV: | D4: SOL #:
A5: QUOTE LOG No.: | D5: RFQ #: | F5: Comments:
A6: QTY: | B6: =F13&", "&G13&", "&H13&", "&I13&", "&J13&", "&K13&", "&L13&", "&M13 -> 10, 25, 50, 75, 100, 250, 500, 1000
A7: DATE:
A8: ESTIMATOR:
A9: Labor Rate Year: | B9: 2026
A11: MANUFACTURING OPERATIONS | F11: COST ESTIMATED QUANTITIES | N11: NRE/SET-UP
B13: SET-UP TIME | C13: RUN TIME | E13: LABOR RATE | F13: 10 | G13: 25 | H13: 50 | I13: 75 | J13: 100 | K13: 250 | L13: 500 | M13: 1000 | N13: 1
A14: Program | E14: 0 | N14: =(($B14/N$13*$E14)+($C14*$E14)) -> 0
A15: Fixtures | E15: 0 | N15: =(($B15/N$13*$E15)+($C15*$E15)) -> 0
A16: Mill/Turn | E16: 0 | F16: =(($B16/F$13*$E16)+($C16*$E16)) -> 0 | G16: =(($B16/G$13*$E16)+($C16*$E16)) -> 0 | H16: =(($B16/H$13*$E16)+($C16*$E16)) -> 0 | I16: =(($B16/I$13*$E16)+($C16*$E16)) -> 0 | J16: =(($B16/J$13*$E16)+($C16*$E16)) -> 0 | K16: =(($B16/K$13*$E16)+($C16*$E16)) -> 0 | L16: =(($B16/L$13*$E16)+($C16*$E16)) -> 0 | M16: =(($B16/M$13*$E16)+($C16*$E16)) -> 0
A17: Metals - Mills | E17: 0 | F17: =(($B17/F$13*$E17)+($C17*$E17)) -> 0 | G17: =(($B17/G$13*$E17)+($C17*$E17)) -> 0 | H17: =(($B17/H$13*$E17)+($C17*$E17)) -> 0 | I17: =(($B17/I$13*$E17)+($C17*$E17)) -> 0 | J17: =(($B17/J$13*$E17)+($C17*$E17)) -> 0 | K17: =(($B17/K$13*$E17)+($C17*$E17)) -> 0 | L17: =(($B17/L$13*$E17)+($C17*$E17)) -> 0 | M17: =(($B17/M$13*$E17)+($C17*$E17)) -> 0
A18: Metals - Lathe | E18: 0 | F18: =(($B18/F$13*$E18)+($C18*$E18)) -> 0 | G18: =(($B18/G$13*$E18)+($C18*$E18)) -> 0 | H18: =(($B18/H$13*$E18)+($C18*$E18)) -> 0 | I18: =(($B18/I$13*$E18)+($C18*$E18)) -> 0 | J18: =(($B18/J$13*$E18)+($C18*$E18)) -> 0 | K18: =(($B18/K$13*$E18)+($C18*$E18)) -> 0 | L18: =(($B18/L$13*$E18)+($C18*$E18)) -> 0 | M18: =(($B18/M$13*$E18)+($C18*$E18)) -> 0
A19: Rubber Mold | E19: 0 | F19: =(($B19/F$13*$E19)+($C19*$E19)) -> 0 | G19: =(($B19/G$13*$E19)+($C19*$E19)) -> 0 | H19: =(($B19/H$13*$E19)+($C19*$E19)) -> 0 | I19: =(($B19/I$13*$E19)+($C19*$E19)) -> 0 | J19: =(($B19/J$13*$E19)+($C19*$E19)) -> 0 | K19: =(($B19/K$13*$E19)+($C19*$E19)) -> 0 | L19: =(($B19/L$13*$E19)+($C19*$E19)) -> 0 | M19: =(($B19/M$13*$E19)+($C19*$E19)) -> 0
A20: Plastic Injection Mold | E20: 0 | F20: =(($B20/F$13*$E20)+($C20*$E20)) -> 0 | G20: =(($B20/G$13*$E20)+($C20*$E20)) -> 0 | H20: =(($B20/H$13*$E20)+($C20*$E20)) -> 0 | I20: =(($B20/I$13*$E20)+($C20*$E20)) -> 0 | J20: =(($B20/J$13*$E20)+($C20*$E20)) -> 0 | K20: =(($B20/K$13*$E20)+($C20*$E20)) -> 0 | L20: =(($B20/L$13*$E20)+($C20*$E20)) -> 0 | M20: =(($B20/M$13*$E20)+($C20*$E20)) -> 0
A21: Plastic Compression Mold | E21: 0 | F21: =(($B21/F$13*$E21)+($C21*$E21)) -> 0 | G21: =(($B21/G$13*$E21)+($C21*$E21)) -> 0 | H21: =(($B21/H$13*$E21)+($C21*$E21)) -> 0 | I21: =(($B21/I$13*$E21)+($C21*$E21)) -> 0 | J21: =(($B21/J$13*$E21)+($C21*$E21)) -> 0 | K21: =(($B21/K$13*$E21)+($C21*$E21)) -> 0 | L21: =(($B21/L$13*$E21)+($C21*$E21)) -> 0 | M21: =(($B21/M$13*$E21)+($C21*$E21)) -> 0
A22: Waterjet - Operator | E22: 0 | F22: =(($B22/F$13*$E22)+($C22*$E22)) -> 0 | G22: =(($B22/G$13*$E22)+($C22*$E22)) -> 0 | H22: =(($B22/H$13*$E22)+($C22*$E22)) -> 0 | I22: =(($B22/I$13*$E22)+($C22*$E22)) -> 0 | J22: =(($B22/J$13*$E22)+($C22*$E22)) -> 0 | K22: =(($B22/K$13*$E22)+($C22*$E22)) -> 0 | L22: =(($B22/L$13*$E22)+($C22*$E22)) -> 0 | M22: =(($B22/M$13*$E22)+($C22*$E22)) -> 0
A23: Assembly, Die Punch, Deburr | E23: 0 | F23: =(($B23/F$13*$E23)+($C23*$E23)) -> 0 | G23: =(($B23/G$13*$E23)+($C23*$E23)) -> 0 | H23: =(($B23/H$13*$E23)+($C23*$E23)) -> 0 | I23: =(($B23/I$13*$E23)+($C23*$E23)) -> 0 | J23: =(($B23/J$13*$E23)+($C23*$E23)) -> 0 | K23: =(($B23/K$13*$E23)+($C23*$E23)) -> 0 | L23: =(($B23/L$13*$E23)+($C23*$E23)) -> 0 | M23: =(($B23/M$13*$E23)+($C23*$E23)) -> 0
A24: Quality Inspection | E24: 0 | F24: =(($B24/F$13*$E24)+($C24*$E24)) -> 0 | G24: =(($B24/G$13*$E24)+($C24*$E24)) -> 0 | H24: =(($B24/H$13*$E24)+($C24*$E24)) -> 0 | I24: =(($B24/I$13*$E24)+($C24*$E24)) -> 0 | J24: =(($B24/J$13*$E24)+($C24*$E24)) -> 0 | K24: =(($B24/K$13*$E24)+($C24*$E24)) -> 0 | L24: =(($B24/L$13*$E24)+($C24*$E24)) -> 0 | M24: =(($B24/M$13*$E24)+($C24*$E24)) -> 0
A25: ID & Pack | E25: 0 | F25: =(($B25/F$13*$E25)+($C25*$E25)) -> 0 | G25: =(($B25/G$13*$E25)+($C25*$E25)) -> 0 | H25: =(($B25/H$13*$E25)+($C25*$E25)) -> 0 | I25: =(($B25/I$13*$E25)+($C25*$E25)) -> 0 | J25: =(($B25/J$13*$E25)+($C25*$E25)) -> 0 | K25: =(($B25/K$13*$E25)+($C25*$E25)) -> 0 | L25: =(($B25/L$13*$E25)+($C25*$E25)) -> 0 | M25: =(($B25/M$13*$E25)+($C25*$E25)) -> 0
C26: Labor | E26: Basic LABOR | F26: =SUM(F16:F25) -> 0 | G26: =SUM(G16:G25) -> 0 | H26: =SUM(H16:H25) -> 0 | I26: =SUM(I16:I25) -> 0 | J26: =SUM(J16:J25) -> 0 | K26: =SUM(K16:K25) -> 0 | L26: =SUM(L16:L25) -> 0 | M26: =SUM(M16:M25) -> 0 | N26: =SUM(N14:N25) -> 0
B27: T. setup | C27: T.RUN | E27: hrs | F27: =(($B$28/F13)+$C$28)/60 -> 0 | G27: =(($B$28/G13)+$C$28)/60 -> 0 | H27: =(($B$28/H13)+$C$28)/60 -> 0 | I27: =(($B$28/I13)+$C$28)/60 -> 0 | J27: =(($B$28/J13)+$C$28)/60 -> 0 | K27: =(($B$28/K13)+$C$28)/60 -> 0 | L27: =(($B$28/L13)+$C$28)/60 -> 0 | M27: =(($B$28/M13)+$C$28)/60 -> 0
B28: =SUM(B16:B25) -> 0 | C28: =SUM(C16:C25) -> 0 | D28: 0 | E28: BURDEN | F28: =F26*$D$28 -> 0 | G28: =G26*$D$28 -> 0 | H28: =H26*$D$28 -> 0 | I28: =I26*$D$28 -> 0 | J28: =J26*$D$28 -> 0 | K28: =K26*$D$28 -> 0 | L28: =L26*$D$28 -> 0 | M28: =M26*$D$28 -> 0
E30: Total | F30: =F26+F28 -> 0 | G30: =G26+G28 -> 0 | H30: =H26+H28 -> 0 | I30: =I26+I28 -> 0 | J30: =J26+J28 -> 0 | K30: =K26+K28 -> 0 | L30: =L26+L28 -> 0 | M30: =M26+M28 -> 0 | N30: =N26 -> 0
A32: Raw Materials & Hardware | B32: Matl UoM | C32: Parts QTY | D32: Unit Price | E32: Matl Burden | F32: ="Qty: "& F13 -> Qty: 10 | G32: ="Qty: "& G13 -> Qty: 25 | H32: ="Qty: "& H13 -> Qty: 50 | I32: ="Qty: "& I13 -> Qty: 75 | J32: ="Qty: "& J13 -> Qty: 100 | K32: ="Qty: "& K13 -> Qty: 250 | L32: ="Qty: "& L13 -> Qty: 500 | M32: ="Qty: "& M13 -> Qty: 1000 | N32: Amortize/ Min Buy
E33: =C33*D33 -> 0 | F33: =IF($N33=TRUE,$E33/F$13,$E33*(1+(1/F$13))) -> 0 | G33: =IF($N33=TRUE,$E33/G$13,$E33*(1+(1/G$13))) -> 0 | H33: =IF($N33=TRUE,$E33/H$13,$E33*(1+(1/H$13))) -> 0 | I33: =IF($N33=TRUE,$E33/I$13,$E33*(1+(1/I$13))) -> 0 | J33: =IF($N33=TRUE,$E33/J$13,$E33*(1+(1/J$13))) -> 0 | K33: =IF($N33=TRUE,$E33/K$13,$E33*(1+(1/K$13))) -> 0 | L33: =IF($N33=TRUE,E33/L$13,$E33*(1+(1/L$13))) -> 0 | M33: =IF($N33=TRUE,E33/M$13,$E33*(1+(1/M$13))) -> 0 | N33: FALSE
E34: =C34*D34 -> 0 | F34: =IF($N34=TRUE,$E34/F$13,$E34*(1+(1/F$13))) -> 0 | G34: =IF($N34=TRUE,$E34/G$13,$E34*(1+(1/G$13))) -> 0 | H34: =IF($N34=TRUE,$E34/H$13,$E34*(1+(1/H$13))) -> 0 | I34: =IF($N34=TRUE,$E34/I$13,$E34*(1+(1/I$13))) -> 0 | J34: =IF($N34=TRUE,$E34/J$13,$E34*(1+(1/J$13))) -> 0 | K34: =IF($N34=TRUE,$E34/K$13,$E34*(1+(1/K$13))) -> 0 | L34: =IF($N34=TRUE,E34/L$13,$E34*(1+(1/L$13))) -> 0 | M34: =IF($N34=TRUE,E34/M$13,$E34*(1+(1/M$13))) -> 0 | N34: FALSE
E35: =C35*D35 -> 0 | F35: =IF($N35=TRUE,$E35/F$13,$E35*(1+(1/F$13))) -> 0 | G35: =IF($N35=TRUE,$E35/G$13,$E35*(1+(1/G$13))) -> 0 | H35: =IF($N35=TRUE,$E35/H$13,$E35*(1+(1/H$13))) -> 0 | I35: =IF($N35=TRUE,$E35/I$13,$E35*(1+(1/I$13))) -> 0 | J35: =IF($N35=TRUE,$E35/J$13,$E35*(1+(1/J$13))) -> 0 | K35: =IF($N35=TRUE,$E35/K$13,$E35*(1+(1/K$13))) -> 0 | L35: =IF($N35=TRUE,E35/L$13,$E35*(1+(1/L$13))) -> 0 | M35: =IF($N35=TRUE,E35/M$13,$E35*(1+(1/M$13))) -> 0 | N35: FALSE | S35: QTY | T35: Total
E36: =C36*D36 -> 0 | F36: =IF($N36=TRUE,$E36/F$13,$E36*(1+(1/F$13))) -> 0 | G36: =IF($N36=TRUE,$E36/G$13,$E36*(1+(1/G$13))) -> 0 | H36: =IF($N36=TRUE,$E36/H$13,$E36*(1+(1/H$13))) -> 0 | I36: =IF($N36=TRUE,$E36/I$13,$E36*(1+(1/I$13))) -> 0 | J36: =IF($N36=TRUE,$E36/J$13,$E36*(1+(1/J$13))) -> 0 | K36: =IF($N36=TRUE,$E36/K$13,$E36*(1+(1/K$13))) -> 0 | L36: =IF($N36=TRUE,E36/L$13,$E36*(1+(1/L$13))) -> 0 | M36: =IF($N36=TRUE,E36/M$13,$E36*(1+(1/M$13))) -> 0 | N36: FALSE | S36: =M13 -> 1000 | T36: =M80 -> 0
E37: =C37*D37 -> 0 | F37: =IF($N37=TRUE,$E37/F$13,$E37*(1+(1/F$13))) -> 0 | G37: =IF($N37=TRUE,$E37/G$13,$E37*(1+(1/G$13))) -> 0 | H37: =IF($N37=TRUE,$E37/H$13,$E37*(1+(1/H$13))) -> 0 | I37: =IF($N37=TRUE,$E37/I$13,$E37*(1+(1/I$13))) -> 0 | J37: =IF($N37=TRUE,$E37/J$13,$E37*(1+(1/J$13))) -> 0 | K37: =IF($N37=TRUE,$E37/K$13,$E37*(1+(1/K$13))) -> 0 | L37: =IF($N37=TRUE,E37/L$13,$E37*(1+(1/L$13))) -> 0 | M37: =IF($N37=TRUE,E37/M$13,$E37*(1+(1/M$13))) -> 0 | N37: FALSE | S37: =L13 -> 500 | T37: =L80 -> 0
E38: =C38*D38 -> 0 | F38: =IF($N38=TRUE,$E38/F$13,$E38*(1+(1/F$13))) -> 0 | G38: =IF($N38=TRUE,$E38/G$13,$E38*(1+(1/G$13))) -> 0 | H38: =IF($N38=TRUE,$E38/H$13,$E38*(1+(1/H$13))) -> 0 | I38: =IF($N38=TRUE,$E38/I$13,$E38*(1+(1/I$13))) -> 0 | J38: =IF($N38=TRUE,$E38/J$13,$E38*(1+(1/J$13))) -> 0 | K38: =IF($N38=TRUE,$E38/K$13,$E38*(1+(1/K$13))) -> 0 | L38: =IF($N38=TRUE,E38/L$13,$E38*(1+(1/L$13))) -> 0 | M38: =IF($N38=TRUE,E38/M$13,$E38*(1+(1/M$13))) -> 0 | N38: FALSE | S38: =I13 -> 75 | T38: =I80 -> 0
E39: =C39*D39 -> 0 | F39: =IF($N39=TRUE,$E39/F$13,$E39*(1+(1/F$13))) -> 0 | G39: =IF($N39=TRUE,$E39/G$13,$E39*(1+(1/G$13))) -> 0 | H39: =IF($N39=TRUE,$E39/H$13,$E39*(1+(1/H$13))) -> 0 | I39: =IF($N39=TRUE,$E39/I$13,$E39*(1+(1/I$13))) -> 0 | J39: =IF($N39=TRUE,$E39/J$13,$E39*(1+(1/J$13))) -> 0 | K39: =IF($N39=TRUE,$E39/K$13,$E39*(1+(1/K$13))) -> 0 | L39: =IF($N39=TRUE,E39/L$13,$E39*(1+(1/L$13))) -> 0 | M39: =IF($N39=TRUE,E39/M$13,$E39*(1+(1/M$13))) -> 0 | N39: FALSE | S39: =H13 -> 50 | T39: =H80 -> 0
E40: =C40*D40 -> 0 | F40: =IF($N40=TRUE,$E40/F$13,$E40*(1+(1/F$13))) -> 0 | G40: =IF($N40=TRUE,$E40/G$13,$E40*(1+(1/G$13))) -> 0 | H40: =IF($N40=TRUE,$E40/H$13,$E40*(1+(1/H$13))) -> 0 | I40: =IF($N40=TRUE,$E40/I$13,$E40*(1+(1/I$13))) -> 0 | J40: =IF($N40=TRUE,$E40/J$13,$E40*(1+(1/J$13))) -> 0 | K40: =IF($N40=TRUE,$E40/K$13,$E40*(1+(1/K$13))) -> 0 | L40: =IF($N40=TRUE,E40/L$13,$E40*(1+(1/L$13))) -> 0 | M40: =IF($N40=TRUE,E40/M$13,$E40*(1+(1/M$13))) -> 0 | N40: FALSE | S40: =G13 -> 25 | T40: =G80 -> 0
E41: =C41*D41 -> 0 | F41: =IF($N41=TRUE,$E41/F$13,$E41*(1+(1/F$13))) -> 0 | G41: =IF($N41=TRUE,$E41/G$13,$E41*(1+(1/G$13))) -> 0 | H41: =IF($N41=TRUE,$E41/H$13,$E41*(1+(1/H$13))) -> 0 | I41: =IF($N41=TRUE,$E41/I$13,$E41*(1+(1/I$13))) -> 0 | J41: =IF($N41=TRUE,$E41/J$13,$E41*(1+(1/J$13))) -> 0 | K41: =IF($N41=TRUE,$E41/K$13,$E41*(1+(1/K$13))) -> 0 | L41: =IF($N41=TRUE,E41/L$13,$E41*(1+(1/L$13))) -> 0 | M41: =IF($N41=TRUE,E41/M$13,$E41*(1+(1/M$13))) -> 0 | N41: FALSE | S41: =F13 -> 10 | T41: =F80 -> 0
E42: =C42*D42 -> 0 | F42: =IF($N42=TRUE,$E42/F$13,$E42*(1+(1/F$13))) -> 0 | G42: =IF($N42=TRUE,$E42/G$13,$E42*(1+(1/G$13))) -> 0 | H42: =IF($N42=TRUE,$E42/H$13,$E42*(1+(1/H$13))) -> 0 | I42: =IF($N42=TRUE,$E42/I$13,$E42*(1+(1/I$13))) -> 0 | J42: =IF($N42=TRUE,$E42/J$13,$E42*(1+(1/J$13))) -> 0 | K42: =IF($N42=TRUE,$E42/K$13,$E42*(1+(1/K$13))) -> 0 | L42: =IF($N42=TRUE,E42/L$13,$E42*(1+(1/L$13))) -> 0 | M42: =IF($N42=TRUE,E42/M$13,$E42*(1+(1/M$13))) -> 0 | N42: FALSE
E43: =C43*D43 -> 0 | F43: =IF($N43=TRUE,$E43/F$13,$E43*(1+(1/F$13))) -> 0 | G43: =IF($N43=TRUE,$E43/G$13,$E43*(1+(1/G$13))) -> 0 | H43: =IF($N43=TRUE,$E43/H$13,$E43*(1+(1/H$13))) -> 0 | I43: =IF($N43=TRUE,$E43/I$13,$E43*(1+(1/I$13))) -> 0 | J43: =IF($N43=TRUE,$E43/J$13,$E43*(1+(1/J$13))) -> 0 | K43: =IF($N43=TRUE,$E43/K$13,$E43*(1+(1/K$13))) -> 0 | L43: =IF($N43=TRUE,E43/L$13,$E43*(1+(1/L$13))) -> 0 | M43: =IF($N43=TRUE,E43/M$13,$E43*(1+(1/M$13))) -> 0 | N43: FALSE
E44: =C44*D44 -> 0 | F44: =IF($N44=TRUE,$E44/F$13,$E44*(1+(1/F$13))) -> 0 | G44: =IF($N44=TRUE,$E44/G$13,$E44*(1+(1/G$13))) -> 0 | H44: =IF($N44=TRUE,$E44/H$13,$E44*(1+(1/H$13))) -> 0 | I44: =IF($N44=TRUE,$E44/I$13,$E44*(1+(1/I$13))) -> 0 | J44: =IF($N44=TRUE,$E44/J$13,$E44*(1+(1/J$13))) -> 0 | K44: =IF($N44=TRUE,$E44/K$13,$E44*(1+(1/K$13))) -> 0 | L44: =IF($N44=TRUE,E44/L$13,$E44*(1+(1/L$13))) -> 0 | M44: =IF($N44=TRUE,E44/M$13,$E44*(1+(1/M$13))) -> 0 | N44: FALSE
A45: Processes | B45: QTY | C45: Subassy? | D45: SETUP $ | E45: RUN$ EA.
C46: FALSE | F46: =IF($C46=TRUE,VLOOKUP($A46,Subassembly,2,FALSE)*IF($B46=0,1,$B46),($D46/F$13)+$E46) -> 0 | G46: =IF($C46=TRUE,VLOOKUP($A46,Subassembly,3,FALSE)*IF($B46=0,1,$B46),($D46/G$13)+$E46) -> 0 | H46: =IF($C46=TRUE,VLOOKUP($A46,Subassembly,4,FALSE)*IF($B46=0,1,$B46),($D46/H$13)+$E46) -> 0 | I46: =IF($C46=TRUE,VLOOKUP($A46,Subassembly,5,FALSE)*IF($B46=0,1,$B46),($D46/I$13)+$E46) -> 0 | J46: =IF($C46=TRUE,VLOOKUP($A46,Subassembly,6,FALSE)*IF($B46=0,1,$B46),($D46/J$13)+$E46) -> 0 | K46: =IF($C46=TRUE,VLOOKUP($A46,Subassembly,7,FALSE)*IF($B46=0,1,$B46),($D46/K$13)+$E46) -> 0 | L46: =IF($C46=TRUE,VLOOKUP($A46,Subassembly,8,FALSE)*IF($B46=0,1,$B46),($D46/L$13)+$E46) -> 0 | M46: =IF($C46=TRUE,VLOOKUP($A46,Subassembly,9,FALSE)*IF($B46=0,1,$B46),($D46/M$13)+$E46) -> 0
C47: FALSE | F47: =IF($C47=TRUE,VLOOKUP($A47,Subassembly,2,FALSE)*IF($B47=0,1,$B47),($D47/F$13)+$E47) -> 0 | G47: =IF($C47=TRUE,VLOOKUP($A47,Subassembly,3,FALSE)*IF($B47=0,1,$B47),($D47/G$13)+$E47) -> 0 | H47: =IF($C47=TRUE,VLOOKUP($A47,Subassembly,4,FALSE)*IF($B47=0,1,$B47),($D47/H$13)+$E47) -> 0 | I47: =IF($C47=TRUE,VLOOKUP($A47,Subassembly,5,FALSE)*IF($B47=0,1,$B47),($D47/I$13)+$E47) -> 0 | J47: =IF($C47=TRUE,VLOOKUP($A47,Subassembly,6,FALSE)*IF($B47=0,1,$B47),($D47/J$13)+$E47) -> 0 | K47: =IF($C47=TRUE,VLOOKUP($A47,Subassembly,7,FALSE)*IF($B47=0,1,$B47),($D47/K$13)+$E47) -> 0 | L47: =IF($C47=TRUE,VLOOKUP($A47,Subassembly,8,FALSE)*IF($B47=0,1,$B47),($D47/L$13)+$E47) -> 0 | M47: =IF($C47=TRUE,VLOOKUP($A47,Subassembly,9,FALSE)*IF($B47=0,1,$B47),($D47/M$13)+$E47) -> 0
C48: FALSE | F48: =IF($C48=TRUE,VLOOKUP($A48,Subassembly,2,FALSE)*IF($B48=0,1,$B48),($D48/F$13)+$E48) -> 0 | G48: =IF($C48=TRUE,VLOOKUP($A48,Subassembly,3,FALSE)*IF($B48=0,1,$B48),($D48/G$13)+$E48) -> 0 | H48: =IF($C48=TRUE,VLOOKUP($A48,Subassembly,4,FALSE)*IF($B48=0,1,$B48),($D48/H$13)+$E48) -> 0 | I48: =IF($C48=TRUE,VLOOKUP($A48,Subassembly,5,FALSE)*IF($B48=0,1,$B48),($D48/I$13)+$E48) -> 0 | J48: =IF($C48=TRUE,VLOOKUP($A48,Subassembly,6,FALSE)*IF($B48=0,1,$B48),($D48/J$13)+$E48) -> 0 | K48: =IF($C48=TRUE,VLOOKUP($A48,Subassembly,7,FALSE)*IF($B48=0,1,$B48),($D48/K$13)+$E48) -> 0 | L48: =IF($C48=TRUE,VLOOKUP($A48,Subassembly,8,FALSE)*IF($B48=0,1,$B48),($D48/L$13)+$E48) -> 0 | M48: =IF($C48=TRUE,VLOOKUP($A48,Subassembly,9,FALSE)*IF($B48=0,1,$B48),($D48/M$13)+$E48) -> 0
C49: FALSE | F49: =IF($C49=TRUE,VLOOKUP($A49,Subassembly,2,FALSE)*IF($B49=0,1,$B49),($D49/F$13)+$E49) -> 0 | G49: =IF($C49=TRUE,VLOOKUP($A49,Subassembly,3,FALSE)*IF($B49=0,1,$B49),($D49/G$13)+$E49) -> 0 | H49: =IF($C49=TRUE,VLOOKUP($A49,Subassembly,4,FALSE)*IF($B49=0,1,$B49),($D49/H$13)+$E49) -> 0 | I49: =IF($C49=TRUE,VLOOKUP($A49,Subassembly,5,FALSE)*IF($B49=0,1,$B49),($D49/I$13)+$E49) -> 0 | J49: =IF($C49=TRUE,VLOOKUP($A49,Subassembly,6,FALSE)*IF($B49=0,1,$B49),($D49/J$13)+$E49) -> 0 | K49: =IF($C49=TRUE,VLOOKUP($A49,Subassembly,7,FALSE)*IF($B49=0,1,$B49),($D49/K$13)+$E49) -> 0 | L49: =IF($C49=TRUE,VLOOKUP($A49,Subassembly,8,FALSE)*IF($B49=0,1,$B49),($D49/L$13)+$E49) -> 0 | M49: =IF($C49=TRUE,VLOOKUP($A49,Subassembly,9,FALSE)*IF($B49=0,1,$B49),($D49/M$13)+$E49) -> 0
C50: FALSE | F50: =IF($C50=TRUE,VLOOKUP($A50,Subassembly,2,FALSE)*IF($B50=0,1,$B50),($D50/F$13)+$E50) -> 0 | G50: =IF($C50=TRUE,VLOOKUP($A50,Subassembly,3,FALSE)*IF($B50=0,1,$B50),($D50/G$13)+$E50) -> 0 | H50: =IF($C50=TRUE,VLOOKUP($A50,Subassembly,4,FALSE)*IF($B50=0,1,$B50),($D50/H$13)+$E50) -> 0 | I50: =IF($C50=TRUE,VLOOKUP($A50,Subassembly,5,FALSE)*IF($B50=0,1,$B50),($D50/I$13)+$E50) -> 0 | J50: =IF($C50=TRUE,VLOOKUP($A50,Subassembly,6,FALSE)*IF($B50=0,1,$B50),($D50/J$13)+$E50) -> 0 | K50: =IF($C50=TRUE,VLOOKUP($A50,Subassembly,7,FALSE)*IF($B50=0,1,$B50),($D50/K$13)+$E50) -> 0 | L50: =IF($C50=TRUE,VLOOKUP($A50,Subassembly,8,FALSE)*IF($B50=0,1,$B50),($D50/L$13)+$E50) -> 0 | M50: =IF($C50=TRUE,VLOOKUP($A50,Subassembly,9,FALSE)*IF($B50=0,1,$B50),($D50/M$13)+$E50) -> 0
C51: FALSE | F51: =IF($C51=TRUE,VLOOKUP($A51,Subassembly,2,FALSE)*IF($B51=0,1,$B51),($D51/F$13)+$E51) -> 0 | G51: =IF($C51=TRUE,VLOOKUP($A51,Subassembly,3,FALSE)*IF($B51=0,1,$B51),($D51/G$13)+$E51) -> 0 | H51: =IF($C51=TRUE,VLOOKUP($A51,Subassembly,4,FALSE)*IF($B51=0,1,$B51),($D51/H$13)+$E51) -> 0 | I51: =IF($C51=TRUE,VLOOKUP($A51,Subassembly,5,FALSE)*IF($B51=0,1,$B51),($D51/I$13)+$E51) -> 0 | J51: =IF($C51=TRUE,VLOOKUP($A51,Subassembly,6,FALSE)*IF($B51=0,1,$B51),($D51/J$13)+$E51) -> 0 | K51: =IF($C51=TRUE,VLOOKUP($A51,Subassembly,7,FALSE)*IF($B51=0,1,$B51),($D51/K$13)+$E51) -> 0 | L51: =IF($C51=TRUE,VLOOKUP($A51,Subassembly,8,FALSE)*IF($B51=0,1,$B51),($D51/L$13)+$E51) -> 0 | M51: =IF($C51=TRUE,VLOOKUP($A51,Subassembly,9,FALSE)*IF($B51=0,1,$B51),($D51/M$13)+$E51) -> 0
C52: FALSE | F52: =IF($C52=TRUE,VLOOKUP($A52,Subassembly,2,FALSE)*IF($B52=0,1,$B52),($D52/F$13)+$E52) -> 0 | G52: =IF($C52=TRUE,VLOOKUP($A52,Subassembly,3,FALSE)*IF($B52=0,1,$B52),($D52/G$13)+$E52) -> 0 | H52: =IF($C52=TRUE,VLOOKUP($A52,Subassembly,4,FALSE)*IF($B52=0,1,$B52),($D52/H$13)+$E52) -> 0 | I52: =IF($C52=TRUE,VLOOKUP($A52,Subassembly,5,FALSE)*IF($B52=0,1,$B52),($D52/I$13)+$E52) -> 0 | J52: =IF($C52=TRUE,VLOOKUP($A52,Subassembly,6,FALSE)*IF($B52=0,1,$B52),($D52/J$13)+$E52) -> 0 | K52: =IF($C52=TRUE,VLOOKUP($A52,Subassembly,7,FALSE)*IF($B52=0,1,$B52),($D52/K$13)+$E52) -> 0 | L52: =IF($C52=TRUE,VLOOKUP($A52,Subassembly,8,FALSE)*IF($B52=0,1,$B52),($D52/L$13)+$E52) -> 0 | M52: =IF($C52=TRUE,VLOOKUP($A52,Subassembly,9,FALSE)*IF($B52=0,1,$B52),($D52/M$13)+$E52) -> 0
C53: FALSE | F53: =IF($C53=TRUE,VLOOKUP($A53,Subassembly,2,FALSE)*IF($B53=0,1,$B53),($D53/F$13)+$E53) -> 0 | G53: =IF($C53=TRUE,VLOOKUP($A53,Subassembly,3,FALSE)*IF($B53=0,1,$B53),($D53/G$13)+$E53) -> 0 | H53: =IF($C53=TRUE,VLOOKUP($A53,Subassembly,4,FALSE)*IF($B53=0,1,$B53),($D53/H$13)+$E53) -> 0 | I53: =IF($C53=TRUE,VLOOKUP($A53,Subassembly,5,FALSE)*IF($B53=0,1,$B53),($D53/I$13)+$E53) -> 0 | J53: =IF($C53=TRUE,VLOOKUP($A53,Subassembly,6,FALSE)*IF($B53=0,1,$B53),($D53/J$13)+$E53) -> 0 | K53: =IF($C53=TRUE,VLOOKUP($A53,Subassembly,7,FALSE)*IF($B53=0,1,$B53),($D53/K$13)+$E53) -> 0 | L53: =IF($C53=TRUE,VLOOKUP($A53,Subassembly,8,FALSE)*IF($B53=0,1,$B53),($D53/L$13)+$E53) -> 0 | M53: =IF($C53=TRUE,VLOOKUP($A53,Subassembly,9,FALSE)*IF($B53=0,1,$B53),($D53/M$13)+$E53) -> 0
C54: FALSE | F54: =IF($C54=TRUE,VLOOKUP($A54,Subassembly,2,FALSE)*IF($B54=0,1,$B54),($D54/F$13)+$E54) -> 0 | G54: =IF($C54=TRUE,VLOOKUP($A54,Subassembly,3,FALSE)*IF($B54=0,1,$B54),($D54/G$13)+$E54) -> 0 | H54: =IF($C54=TRUE,VLOOKUP($A54,Subassembly,4,FALSE)*IF($B54=0,1,$B54),($D54/H$13)+$E54) -> 0 | I54: =IF($C54=TRUE,VLOOKUP($A54,Subassembly,5,FALSE)*IF($B54=0,1,$B54),($D54/I$13)+$E54) -> 0 | J54: =IF($C54=TRUE,VLOOKUP($A54,Subassembly,6,FALSE)*IF($B54=0,1,$B54),($D54/J$13)+$E54) -> 0 | K54: =IF($C54=TRUE,VLOOKUP($A54,Subassembly,7,FALSE)*IF($B54=0,1,$B54),($D54/K$13)+$E54) -> 0 | L54: =IF($C54=TRUE,VLOOKUP($A54,Subassembly,8,FALSE)*IF($B54=0,1,$B54),($D54/L$13)+$E54) -> 0 | M54: =IF($C54=TRUE,VLOOKUP($A54,Subassembly,9,FALSE)*IF($B54=0,1,$B54),($D54/M$13)+$E54) -> 0
C55: FALSE | F55: =IF($C55=TRUE,VLOOKUP($A55,Subassembly,2,FALSE)*IF($B55=0,1,$B55),($D55/F$13)+$E55) -> 0 | G55: =IF($C55=TRUE,VLOOKUP($A55,Subassembly,3,FALSE)*IF($B55=0,1,$B55),($D55/G$13)+$E55) -> 0 | H55: =IF($C55=TRUE,VLOOKUP($A55,Subassembly,4,FALSE)*IF($B55=0,1,$B55),($D55/H$13)+$E55) -> 0 | I55: =IF($C55=TRUE,VLOOKUP($A55,Subassembly,5,FALSE)*IF($B55=0,1,$B55),($D55/I$13)+$E55) -> 0 | J55: =IF($C55=TRUE,VLOOKUP($A55,Subassembly,6,FALSE)*IF($B55=0,1,$B55),($D55/J$13)+$E55) -> 0 | K55: =IF($C55=TRUE,VLOOKUP($A55,Subassembly,7,FALSE)*IF($B55=0,1,$B55),($D55/K$13)+$E55) -> 0 | L55: =IF($C55=TRUE,VLOOKUP($A55,Subassembly,8,FALSE)*IF($B55=0,1,$B55),($D55/L$13)+$E55) -> 0 | M55: =IF($C55=TRUE,VLOOKUP($A55,Subassembly,9,FALSE)*IF($B55=0,1,$B55),($D55/M$13)+$E55) -> 0
C56: FALSE | F56: =IF($C56=TRUE,VLOOKUP($A56,Subassembly,2,FALSE)*IF($B56=0,1,$B56),($D56/F$13)+$E56) -> 0 | G56: =IF($C56=TRUE,VLOOKUP($A56,Subassembly,3,FALSE)*IF($B56=0,1,$B56),($D56/G$13)+$E56) -> 0 | H56: =IF($C56=TRUE,VLOOKUP($A56,Subassembly,4,FALSE)*IF($B56=0,1,$B56),($D56/H$13)+$E56) -> 0 | I56: =IF($C56=TRUE,VLOOKUP($A56,Subassembly,5,FALSE)*IF($B56=0,1,$B56),($D56/I$13)+$E56) -> 0 | J56: =IF($C56=TRUE,VLOOKUP($A56,Subassembly,6,FALSE)*IF($B56=0,1,$B56),($D56/J$13)+$E56) -> 0 | K56: =IF($C56=TRUE,VLOOKUP($A56,Subassembly,7,FALSE)*IF($B56=0,1,$B56),($D56/K$13)+$E56) -> 0 | L56: =IF($C56=TRUE,VLOOKUP($A56,Subassembly,8,FALSE)*IF($B56=0,1,$B56),($D56/L$13)+$E56) -> 0 | M56: =IF($C56=TRUE,VLOOKUP($A56,Subassembly,9,FALSE)*IF($B56=0,1,$B56),($D56/M$13)+$E56) -> 0
C57: FALSE | F57: =IF($C57=TRUE,VLOOKUP($A57,Subassembly,2,FALSE)*IF($B57=0,1,$B57),($D57/F$13)+$E57) -> 0 | G57: =IF($C57=TRUE,VLOOKUP($A57,Subassembly,3,FALSE)*IF($B57=0,1,$B57),($D57/G$13)+$E57) -> 0 | H57: =IF($C57=TRUE,VLOOKUP($A57,Subassembly,4,FALSE)*IF($B57=0,1,$B57),($D57/H$13)+$E57) -> 0 | I57: =IF($C57=TRUE,VLOOKUP($A57,Subassembly,5,FALSE)*IF($B57=0,1,$B57),($D57/I$13)+$E57) -> 0 | J57: =IF($C57=TRUE,VLOOKUP($A57,Subassembly,6,FALSE)*IF($B57=0,1,$B57),($D57/J$13)+$E57) -> 0 | K57: =IF($C57=TRUE,VLOOKUP($A57,Subassembly,7,FALSE)*IF($B57=0,1,$B57),($D57/K$13)+$E57) -> 0 | L57: =IF($C57=TRUE,VLOOKUP($A57,Subassembly,8,FALSE)*IF($B57=0,1,$B57),($D57/L$13)+$E57) -> 0 | M57: =IF($C57=TRUE,VLOOKUP($A57,Subassembly,9,FALSE)*IF($B57=0,1,$B57),($D57/M$13)+$E57) -> 0
B58: MATERIAL & HARDWARE TOTAL | F58: =SUM(F33:F44) -> 0 | G58: =SUM(G33:G44) -> 0 | H58: =SUM(H33:H44) -> 0 | I58: =SUM(I33:I44) -> 0 | J58: =SUM(J33:J44) -> 0 | K58: =SUM(K33:K44) -> 0 | L58: =SUM(L33:L44) -> 0 | M58: =SUM(M33:M44) -> 0 | N58: =IF(N13=0,0,SUM(N42:N44)) -> 0
B59: PROCESSES TOTAL | F59: =SUM(F46:F57) -> 0 | G59: =SUM(G46:G57) -> 0 | H59: =SUM(H46:H57) -> 0 | I59: =SUM(I46:I57) -> 0 | J59: =SUM(J46:J57) -> 0 | K59: =SUM(K46:K57) -> 0 | L59: =SUM(L46:L57) -> 0 | M59: =SUM(M46:M57) -> 0 | N59: =IF(N13=0,0,SUM(N46:N57)) -> 0
B60: M+L Subtotal | F60: =SUM(F30+F58+F59) -> 0 | G60: =SUM(G30+G58+G59) -> 0 | H60: =SUM(H30+H58+H59) -> 0 | I60: =SUM(I30+I58+I59) -> 0 | J60: =SUM(J30+J58+J59) -> 0 | K60: =SUM(K30+K58+K59) -> 0 | L60: =SUM(L30+L58+L59) -> 0 | M60: =SUM(M30+M58+M59) -> 0 | N60: =IF(N13=0,0,SUM(N30+N58+N59)) -> 0
D62: LABOR G&A | E62: 0 | F62: =F30*$E62 -> 0 | G62: =G30*$E62 -> 0 | H62: =H30*$E62 -> 0 | I62: =I30*$E62 -> 0 | J62: =J30*$E62 -> 0 | K62: =K30*$E62 -> 0 | L62: =L30*$E62 -> 0 | M62: =M30*$E62 -> 0
D63: MAT'ls &HARDWARE G&A | E63: 0 | F63: =F58*$E63 -> 0 | G63: =G58*$E63 -> 0 | H63: =H58*$E63 -> 0 | I63: =I58*$E63 -> 0 | J63: =J58*$E63 -> 0 | K63: =K58*$E63 -> 0 | L63: =L58*$E63 -> 0 | M63: =M58*$E63 -> 0
D64: PROCESS G&A | E64: 0 | F64: =F59*$E64 -> 0 | G64: =G59*$E64 -> 0 | H64: =H59*$E64 -> 0 | I64: =I59*$E64 -> 0 | J64: =J59*$E64 -> 0 | K64: =K59*$E64 -> 0 | L64: =L59*$E64 -> 0 | M64: =M59*$E64 -> 0
E65: SUBTOTAL | F65: =SUM(F62:F64) -> 0 | G65: =SUM(G62:G64) -> 0 | H65: =SUM(H62:H64) -> 0 | I65: =SUM(I62:I64) -> 0 | J65: =SUM(J62:J64) -> 0 | K65: =SUM(K62:K64) -> 0 | L65: =SUM(L62:L64) -> 0 | M65: =SUM(M62:M64) -> 0
D66: LABOR PROFIT | E66: 0 | F66: =(F30+F62)*$E66 -> 0 | G66: =(G30+G62)*$E66 -> 0 | H66: =(H30+H62)*$E66 -> 0 | I66: =(I30+I62)*$E66 -> 0 | J66: =(J30+J62)*$E66 -> 0 | K66: =(K30+K62)*$E66 -> 0 | L66: =(L30+L62)*$E66 -> 0 | M66: =(M30+M62)*$E66 -> 0
D67: MAT'ls &HARDWARE PROFIT | E67: 0 | F67: =(+F63+F58)*$E67 -> 0 | G67: =(+G63+G58)*$E67 -> 0 | H67: =(+H63+H58)*$E67 -> 0 | I67: =(+I63+I58)*$E67 -> 0 | J67: =(+J63+J58)*$E67 -> 0 | K67: =(+K63+K58)*$E67 -> 0 | L67: =(+L63+L58)*$E67 -> 0 | M67: =(+M63+M58)*$E67 -> 0
D68: PROCESS PROFIT | E68: 0 | F68: =(+F64+F59)*$E68 -> 0 | G68: =(+G64+G59)*$E68 -> 0 | H68: =(+H64+H59)*$E68 -> 0 | I68: =(+I64+I59)*$E68 -> 0 | J68: =(+J64+J59)*$E68 -> 0 | K68: =(+K64+K59)*$E68 -> 0 | L68: =(+L64+L59)*$E68 -> 0 | M68: =(+M64+M59)*$E68 -> 0
E69: SUBTOTAL | F69: =SUM(F66:F68) -> 0 | G69: =SUM(G66:G68) -> 0 | H69: =SUM(H66:H68) -> 0 | I69: =SUM(I66:I68) -> 0 | J69: =SUM(J66:J68) -> 0 | K69: =SUM(K66:K68) -> 0 | L69: =SUM(L66:L68) -> 0 | M69: =SUM(M66:M68) -> 0 | Q69: Total Value
E70: REFERENCE | F70: =SUM(F60+F65+F69) -> 0 | G70: =SUM(G60+G65+G69) -> 0 | H70: =SUM(H60+H65+H69) -> 0 | I70: =SUM(I60+I65+I69) -> 0 | J70: =SUM(J60+J65+J69) -> 0 | K70: =SUM(K60+K65+K69) -> 0 | L70: =SUM(L60+L65+L69) -> 0 | M70: =SUM(M60+M65+M69) -> 0 | N70: =SUM(N60+N65+N69) -> 0
D71: MARGIN | F71: =(F70-F60)/F70 -> #DIV/0! | G71: =(G70-G60)/G70 -> #DIV/0! | H71: =(H70-H60)/H70 -> #DIV/0! | I71: =(I70-I60)/I70 -> #DIV/0! | J71: =(J70-J60)/J70 -> #DIV/0! | K71: =(K70-K60)/K70 -> #DIV/0! | L71: =(L70-L60)/L70 -> #DIV/0! | M71: =(M70-M60)/M70 -> #DIV/0!
D72: Labor | F72: =SUM((F30,F62,F66)) -> 0 | G72: =SUM((G30,G62,G66)) -> 0 | H72: =SUM((H30,H62,H66)) -> 0 | I72: =SUM((I30,I62,I66)) -> 0 | J72: =SUM((J30,J62,J66)) -> 0 | K72: =SUM((K30,K62,K66)) -> 0 | L72: =SUM((L30,L62,L66)) -> 0 | M72: =SUM((M30,M62,M66)) -> 0 | N72: =SUM((N30,N62,N66)) -> 0 | Q72: QTY | R72: Unit | S72: Ext. Cost
C73: Matl & Hardware | F73: =(F58+F63+F67) -> 0 | G73: =(G58+G63+G67) -> 0 | H73: =(H58+H63+H67) -> 0 | I73: =(I58+I63+I67) -> 0 | J73: =(J58+J63+J67) -> 0 | K73: =(K58+K63+K67) -> 0 | L73: =(L58+L63+L67) -> 0 | M73: =(M58+M63+M67) -> 0 | N73: =(N58+N63+N67) -> 0 | Q73: =F13 -> 10 | R73: =F80 -> 0 | S73: =R73*Q73 -> 0
D74: Process | F74: =F59+F64+F68 -> 0 | G74: =G59+G64+G68 -> 0 | H74: =H59+H64+H68 -> 0 | I74: =I59+I64+I68 -> 0 | J74: =J59+J64+J68 -> 0 | K74: =K59+K64+K68 -> 0 | L74: =L59+L64+L68 -> 0 | M74: =M59+M64+M68 -> 0 | N74: =N59+N64+N68 -> 0 | Q74: =G13 -> 25 | R74: =G80 -> 0 | S74: =R74*Q74 -> 0
D75: Subtotal | F75: =SUM(F72:F74) -> 0 | G75: =SUM(G72:G74) -> 0 | H75: =SUM(H72:H74) -> 0 | I75: =SUM(I72:I74) -> 0 | J75: =SUM(J72:J74) -> 0 | K75: =SUM(K72:K74) -> 0 | L75: =SUM(L72:L74) -> 0 | M75: =SUM(M72:M74) -> 0 | N75: =SUM(N72:N74) -> 0 | Q75: =H13 -> 50 | R75: =H80 -> 0 | S75: =R75*Q75 -> 0
D76: Amortized | F76: =$N$75/F13 -> 0 | G76: =$N$75/G13 -> 0 | H76: =$N$75/H13 -> 0 | I76: =$N$75/I13 -> 0 | J76: =$N$75/J13 -> 0 | K76: =$N$75/K13 -> 0 | L76: =$N$75/L13 -> 0 | M76: =$N$75/M13 -> 0 | Q76: =I13 -> 75 | R76: =I80 -> 0 | S76: =R76*Q76 -> 0
D77: Yield | F77: =F60-F60*$G$3 -> 0 | G77: =G60-G60*$G$3 -> 0 | H77: =H60-H60*$G$3 -> 0 | I77: =I60-I60*$G$3 -> 0 | J77: =J60-J60*$G$3 -> 0 | K77: =K60-K60*$G$3 -> 0 | L77: =L60-L60*$G$3 -> 0 | M77: =M60-M60*$G$3 -> 0 | Q77: =J13 -> 100 | R77: =J80 -> 0 | S77: =R77*Q77 -> 0
D78: Facilities | F78: 0 | G78: 0 | H78: 0 | I78: 0 | J78: 0 | K78: 0 | L78: 0 | M78: 0 | Q78: =K13 -> 250 | R78: =K80 -> 0 | S78: =R78*Q78 -> 0
B79: Sales/Management Markup | E79: 0 | F79: =F75*$E$79 -> 0 | G79: =G75*$E$79 -> 0 | H79: =H75*$E$79 -> 0 | I79: =I75*$E$79 -> 0 | J79: =J75*$E$79 -> 0 | K79: =K75*$E$79 -> 0 | L79: =L75*$E$79 -> 0 | M79: =M75*$E$79 -> 0 | Q79: =L13 -> 500 | R79: =L80 -> 0 | S79: =R79*Q79 -> 0
D80: Sell Price | F80: =SUM(F75:F79) -> 0 | G80: =SUM(G75:G79) -> 0 | H80: =SUM(H75:H79) -> 0 | I80: =SUM(I75:I79) -> 0 | J80: =SUM(J75:J79) -> 0 | K80: =SUM(K75:K79) -> 0 | L80: =SUM(L75:L79) -> 0 | M80: =SUM(M75:M79) -> 0 | Q80: =M13 -> 1000 | R80: =M80 -> 0 | S80: =R80*Q80 -> 0
D81: Gross Margin | F81: =(F80-F60-F76-F77)/(F80-F76) -> #DIV/0! | G81: =(G80-G60-G76-G77)/(G80-G76) -> #DIV/0! | H81: =(H80-H60-H76-H77)/(H80-H76) -> #DIV/0! | I81: =(I80-I60-I76-I77)/(I80-I76) -> #DIV/0! | J81: =(J80-J60-J76-J77)/(J80-J76) -> #DIV/0! | K81: =(K80-K60-K76-K77)/(K80-K76) -> #DIV/0! | L81: =(L80-L60-L76-L77)/(L80-L76) -> #DIV/0! | M81: =(M80-M60-M76-M77)/(M80-M76) -> #DIV/0!
D82: Material % of Price | F82: =(F58+'Subassy 1'!F51+'Subassy 2'!F51+'Subassy 3'!F51+'Subassy 4'!F51+'Subassy 5'!F51+'Subassy 6'!F51+'Subassy 7'!F51+'Subassy 8'!F51+'Subassy 9'!F51+'Subassy 10'!F51+'Subassy 11'!F51+'Subassy 12'!F51)/F80 -> #DIV/0! | G82: =(G58+'Subassy 1'!G51+'Subassy 2'!G51+'Subassy 3'!G51+'Subassy 4'!G51+'Subassy 5'!G51+'Subassy 6'!G51+'Subassy 7'!G51+'Subassy 8'!G51+'Subassy 9'!G51+'Subassy 10'!G51+'Subassy 11'!G51+'Subassy 12'!G51)/G80 -> #DIV/0! | H82: =(H58+'Subassy 1'!H51+'Subassy 2'!H51+'Subassy 3'!H51+'Subassy 4'!H51+'Subassy 5'!H51+'Subassy 6'!H51+'Subassy 7'!H51+'Subassy 8'!H51+'Subassy 9'!H51+'Subassy 10'!H51+'Subassy 11'!H51+'Subassy 12'!H51)/H80 -> #DIV/0! | I82: =(I58+'Subassy 1'!I51+'Subassy 2'!K51+'Subassy 3'!K51+'Subassy 4'!I51+'Subassy 5'!I51+'Subassy 6'!I51+'Subassy 7'!I51+'Subassy 8'!I51+'Subassy 9'!I51+'Subassy 10'!I51+'Subassy 11'!I51+'Subassy 12'!I51)/I80 -> #DIV/0! | J82: =(J58+'Subassy 1'!L51+'Subassy 2'!L51+'Subassy 3'!L51+'Subassy 4'!L51+'Subassy 5'!L51+'Subassy 6'!L51+'Subassy 7'!L51+'Subassy 8'!L51+'Subassy 9'!L51+'Subassy 10'!L51+'Subassy 11'!L51+'Subassy 12'!L51)/J80 -> #DIV/0! | K82: =(K58+'Subassy 1'!M51+'Subassy 2'!M51+'Subassy 3'!M51+'Subassy 4'!M51+'Subassy 5'!M51+'Subassy 6'!M51+'Subassy 7'!M51+'Subassy 8'!M51+'Subassy 9'!M51+'Subassy 10'!M51+'Subassy 11'!M51+'Subassy 12'!M51)/K80 -> #DIV/0! | L82: =(L58+'Subassy 1'!L51+'Subassy 2'!L51+'Subassy 3'!L51+'Subassy 4'!L51+'Subassy 5'!L51+'Subassy 6'!L51+'Subassy 7'!L51+'Subassy 8'!L51+'Subassy 9'!L51+'Subassy 10'!L51+'Subassy 11'!L51+'Subassy 12'!L51)/L80 -> #DIV/0! | M82: =(M58+'Subassy 1'!M51+'Subassy 2'!M51+'Subassy 3'!M51+'Subassy 4'!M51+'Subassy 5'!M51+'Subassy 6'!M51+'Subassy 7'!M51+'Subassy 8'!M51+'Subassy 9'!M51+'Subassy 10'!M51+'Subassy 11'!M51+'Subassy 12'!M51)/M80 -> #DIV/0!
A90: Subassemblies Totals Before Profit + G&A
A91: Total Costs | B91: 10 | C91: 25 | D91: 50 | E91: 100 | F91: 250 | G91: 500 | H91: 750 | I91: 1000
A92: ='Subassy 1'!D63 -> 1 | B92: ='Subassy 1'!F63 -> 0 | C92: ='Subassy 1'!G63 -> 0 | D92: ='Subassy 1'!H63 -> 0 | E92: ='Subassy 1'!I63 -> 0 | F92: ='Subassy 1'!J63 -> 0 | G92: ='Subassy 1'!K63 -> 0 | H92: ='Subassy 1'!L63 -> 0 | I92: ='Subassy 1'!M63 -> 0
A93: ='Subassy 2'!D63 -> 2 | B93: ='Subassy 2'!F63 -> 0 | C93: ='Subassy 2'!G63 -> 0 | D93: ='Subassy 2'!H63 -> 0 | E93: ='Subassy 2'!I63 -> 0 | F93: ='Subassy 2'!J63 -> 0 | G93: ='Subassy 2'!K63 -> 0 | H93: ='Subassy 2'!L63 -> 0 | I93: ='Subassy 2'!M63 -> 0
A94: ='Subassy 3'!D63 -> 3 | B94: ='Subassy 3'!F63 -> 0 | C94: ='Subassy 3'!G63 -> 0 | D94: ='Subassy 3'!H63 -> 0 | E94: ='Subassy 3'!I63 -> 0 | F94: ='Subassy 3'!J63 -> 0 | G94: ='Subassy 3'!K63 -> 0 | H94: ='Subassy 3'!L63 -> 0 | I94: ='Subassy 3'!M63 -> 0
A95: ='Subassy 4'!D63 -> 4 | B95: ='Subassy 4'!F63 -> 0 | C95: ='Subassy 4'!G63 -> 0 | D95: ='Subassy 4'!H63 -> 0 | E95: ='Subassy 4'!I63 -> 0 | F95: ='Subassy 4'!J63 -> 0 | G95: ='Subassy 4'!K63 -> 0 | H95: ='Subassy 4'!L63 -> 0 | I95: ='Subassy 4'!M63 -> 0
A96: ='Subassy 5'!D63 -> 5 | B96: ='Subassy 5'!F63 -> 0 | C96: ='Subassy 5'!G63 -> 0 | D96: ='Subassy 5'!H63 -> 0 | E96: ='Subassy 5'!I63 -> 0 | F96: ='Subassy 5'!J63 -> 0 | G96: ='Subassy 5'!K63 -> 0 | H96: ='Subassy 5'!L63 -> 0 | I96: ='Subassy 5'!M63 -> 0
A97: ='Subassy 6'!D63 -> 6 | B97: ='Subassy 6'!F63 -> 0 | C97: ='Subassy 6'!G63 -> 0 | D97: ='Subassy 6'!H63 -> 0 | E97: ='Subassy 6'!I63 -> 0 | F97: ='Subassy 6'!J63 -> 0 | G97: ='Subassy 6'!K63 -> 0 | H97: ='Subassy 6'!L63 -> 0 | I97: ='Subassy 6'!M63 -> 0
A98: ='Subassy 7'!D63 -> 7 | B98: ='Subassy 7'!F63 -> 0 | C98: ='Subassy 7'!G63 -> 0 | D98: ='Subassy 7'!H63 -> 0 | E98: ='Subassy 7'!I63 -> 0 | F98: ='Subassy 7'!J63 -> 0 | G98: ='Subassy 7'!K63 -> 0 | H98: ='Subassy 7'!L63 -> 0 | I98: ='Subassy 7'!M63 -> 0
A99: ='Subassy 8'!D63 -> 8 | B99: ='Subassy 8'!F$63 -> 0 | C99: ='Subassy 8'!G$63 -> 0 | D99: ='Subassy 8'!H$63 -> 0 | E99: ='Subassy 8'!I$63 -> 0 | F99: ='Subassy 8'!J$63 -> 0 | G99: ='Subassy 8'!K$63 -> 0 | H99: ='Subassy 8'!L$63 -> 0 | I99: ='Subassy 8'!M$63 -> 0
A100: ='Subassy 9'!D63 -> 9 | B100: ='Subassy 9'!F$63 -> 0 | C100: ='Subassy 9'!G$63 -> 0 | D100: ='Subassy 9'!H$63 -> 0 | E100: ='Subassy 9'!I$63 -> 0 | F100: ='Subassy 9'!J$63 -> 0 | G100: ='Subassy 9'!K$63 -> 0 | H100: ='Subassy 9'!L$63 -> 0 | I100: ='Subassy 9'!M$63 -> 0
A101: ='Subassy 10'!D63 -> 10 | B101: ='Subassy 10'!F$63 -> 0 | C101: ='Subassy 10'!G$63 -> 0 | D101: ='Subassy 10'!H$63 -> 0 | E101: ='Subassy 10'!I$63 -> 0 | F101: ='Subassy 10'!J$63 -> 0 | G101: ='Subassy 10'!K$63 -> 0 | H101: ='Subassy 10'!L$63 -> 0 | I101: ='Subassy 10'!M$63 -> 0
A102: ='Subassy 11'!D63 -> 11 | B102: ='Subassy 11'!F$63 -> 0 | C102: ='Subassy 11'!G$63 -> 0 | D102: ='Subassy 11'!H$63 -> 0 | E102: ='Subassy 11'!I$63 -> 0 | F102: ='Subassy 11'!J$63 -> 0 | G102: ='Subassy 11'!K$63 -> 0 | H102: ='Subassy 11'!L$63 -> 0 | I102: ='Subassy 11'!M$63 -> 0
A103: ='Subassy 12'!D63 -> 12 | B103: ='Subassy 12'!F$63 -> 0 | C103: ='Subassy 12'!G$63 -> 0 | D103: ='Subassy 12'!H$63 -> 0 | E103: ='Subassy 12'!I$63 -> 0 | F103: ='Subassy 12'!J$63 -> 0 | G103: ='Subassy 12'!K$63 -> 0 | H103: ='Subassy 12'!L$63 -> 0 | I103: ='Subassy 12'!M$63 -> 0
A104: Totals | B104: =SUM(B92:B97) -> 0 | C104: =SUM(C92:C97) -> 0 | D104: =SUM(D92:D97) -> 0 | E104: =SUM(E92:E97) -> 0 | F104: =SUM(F92:F97) -> 0 | G104: =SUM(G92:G97) -> 0 | H104: =SUM(H92:H97) -> 0 | I104: =SUM(I92:I97) -> 0
A106: Labor Costs | B106: 10 | C106: 25 | D106: 50 | E106: 100 | F106: 250 | G106: 500 | H106: 750 | I106: 1000
A107: ='Subassy 1'!D63 -> 1 | B107: ='Subassy 1'!F30 -> 0 | C107: ='Subassy 1'!G30 -> 0 | D107: ='Subassy 1'!H30 -> 0 | E107: ='Subassy 1'!I30 -> 0 | F107: ='Subassy 1'!L30 -> 0 | G107: ='Subassy 1'!M30 -> 0 | H107: ='Subassy 1'!N30 -> 0 | I107: ='Subassy 1'!O30 -> 0
A108: ='Subassy 2'!D63 -> 2 | B108: ='Subassy 2'!F30 -> 0 | C108: ='Subassy 2'!G30 -> 0 | D108: ='Subassy 2'!H30 -> 0 | E108: ='Subassy 2'!K30 -> 0 | F108: ='Subassy 2'!L30 -> 0 | G108: ='Subassy 2'!M30 -> 0 | H108: ='Subassy 2'!N30 -> 0 | I108: ='Subassy 2'!O30 -> 0
A109: ='Subassy 3'!D63 -> 3 | B109: ='Subassy 3'!F30 -> 0 | C109: ='Subassy 3'!G30 -> 0 | D109: ='Subassy 3'!H30 -> 0 | E109: ='Subassy 3'!K30 -> 0 | F109: ='Subassy 3'!L30 -> 0 | G109: ='Subassy 3'!M30 -> 0 | H109: ='Subassy 3'!N30 -> 0 | I109: ='Subassy 3'!O30 -> 0
A110: ='Subassy 4'!D63 -> 4 | B110: ='Subassy 4'!F30 -> 0 | C110: ='Subassy 4'!G30 -> 0 | D110: ='Subassy 4'!H30 -> 0 | E110: ='Subassy 4'!I30 -> 0 | F110: ='Subassy 4'!L30 -> 0 | G110: ='Subassy 4'!M30 -> 0 | H110: ='Subassy 4'!N30 -> 0 | I110: ='Subassy 4'!O30 -> 0
A111: ='Subassy 5'!D63 -> 5 | B111: ='Subassy 5'!F30 -> 0 | C111: ='Subassy 5'!G30 -> 0 | D111: ='Subassy 5'!H30 -> 0 | E111: ='Subassy 5'!I30 -> 0 | F111: ='Subassy 5'!L30 -> 0 | G111: ='Subassy 5'!M30 -> 0 | H111: ='Subassy 5'!N30 -> 0 | I111: ='Subassy 5'!O30 -> 0
A112: ='Subassy 6'!D63 -> 6 | B112: ='Subassy 6'!F30 -> 0 | C112: ='Subassy 6'!G30 -> 0 | D112: ='Subassy 6'!H30 -> 0 | E112: ='Subassy 6'!I30 -> 0 | F112: ='Subassy 6'!L30 -> 0 | G112: ='Subassy 6'!M30 -> 0 | H112: ='Subassy 6'!N30 -> 0 | I112: ='Subassy 6'!O30 -> 0
A113: ='Subassy 7'!D63 -> 7 | B113: ='Subassy 7'!F30 -> 0 | C113: ='Subassy 7'!G30 -> 0 | D113: ='Subassy 7'!H30 -> 0 | E113: ='Subassy 7'!I30 -> 0 | F113: ='Subassy 7'!L30 -> 0 | G113: ='Subassy 7'!M30 -> 0 | H113: ='Subassy 7'!N30 -> 0 | I113: ='Subassy 7'!O30 -> 0
A114: ='Subassy 8'!$D$63 -> 8 | B114: ='Subassy 8'!F$30 -> 0 | C114: ='Subassy 8'!G30 -> 0 | D114: ='Subassy 8'!H30 -> 0 | E114: ='Subassy 8'!I30 -> 0 | F114: ='Subassy 8'!L30 -> 0 | G114: ='Subassy 8'!M30 -> 0 | H114: ='Subassy 8'!N30 -> 0 | I114: ='Subassy 8'!O30 -> 0
...

Sheet Subassy 1
A2: CUSTOMER: | F2: Comments:
A3: P/N: | B3: 1 | D3: NSN #:
A4: REV: | D4: SOL #:
A5: QUOTE LOG No.: | D5: RFQ #:
A6: QTY: | B6: =F13&", "&G13&", "&H13&", "&I13&", "&J13&", "&K13&", "&L13&", "&M13 -> 10, 25, 50, 75, 100, 250, 500, 1000
A7: DATE:
A8: ESTIMATOR:
A11: MANUFACTURING OPERATIONS | F11: COST ESTIMATED QUANTITIES | N11: NRE/SET-UP
B13: SET-UP TIME | C13: RUN TIME | E13: LABOR RATE | F13: ='Top Assy'!F13 -> 10 | G13: ='Top Assy'!G13 -> 25 | H13: ='Top Assy'!H13 -> 50 | I13: ='Top Assy'!I13 -> 75 | J13: ='Top Assy'!J13 -> 100 | K13: ='Top Assy'!K13 -> 250 | L13: ='Top Assy'!L13 -> 500 | M13: ='Top Assy'!M13 -> 1000 | N13: 1
A14: Program | E14: 0 | N14: =(($B14/N$13*$E14)+($C14*$E14)) -> 0
A15: Fixtures | E15: 0 | N15: =(($B15/N$13*$E15)+($C15*$E15)) -> 0
A16: Mill/Turn | E16: 0 | F16: =(($B16/F$13*$E16)+($C16*$E16)) -> 0 | G16: =(($B16/G$13*$E16)+($C16*$E16)) -> 0 | H16: =(($B16/H$13*$E16)+($C16*$E16)) -> 0 | I16: =(($B16/I$13*$E16)+($C16*$E16)) -> 0 | J16: =(($B16/J$13*$E16)+($C16*$E16)) -> 0 | K16: =(($B16/K$13*$E16)+($C16*$E16)) -> 0 | L16: =(($B16/L$13*$E16)+($C16*$E16)) -> 0 | M16: =(($B16/M$13*$E16)+($C16*$E16)) -> 0
A17: Metals - Mills | E17: 0 | F17: =(($B17/F$13*$E17)+($C17*$E17)) -> 0 | G17: =(($B17/G$13*$E17)+($C17*$E17)) -> 0 | H17: =(($B17/H$13*$E17)+($C17*$E17)) -> 0 | I17: =(($B17/I$13*$E17)+($C17*$E17)) -> 0 | J17: =(($B17/J$13*$E17)+($C17*$E17)) -> 0 | K17: =(($B17/K$13*$E17)+($C17*$E17)) -> 0 | L17: =(($B17/L$13*$E17)+($C17*$E17)) -> 0 | M17: =(($B17/M$13*$E17)+($C17*$E17)) -> 0
A18: Metals - Lathe | E18: 0 | F18: =(($B18/F$13*$E18)+($C18*$E18)) -> 0 | G18: =(($B18/G$13*$E18)+($C18*$E18)) -> 0 | H18: =(($B18/H$13*$E18)+($C18*$E18)) -> 0 | I18: =(($B18/I$13*$E18)+($C18*$E18)) -> 0 | J18: =(($B18/J$13*$E18)+($C18*$E18)) -> 0 | K18: =(($B18/K$13*$E18)+($C18*$E18)) -> 0 | L18: =(($B18/L$13*$E18)+($C18*$E18)) -> 0 | M18: =(($B18/M$13*$E18)+($C18*$E18)) -> 0
A19: Rubber Mold | E19: 0 | F19: =(($B19/F$13*$E19)+($C19*$E19)) -> 0 | G19: =(($B19/G$13*$E19)+($C19*$E19)) -> 0 | H19: =(($B19/H$13*$E19)+($C19*$E19)) -> 0 | I19: =(($B19/I$13*$E19)+($C19*$E19)) -> 0 | J19: =(($B19/J$13*$E19)+($C19*$E19)) -> 0 | K19: =(($B19/K$13*$E19)+($C19*$E19)) -> 0 | L19: =(($B19/L$13*$E19)+($C19*$E19)) -> 0 | M19: =(($B19/M$13*$E19)+($C19*$E19)) -> 0
A20: Plastic Injection Mold | E20: 0 | F20: =(($B20/F$13*$E20)+($C20*$E20)) -> 0 | G20: =(($B20/G$13*$E20)+($C20*$E20)) -> 0 | H20: =(($B20/H$13*$E20)+($C20*$E20)) -> 0 | I20: =(($B20/I$13*$E20)+($C20*$E20)) -> 0 | J20: =(($B20/J$13*$E20)+($C20*$E20)) -> 0 | K20: =(($B20/K$13*$E20)+($C20*$E20)) -> 0 | L20: =(($B20/L$13*$E20)+($C20*$E20)) -> 0 | M20: =(($B20/M$13*$E20)+($C20*$E20)) -> 0
A21: Plastic Compression Mold | E21: 0 | F21: =(($B21/F$13*$E21)+($C21*$E21)) -> 0 | G21: =(($B21/G$13*$E21)+($C21*$E21)) -> 0 | H21: =(($B21/H$13*$E21)+($C21*$E21)) -> 0 | I21: =(($B21/I$13*$E21)+($C21*$E21)) -> 0 | J21: =(($B21/J$13*$E21)+($C21*$E21)) -> 0 | K21: =(($B21/K$13*$E21)+($C21*$E21)) -> 0 | L21: =(($B21/L$13*$E21)+($C21*$E21)) -> 0 | M21: =(($B21/M$13*$E21)+($C21*$E21)) -> 0
A22: Waterjet - Setup | E22: 0 | F22: =(($B22/F$13*$E22)+($C22*$E22)) -> 0 | G22: =(($B22/G$13*$E22)+($C22*$E22)) -> 0 | H22: =(($B22/H$13*$E22)+($C22*$E22)) -> 0 | I22: =(($B22/I$13*$E22)+($C22*$E22)) -> 0 | J22: =(($B22/J$13*$E22)+($C22*$E22)) -> 0 | K22: =(($B22/K$13*$E22)+($C22*$E22)) -> 0 | L22: =(($B22/L$13*$E22)+($C22*$E22)) -> 0 | M22: =(($B22/M$13*$E22)+($C22*$E22)) -> 0
A23: Waterjet - Operator | E23: 0 | F23: =(($B23/F$13*$E23)+($C23*$E23)) -> 0 | G23: =(($B23/G$13*$E23)+($C23*$E23)) -> 0 | H23: =(($B23/H$13*$E23)+($C23*$E23)) -> 0 | I23: =(($B23/I$13*$E23)+($C23*$E23)) -> 0 | J23: =(($B23/J$13*$E23)+($C23*$E23)) -> 0 | K23: =(($B23/K$13*$E23)+($C23*$E23)) -> 0 | L23: =(($B23/L$13*$E23)+($C23*$E23)) -> 0 | M23: =(($B23/M$13*$E23)+($C23*$E23)) -> 0
A24: Assembly, Die Punch, Deburr | E24: 0 | F24: =(($B24/F$13*$E24)+($C24*$E24)) -> 0 | G24: =(($B24/G$13*$E24)+($C24*$E24)) -> 0 | H24: =(($B24/H$13*$E24)+($C24*$E24)) -> 0 | I24: =(($B24/I$13*$E24)+($C24*$E24)) -> 0 | J24: =(($B24/J$13*$E24)+($C24*$E24)) -> 0 | K24: =(($B24/K$13*$E24)+($C24*$E24)) -> 0 | L24: =(($B24/L$13*$E24)+($C24*$E24)) -> 0 | M24: =(($B24/M$13*$E24)+($C24*$E24)) -> 0
A25: Quality Inspection | E25: 0 | F25: =(($B25/F$13*$E25)+($C25*$E25)) -> 0 | G25: =(($B25/G$13*$E25)+($C25*$E25)) -> 0 | H25: =(($B25/H$13*$E25)+($C25*$E25)) -> 0 | I25: =(($B25/I$13*$E25)+($C25*$E25)) -> 0 | J25: =(($B25/J$13*$E25)+($C25*$E25)) -> 0 | K25: =(($B25/K$13*$E25)+($C25*$E25)) -> 0 | L25: =(($B25/L$13*$E25)+($C25*$E25)) -> 0 | M25: =(($B25/M$13*$E25)+($C25*$E25)) -> 0
C26: Labor | E26: Basic LABOR | F26: =SUM(F16:F25) -> 0 | G26: =SUM(G16:G25) -> 0 | H26: =SUM(H16:H25) -> 0 | I26: =SUM(I16:I25) -> 0 | J26: =SUM(J16:J25) -> 0 | K26: =SUM(K16:K25) -> 0 | L26: =SUM(L16:L25) -> 0 | M26: =SUM(M16:M25) -> 0 | N26: =SUM(N14:N25) -> 0
B27: T. setup | C27: T.RUN | E27: hrs | F27: =(($B$28/F13)+$C$28)/60 -> 0 | G27: =(($B$28/G13)+$C$28)/60 -> 0 | H27: =(($B$28/H13)+$C$28)/60 -> 0 | I27: =(($B$28/I13)+$C$28)/60 -> 0 | J27: =(($B$28/J13)+$C$28)/60 -> 0 | K27: =(($B$28/K13)+$C$28)/60 -> 0 | L27: =(($B$28/L13)+$C$28)/60 -> 0 | M27: =(($B$28/M13)+$C$28)/60 -> 0
B28: =SUM(B16:B25) -> 0 | C28: =SUM(C16:C25) -> 0 | D28: 0 | E28: BURDEN | F28: =F26*$D$28 -> 0 | G28: =G26*$D$28 -> 0 | H28: =H26*$D$28 -> 0 | I28: =I26*$D$28 -> 0 | J28: =J26*$D$28 -> 0 | K28: =K26*$D$28 -> 0 | L28: =L26*$D$28 -> 0 | M28: =M26*$D$28 -> 0
E30: Total | F30: =F26+F28 -> 0 | G30: =G26+G28 -> 0 | H30: =H26+H28 -> 0 | I30: =I26+I28 -> 0 | J30: =J26+J28 -> 0 | K30: =K26+K28 -> 0 | L30: =L26+L28 -> 0 | M30: =M26+M28 -> 0 | N30: =N26 -> 0
A32: RAW MATERIALS & HARDWARE | B32: Matl UoM | C32: PARTS QTY | D32: UNIT PRICE | E32: MAT'l BURDEN | F32: ="Qty: "& F13 -> Qty: 10 | G32: ="Qty: "& G13 -> Qty: 25 | H32: ="Qty: "& H13 -> Qty: 50 | I32: ="Qty: "& I13 -> Qty: 75 | J32: ="Qty: "& J13 -> Qty: 100 | K32: ="Qty: "& K13 -> Qty: 250 | L32: ="Qty: "& L13 -> Qty: 500 | M32: ="Qty: "& M13 -> Qty: 1000 | N32: Amortize/ Min Buy
E33: =C33*D33 -> 0 | F33: =IF($N33=TRUE,$E33/F$13,$E33*(1+(1/F$13))) -> 0 | G33: =IF($N33=TRUE,$E33/G$13,$E33*(1+(1/G$13))) -> 0 | H33: =IF($N33=TRUE,$E33/H$13,$E33*(1+(1/H$13))) -> 0 | I33: =IF($N33=TRUE,$E33/I$13,$E33*(1+(1/I$13))) -> 0 | J33: =IF($N33=TRUE,$E33/J$13,$E33*(1+(1/J$13))) -> 0 | K33: =IF($N33=TRUE,$E33/K$13,$E33*(1+(1/K$13))) -> 0 | L33: =IF($N33=TRUE,$E33/L$13,$E33*(1+(1/L$13))) -> 0 | M33: =IF($N33=TRUE,$E33/M$13,$E33*(1+(1/M$13))) -> 0 | N33: FALSE
E34: =C34*D34 -> 0 | F34: =IF($N34=TRUE,$E34/F$13,$E34*(1+(1/F$13))) -> 0 | G34: =IF($N34=TRUE,$E34/G$13,$E34*(1+(1/G$13))) -> 0 | H34: =IF($N34=TRUE,$E34/H$13,$E34*(1+(1/H$13))) -> 0 | I34: =IF($N34=TRUE,$E34/I$13,$E34*(1+(1/I$13))) -> 0 | J34: =IF($N34=TRUE,$E34/J$13,$E34*(1+(1/J$13))) -> 0 | K34: =IF($N34=TRUE,$E34/K$13,$E34*(1+(1/K$13))) -> 0 | L34: =IF($N34=TRUE,$E34/L$13,$E34*(1+(1/L$13))) -> 0 | M34: =IF($N34=TRUE,$E34/M$13,$E34*(1+(1/M$13))) -> 0 | N34: FALSE
E35: =C35*D35 -> 0 | F35: =IF($N35=TRUE,$E35/F$13,$E35*(1+(1/F$13))) -> 0 | G35: =IF($N35=TRUE,$E35/G$13,$E35*(1+(1/G$13))) -> 0 | H35: =IF($N35=TRUE,$E35/H$13,$E35*(1+(1/H$13))) -> 0 | I35: =IF($N35=TRUE,$E35/I$13,$E35*(1+(1/I$13))) -> 0 | J35: =IF($N35=TRUE,$E35/J$13,$E35*(1+(1/J$13))) -> 0 | K35: =IF($N35=TRUE,$E35/K$13,$E35*(1+(1/K$13))) -> 0 | L35: =IF($N35=TRUE,$E35/L$13,$E35*(1+(1/L$13))) -> 0 | M35: =IF($N35=TRUE,$E35/M$13,$E35*(1+(1/M$13))) -> 0 | N35: FALSE | S35: QTY | T35: Total
E36: =C36*D36 -> 0 | F36: =IF($N36=TRUE,$E36/F$13,$E36*(1+(1/F$13))) -> 0 | G36: =IF($N36=TRUE,$E36/G$13,$E36*(1+(1/G$13))) -> 0 | H36: =IF($N36=TRUE,$E36/H$13,$E36*(1+(1/H$13))) -> 0 | I36: =IF($N36=TRUE,$E36/I$13,$E36*(1+(1/I$13))) -> 0 | J36: =IF($N36=TRUE,$E36/J$13,$E36*(1+(1/J$13))) -> 0 | K36: =IF($N36=TRUE,$E36/K$13,$E36*(1+(1/K$13))) -> 0 | L36: =IF($N36=TRUE,$E36/L$13,$E36*(1+(1/L$13))) -> 0 | M36: =IF($N36=TRUE,$E36/M$13,$E36*(1+(1/M$13))) -> 0 | N36: FALSE | S36: =M13 -> 1000 | T36: =M63 -> 0
E37: =C37*D37 -> 0 | F37: =IF($N37=TRUE,$E37/F$13,$E37*(1+(1/F$13))) -> 0 | G37: =IF($N37=TRUE,$E37/G$13,$E37*(1+(1/G$13))) -> 0 | H37: =IF($N37=TRUE,$E37/H$13,$E37*(1+(1/H$13))) -> 0 | I37: =IF($N37=TRUE,$E37/I$13,$E37*(1+(1/I$13))) -> 0 | J37: =IF($N37=TRUE,$E37/J$13,$E37*(1+(1/J$13))) -> 0 | K37: =IF($N37=TRUE,$E37/K$13,$E37*(1+(1/K$13))) -> 0 | L37: =IF($N37=TRUE,$E37/L$13,$E37*(1+(1/L$13))) -> 0 | M37: =IF($N37=TRUE,$E37/M$13,$E37*(1+(1/M$13))) -> 0 | N37: FALSE | S37: =L13 -> 500 | T37: =L63 -> 0
E38: =C38*D38 -> 0 | F38: =IF($N38=TRUE,$E38/F$13,$E38*(1+(1/F$13))) -> 0 | G38: =IF($N38=TRUE,$E38/G$13,$E38*(1+(1/G$13))) -> 0 | H38: =IF($N38=TRUE,$E38/H$13,$E38*(1+(1/H$13))) -> 0 | I38: =IF($N38=TRUE,$E38/I$13,$E38*(1+(1/I$13))) -> 0 | J38: =IF($N38=TRUE,$E38/J$13,$E38*(1+(1/J$13))) -> 0 | K38: =IF($N38=TRUE,$E38/K$13,$E38*(1+(1/K$13))) -> 0 | L38: =IF($N38=TRUE,$E38/L$13,$E38*(1+(1/L$13))) -> 0 | M38: =IF($N38=TRUE,$E38/M$13,$E38*(1+(1/M$13))) -> 0 | N38: FALSE | S38: =I13 -> 75 | T38: =I63 -> 0
E39: =C39*D39 -> 0 | F39: =IF($N39=TRUE,$E39/F$13,$E39*(1+(1/F$13))) -> 0 | G39: =IF($N39=TRUE,$E39/G$13,$E39*(1+(1/G$13))) -> 0 | H39: =IF($N39=TRUE,$E39/H$13,$E39*(1+(1/H$13))) -> 0 | I39: =IF($N39=TRUE,$E39/I$13,$E39*(1+(1/I$13))) -> 0 | J39: =IF($N39=TRUE,$E39/J$13,$E39*(1+(1/J$13))) -> 0 | K39: =IF($N39=TRUE,$E39/K$13,$E39*(1+(1/K$13))) -> 0 | L39: =IF($N39=TRUE,$E39/L$13,$E39*(1+(1/L$13))) -> 0 | M39: =IF($N39=TRUE,$E39/M$13,$E39*(1+(1/M$13))) -> 0 | S39: =H13 -> 50 | T39: =H63 -> 0
E40: =C40*D40 -> 0 | F40: =IF($N40=TRUE,$E40/F$13,$E40*(1+(1/F$13))) -> 0 | G40: =IF($N40=TRUE,$E40/G$13,$E40*(1+(1/G$13))) -> 0 | H40: =IF($N40=TRUE,$E40/H$13,$E40*(1+(1/H$13))) -> 0 | I40: =IF($N40=TRUE,$E40/I$13,$E40*(1+(1/I$13))) -> 0 | J40: =IF($N40=TRUE,$E40/J$13,$E40*(1+(1/J$13))) -> 0 | K40: =IF($N40=TRUE,$E40/K$13,$E40*(1+(1/K$13))) -> 0 | L40: =IF($N40=TRUE,$E40/L$13,$E40*(1+(1/L$13))) -> 0 | M40: =IF($N40=TRUE,$E40/M$13,$E40*(1+(1/M$13))) -> 0 | N40: FALSE | S40: =G13 -> 25 | T40: =G63 -> 0
E41: =C41*D41 -> 0 | F41: =IF($N41=TRUE,$E41/F$13,$E41*(1+(1/F$13))) -> 0 | G41: =IF($N41=TRUE,$E41/G$13,$E41*(1+(1/G$13))) -> 0 | H41: =IF($N41=TRUE,$E41/H$13,$E41*(1+(1/H$13))) -> 0 | I41: =IF($N41=TRUE,$E41/I$13,$E41*(1+(1/I$13))) -> 0 | J41: =IF($N41=TRUE,$E41/J$13,$E41*(1+(1/J$13))) -> 0 | K41: =IF($N41=TRUE,$E41/K$13,$E41*(1+(1/K$13))) -> 0 | L41: =IF($N41=TRUE,$E41/L$13,$E41*(1+(1/L$13))) -> 0 | M41: =IF($N41=TRUE,$E41/M$13,$E41*(1+(1/M$13))) -> 0 | N41: FALSE | S41: =F13 -> 10 | T41: =F63 -> 0
E42: =C42*D42 -> 0 | F42: =IF($N42=TRUE,$E42/F$13,$E42*(1+(1/F$13))) -> 0 | G42: =IF($N42=TRUE,$E42/G$13,$E42*(1+(1/G$13))) -> 0 | H42: =IF($N42=TRUE,$E42/H$13,$E42*(1+(1/H$13))) -> 0 | I42: =IF($N42=TRUE,$E42/I$13,$E42*(1+(1/I$13))) -> 0 | J42: =IF($N42=TRUE,$E42/J$13,$E42*(1+(1/J$13))) -> 0 | K42: =IF($N42=TRUE,$E42/K$13,$E42*(1+(1/K$13))) -> 0 | L42: =IF($N42=TRUE,$E42/L$13,$E42*(1+(1/L$13))) -> 0 | M42: =IF($N42=TRUE,$E42/M$13,$E42*(1+(1/M$13))) -> 0 | N42: FALSE
E43: =C43*D43 -> 0 | F43: =IF($N43=TRUE,$E43/F$13,$E43*(1+(1/F$13))) -> 0 | G43: =IF($N43=TRUE,$E43/G$13,$E43*(1+(1/G$13))) -> 0 | H43: =IF($N43=TRUE,$E43/H$13,$E43*(1+(1/H$13))) -> 0 | I43: =IF($N43=TRUE,$E43/I$13,$E43*(1+(1/I$13))) -> 0 | J43: =IF($N43=TRUE,$E43/J$13,$E43*(1+(1/J$13))) -> 0 | K43: =IF($N43=TRUE,$E43/K$13,$E43*(1+(1/K$13))) -> 0 | L43: =IF($N43=TRUE,$E43/L$13,$E43*(1+(1/L$13))) -> 0 | M43: =IF($N43=TRUE,$E43/M$13,$E43*(1+(1/M$13))) -> 0 | N43: FALSE
E44: =C44*D44 -> 0 | F44: =IF($N44=TRUE,$E44/F$13,$E44*(1+(1/F$13))) -> 0 | G44: =IF($N44=TRUE,$E44/G$13,$E44*(1+(1/G$13))) -> 0 | H44: =IF($N44=TRUE,$E44/H$13,$E44*(1+(1/H$13))) -> 0 | I44: =IF($N44=TRUE,$E44/I$13,$E44*(1+(1/I$13))) -> 0 | J44: =IF($N44=TRUE,$E44/J$13,$E44*(1+(1/J$13))) -> 0 | K44: =IF($N44=TRUE,$E44/K$13,$E44*(1+(1/K$13))) -> 0 | L44: =IF($N44=TRUE,$E44/L$13,$E44*(1+(1/L$13))) -> 0 | M44: =IF($N44=TRUE,$E44/M$13,$E44*(1+(1/M$13))) -> 0 | N44: FALSE
A45: PROCESSES/COMPONENTS | D45: SETUP $ | E45: RUN$ EA.
F46: =($D46/F$13)+$E46 -> 0 | G46: =($D46/G$13)+$E46 -> 0 | H46: =($D46/H$13)+$E46 -> 0 | I46: =($D46/I$13)+$E46 -> 0 | J46: =($D46/J$13)+$E46 -> 0 | K46: =($D46/K$13)+$E46 -> 0 | L46: =($D46/L$13)+$E46 -> 0 | M46: =($D46/M$13)+$E46 -> 0
F47: =($D47/F$13)+$E47 -> 0 | G47: =($D47/G$13)+$E47 -> 0 | H47: =($D47/H$13)+$E47 -> 0 | I47: =($D47/I$13)+$E47 -> 0 | J47: =($D47/J$13)+$E47 -> 0 | K47: =($D47/K$13)+$E47 -> 0 | L47: =($D47/L$13)+$E47 -> 0 | M47: =($D47/M$13)+$E47 -> 0
F48: =($D48/F$13)+$E48 -> 0 | G48: =($D48/G$13)+$E48 -> 0 | H48: =($D48/H$13)+$E48 -> 0 | I48: =($D48/I$13)+$E48 -> 0 | J48: =($D48/J$13)+$E48 -> 0 | K48: =($D48/K$13)+$E48 -> 0 | L48: =($D48/L$13)+$E48 -> 0 | M48: =($D48/M$13)+$E48 -> 0
F49: =($D49/F$13)+$E49 -> 0 | G49: =($D49/G$13)+$E49 -> 0 | H49: =($D49/H$13)+$E49 -> 0 | I49: =($D49/I$13)+$E49 -> 0 | J49: =($D49/J$13)+$E49 -> 0 | K49: =($D49/K$13)+$E49 -> 0 | L49: =($D49/L$13)+$E49 -> 0 | M49: =($D49/M$13)+$E49 -> 0
F50: =($D50/F$13)+$E50 -> 0 | G50: =($D50/G$13)+$E50 -> 0 | H50: =($D50/H$13)+$E50 -> 0 | I50: =($D50/I$13)+$E50 -> 0 | J50: =($D50/J$13)+$E50 -> 0 | K50: =($D50/K$13)+$E50 -> 0 | L50: =($D50/L$13)+$E50 -> 0 | M50: =($D50/M$13)+$E50 -> 0
B51: MATERIAL & HARDWARE TOTAL | F51: =SUM(F33:F44) -> 0 | G51: =SUM(G33:G44) -> 0 | H51: =SUM(H33:H44) -> 0 | I51: =SUM(I33:I44) -> 0 | J51: =SUM(J33:J44) -> 0 | K51: =SUM(K33:K44) -> 0 | L51: =SUM(L33:L44) -> 0 | M51: =SUM(M33:M44) -> 0 | N51: =IF(N13=0,0,SUM(N42:N44)) -> 0
B52: PROCESSES TOTAL | F52: =SUM(F46:F50) -> 0 | G52: =SUM(G46:G50) -> 0 | H52: =SUM(H46:H50) -> 0 | I52: =SUM(I46:I50) -> 0 | J52: =SUM(J46:J50) -> 0 | K52: =SUM(K46:K50) -> 0 | L52: =SUM(L46:L50) -> 0 | M52: =SUM(M46:M50) -> 0 | N52: =IF(N13=0,0,SUM(N46:N50)) -> 0
B53: M+L Subtotal | F53: =SUM(F30+F51+F52) -> 0 | G53: =SUM(G30+G51+G52) -> 0 | H53: =SUM(H30+H51+H52) -> 0 | I53: =SUM(I30+I51+I52) -> 0 | J53: =SUM(J30+J51+J52) -> 0 | K53: =SUM(K30+K51+K52) -> 0 | L53: =SUM(L30+L51+L52) -> 0 | M53: =SUM(M30+M51+M52) -> 0 | N53: =IF(N13=0,0,SUM(N30+N51+N52)) -> 0
E55: REFERENCE | F55: =SUM(F53+#REF!+#REF!) -> #REF! | G55: =SUM(G53+#REF!+#REF!) -> #REF! | H55: =SUM(H53+#REF!+#REF!) -> #REF! | I55: =SUM(I53+#REF!+#REF!) -> #REF! | J55: =SUM(J53+#REF!+#REF!) -> #REF! | K55: =SUM(K53+#REF!+#REF!) -> #REF! | L55: =SUM(L53+#REF!+#REF!) -> #REF! | M55: =SUM(M53+#REF!+#REF!) -> #REF! | N55: =SUM(N53+#REF!+#REF!) -> #REF!
D56: MARGIN | F56: =(F55-F53)/F55 -> #REF! | G56: =(G55-G53)/G55 -> #REF! | H56: =(H55-H53)/H55 -> #REF! | I56: =(I55-I53)/I55 -> #REF! | J56: =(J55-J53)/J55 -> #REF! | K56: =(K55-K53)/K55 -> #REF! | L56: =(L55-L53)/L55 -> #REF! | M56: =(M55-M53)/M55 -> #REF!
D57: LABOR | F57: =F30 -> 0 | G57: =G30 -> 0 | H57: =H30 -> 0 | I57: =I30 -> 0 | J57: =J30 -> 0 | K57: =K30 -> 0 | L57: =L30 -> 0 | M57: =M30 -> 0 | N57: =SUM((N30)) -> 0
C58: MAT'ls &HARDWARE | F58: =F51 -> 0 | G58: =G51 -> 0 | H58: =H51 -> 0 | I58: =I51 -> 0 | J58: =J51 -> 0 | K58: =K51 -> 0 | L58: =L51 -> 0 | M58: =M51 -> 0 | N58: =(N51) -> 0
D59: PROCESS | F59: =F52 -> 0 | G59: =G52 -> 0 | H59: =H52 -> 0 | I59: =I52 -> 0 | J59: =J52 -> 0 | K59: =K52 -> 0 | L59: =L52 -> 0 | M59: =M52 -> 0 | N59: =N52 -> 0
D60: Subtotal | F60: =SUM(F57:F59) -> 0 | G60: =SUM(G57:G59) -> 0 | H60: =SUM(H57:H59) -> 0 | I60: =SUM(I57:I59) -> 0 | J60: =SUM(J57:J59) -> 0 | K60: =SUM(K57:K59) -> 0 | L60: =SUM(L57:L59) -> 0 | M60: =SUM(M57:M59) -> 0 | N60: =SUM(N57:N59) -> 0
D61: AMORTIZED | F61: =$N$60/F13 -> 0 | G61: =$N$60/G13 -> 0 | H61: =$N$60/H13 -> 0 | I61: =$N$60/I13 -> 0 | J61: =$N$60/J13 -> 0 | K61: =$N$60/K13 -> 0 | L61: =$N$60/L13 -> 0 | M61: =$N$60/M13 -> 0
D62: Facilities | F62: 0 | G62: 0 | H62: 0 | I62: 0 | J62: 0 | K62: 0 | L62: 0 | M62: 0
D63: =B3 -> 1 | F63: =SUM(F60:F62) -> 0 | G63: =SUM(G60:G62) -> 0 | H63: =SUM(H60:H62) -> 0 | I63: =SUM(I60:I62) -> 0 | J63: =SUM(J60:J62) -> 0 | K63: =SUM(K60:K62) -> 0 | L63: =SUM(L60:L62) -> 0 | M63: =SUM(M60:M62) -> 0
A66: NRESC/TOOLING
A67: SETUPS
A68: FAIR
A69: SOURCE

Sheet Subassy 2
A2: CUSTOMER: | F2: Comments:
A3: P/N: | B3: 2 | D3: NSN #:
A4: REV: | D4: SOL #:
A5: QUOTE LOG No.: | D5: RFQ #:
A6: QTY: | B6: =F13&", "&G13&", "&H13&", "&I13&", "&J13&", "&K13&", "&L13&", "&M13 -> 10, 25, 50, 75, 100, 250, 500, 1000
A7: DATE:
A8: ESTIMATOR:
A11: MANUFACTURING OPERATIONS | F11: COST ESTIMATED QUANTITIES | N11: NRE/SET-UP
B13: SET-UP TIME | C13: RUN TIME | E13: LABOR RATE | F13: ='Top Assy'!F13 -> 10 | G13: ='Top Assy'!G13 -> 25 | H13: ='Top Assy'!H13 -> 50 | I13: ='Top Assy'!I13 -> 75 | J13: ='Top Assy'!J13 -> 100 | K13: ='Top Assy'!K13 -> 250 | L13: ='Top Assy'!L13 -> 500 | M13: ='Top Assy'!M13 -> 1000 | N13: 1
A14: Program | E14: 0 | N14: =(($B14/N$13*$E14)+($C14*$E14)) -> 0
A15: Fixtures | E15: 0 | N15: =(($B15/N$13*$E15)+($C15*$E15)) -> 0
A16: Mill/Turn | E16: 0 | F16: =(($B16/F$13*$E16)+($C16*$E16)) -> 0 | G16: =(($B16/G$13*$E16)+($C16*$E16)) -> 0 | H16: =(($B16/H$13*$E16)+($C16*$E16)) -> 0 | I16: =(($B16/I$13*$E16)+($C16*$E16)) -> 0 | J16: =(($B16/J$13*$E16)+($C16*$E16)) -> 0 | K16: =(($B16/K$13*$E16)+($C16*$E16)) -> 0 | L16: =(($B16/L$13*$E16)+($C16*$E16)) -> 0 | M16: =(($B16/M$13*$E16)+($C16*$E16)) -> 0
A17: Metals - Mills | E17: 0 | F17: =(($B17/F$13*$E17)+($C17*$E17)) -> 0 | G17: =(($B17/G$13*$E17)+($C17*$E17)) -> 0 | H17: =(($B17/H$13*$E17)+($C17*$E17)) -> 0 | I17: =(($B17/I$13*$E17)+($C17*$E17)) -> 0 | J17: =(($B17/J$13*$E17)+($C17*$E17)) -> 0 | K17: =(($B17/K$13*$E17)+($C17*$E17)) -> 0 | L17: =(($B17/L$13*$E17)+($C17*$E17)) -> 0 | M17: =(($B17/M$13*$E17)+($C17*$E17)) -> 0
A18: Metals - Lathe | E18: 0 | F18: =(($B18/F$13*$E18)+($C18*$E18)) -> 0 | G18: =(($B18/G$13*$E18)+($C18*$E18)) -> 0 | H18: =(($B18/H$13*$E18)+($C18*$E18)) -> 0 | I18: =(($B18/I$13*$E18)+($C18*$E18)) -> 0 | J18: =(($B18/J$13*$E18)+($C18*$E18)) -> 0 | K18: =(($B18/K$13*$E18)+($C18*$E18)) -> 0 | L18: =(($B18/L$13*$E18)+($C18*$E18)) -> 0 | M18: =(($B18/M$13*$E18)+($C18*$E18)) -> 0
A19: Rubber Mold | E19: 0 | F19: =(($B19/F$13*$E19)+($C19*$E19)) -> 0 | G19: =(($B19/G$13*$E19)+($C19*$E19)) -> 0 | H19: =(($B19/H$13*$E19)+($C19*$E19)) -> 0 | I19: =(($B19/I$13*$E19)+($C19*$E19)) -> 0 | J19: =(($B19/J$13*$E19)+($C19*$E19)) -> 0 | K19: =(($B19/K$13*$E19)+($C19*$E19)) -> 0 | L19: =(($B19/L$13*$E19)+($C19*$E19)) -> 0 | M19: =(($B19/M$13*$E19)+($C19*$E19)) -> 0
A20: Plastic Injection Mold | E20: 0 | F20: =(($B20/F$13*$E20)+($C20*$E20)) -> 0 | G20: =(($B20/G$13*$E20)+($C20*$E20)) -> 0 | H20: =(($B20/H$13*$E20)+($C20*$E20)) -> 0 | I20: =(($B20/I$13*$E20)+($C20*$E20)) -> 0 | J20: =(($B20/J$13*$E20)+($C20*$E20)) -> 0 | K20: =(($B20/K$13*$E20)+($C20*$E20)) -> 0 | L20: =(($B20/L$13*$E20)+($C20*$E20)) -> 0 | M20: =(($B20/M$13*$E20)+($C20*$E20)) -> 0
A21: Plastic Compression Mold | E21: 0 | F21: =(($B21/F$13*$E21)+($C21*$E21)) -> 0 | G21: =(($B21/G$13*$E21)+($C21*$E21)) -> 0 | H21: =(($B21/H$13*$E21)+($C21*$E21)) -> 0 | I21: =(($B21/I$13*$E21)+($C21*$E21)) -> 0 | J21: =(($B21/J$13*$E21)+($C21*$E21)) -> 0 | K21: =(($B21/K$13*$E21)+($C21*$E21)) -> 0 | L21: =(($B21/L$13*$E21)+($C21*$E21)) -> 0 | M21: =(($B21/M$13*$E21)+($C21*$E21)) -> 0
A22: Waterjet - Setup | E22: 0 | F22: =(($B22/F$13*$E22)+($C22*$E22)) -> 0 | G22: =(($B22/G$13*$E22)+($C22*$E22)) -> 0 | H22: =(($B22/H$13*$E22)+($C22*$E22)) -> 0 | I22: =(($B22/I$13*$E22)+($C22*$E22)) -> 0 | J22: =(($B22/J$13*$E22)+($C22*$E22)) -> 0 | K22: =(($B22/K$13*$E22)+($C22*$E22)) -> 0 | L22: =(($B22/L$13*$E22)+($C22*$E22)) -> 0 | M22: =(($B22/M$13*$E22)+($C22*$E22)) -> 0
A23: Waterjet - Operator | E23: 0 | F23: =(($B23/F$13*$E23)+($C23*$E23)) -> 0 | G23: =(($B23/G$13*$E23)+($C23*$E23)) -> 0 | H23: =(($B23/H$13*$E23)+($C23*$E23)) -> 0 | I23: =(($B23/I$13*$E23)+($C23*$E23)) -> 0 | J23: =(($B23/J$13*$E23)+($C23*$E23)) -> 0 | K23: =(($B23/K$13*$E23)+($C23*$E23)) -> 0 | L23: =(($B23/L$13*$E23)+($C23*$E23)) -> 0 | M23: =(($B23/M$13*$E23)+($C23*$E23)) -> 0
A24: Assembly, Die Punch, Deburr | E24: 0 | F24: =(($B24/F$13*$E24)+($C24*$E24)) -> 0 | G24: =(($B24/G$13*$E24)+($C24*$E24)) -> 0 | H24: =(($B24/H$13*$E24)+($C24*$E24)) -> 0 | I24: =(($B24/I$13*$E24)+($C24*$E24)) -> 0 | J24: =(($B24/J$13*$E24)+($C24*$E24)) -> 0 | K24: =(($B24/K$13*$E24)+($C24*$E24)) -> 0 | L24: =(($B24/L$13*$E24)+($C24*$E24)) -> 0 | M24: =(($B24/M$13*$E24)+($C24*$E24)) -> 0
A25: Quality Inspection | E25: 0 | F25: =(($B25/F$13*$E25)+($C25*$E25)) -> 0 | G25: =(($B25/G$13*$E25)+($C25*$E25)) -> 0 | H25: =(($B25/H$13*$E25)+($C25*$E25)) -> 0 | I25: =(($B25/I$13*$E25)+($C25*$E25)) -> 0 | J25: =(($B25/J$13*$E25)+($C25*$E25)) -> 0 | K25: =(($B25/K$13*$E25)+($C25*$E25)) -> 0 | L25: =(($B25/L$13*$E25)+($C25*$E25)) -> 0 | M25: =(($B25/M$13*$E25)+($C25*$E25)) -> 0
C26: Labor | E26: Basic LABOR | F26: =SUM(F16:F25) -> 0 | G26: =SUM(G16:G25) -> 0 | H26: =SUM(H16:H25) -> 0 | I26: =SUM(I16:I25) -> 0 | J26: =SUM(J16:J25) -> 0 | K26: =SUM(K16:K25) -> 0 | L26: =SUM(L16:L25) -> 0 | M26: =SUM(M16:M25) -> 0 | N26: =SUM(N14:N25) -> 0
B27: T. setup | C27: T.RUN | E27: hrs | F27: =(($B$28/F13)+$C$28)/60 -> 0 | G27: =(($B$28/G13)+$C$28)/60 -> 0 | H27: =(($B$28/H13)+$C$28)/60 -> 0 | I27: =(($B$28/I13)+$C$28)/60 -> 0 | J27: =(($B$28/J13)+$C$28)/60 -> 0 | K27: =(($B$28/K13)+$C$28)/60 -> 0 | L27: =(($B$28/L13)+$C$28)/60 -> 0 | M27: =(($B$28/M13)+$C$28)/60 -> 0
B28: =SUM(B16:B25) -> 0 | C28: =SUM(C16:C25) -> 0 | D28: 0 | E28: BURDEN | F28: =F26*$D$28 -> 0 | G28: =G26*$D$28 -> 0 | H28: =H26*$D$28 -> 0 | I28: =I26*$D$28 -> 0 | J28: =J26*$D$28 -> 0 | K28: =K26*$D$28 -> 0 | L28: =L26*$D$28 -> 0 | M28: =M26*$D$28 -> 0
E30: Total | F30: =F26+F28 -> 0 | G30: =G26+G28 -> 0 | H30: =H26+H28 -> 0 | I30: =I26+I28 -> 0 | J30: =J26+J28 -> 0 | K30: =K26+K28 -> 0 | L30: =L26+L28 -> 0 | M30: =M26+M28 -> 0 | N30: =N26 -> 0
A32: RAW MATERIALS & HARDWARE | B32: Matl UoM | C32: PARTS QTY | D32: UNIT PRICE | E32: MAT'l BURDEN | F32: ="Qty: "& F13 -> Qty: 10 | G32: ="Qty: "& G13 -> Qty: 25 | H32: ="Qty: "& H13 -> Qty: 50 | I32: ="Qty: "& I13 -> Qty: 75 | J32: ="Qty: "& J13 -> Qty: 100 | K32: ="Qty: "& K13 -> Qty: 250 | L32: ="Qty: "& L13 -> Qty: 500 | M32: ="Qty: "& M13 -> Qty: 1000 | N32: Amortize/ Min Buy
E33: =C33*D33 -> 0 | F33: =IF($N33=TRUE,$E33/F$13,$E33*(1+(1/F$13))) -> 0 | G33: =IF($N33=TRUE,$E33/G$13,$E33*(1+(1/G$13))) -> 0 | H33: =IF($N33=TRUE,$E33/H$13,$E33*(1+(1/H$13))) -> 0 | I33: =IF($N33=TRUE,$E33/I$13,$E33*(1+(1/I$13))) -> 0 | J33: =IF($N33=TRUE,$E33/J$13,$E33*(1+(1/J$13))) -> 0 | K33: =IF($N33=TRUE,$E33/K$13,$E33*(1+(1/K$13))) -> 0 | L33: =IF($N33=TRUE,$E33/L$13,$E33*(1+(1/L$13))) -> 0 | M33: =IF($N33=TRUE,$E33/M$13,$E33*(1+(1/M$13))) -> 0 | N33: FALSE
E34: =C34*D34 -> 0 | F34: =IF($N34=TRUE,$E34/F$13,$E34*(1+(1/F$13))) -> 0 | G34: =IF($N34=TRUE,$E34/G$13,$E34*(1+(1/G$13))) -> 0 | H34: =IF($N34=TRUE,$E34/H$13,$E34*(1+(1/H$13))) -> 0 | I34: =IF($N34=TRUE,$E34/I$13,$E34*(1+(1/I$13))) -> 0 | J34: =IF($N34=TRUE,$E34/J$13,$E34*(1+(1/J$13))) -> 0 | K34: =IF($N34=TRUE,$E34/K$13,$E34*(1+(1/K$13))) -> 0 | L34: =IF($N34=TRUE,$E34/L$13,$E34*(1+(1/L$13))) -> 0 | M34: =IF($N34=TRUE,$E34/M$13,$E34*(1+(1/M$13))) -> 0 | N34: FALSE
E35: =C35*D35 -> 0 | F35: =IF($N35=TRUE,$E35/F$13,$E35*(1+(1/F$13))) -> 0 | G35: =IF($N35=TRUE,$E35/G$13,$E35*(1+(1/G$13))) -> 0 | H35: =IF($N35=TRUE,$E35/H$13,$E35*(1+(1/H$13))) -> 0 | I35: =IF($N35=TRUE,$E35/I$13,$E35*(1+(1/I$13))) -> 0 | J35: =IF($N35=TRUE,$E35/J$13,$E35*(1+(1/J$13))) -> 0 | K35: =IF($N35=TRUE,$E35/K$13,$E35*(1+(1/K$13))) -> 0 | L35: =IF($N35=TRUE,$E35/L$13,$E35*(1+(1/L$13))) -> 0 | M35: =IF($N35=TRUE,$E35/M$13,$E35*(1+(1/M$13))) -> 0 | N35: FALSE | S35: QTY | T35: Total
E36: =C36*D36 -> 0 | F36: =IF($N36=TRUE,$E36/F$13,$E36*(1+(1/F$13))) -> 0 | G36: =IF($N36=TRUE,$E36/G$13,$E36*(1+(1/G$13))) -> 0 | H36: =IF($N36=TRUE,$E36/H$13,$E36*(1+(1/H$13))) -> 0 | I36: =IF($N36=TRUE,$E36/I$13,$E36*(1+(1/I$13))) -> 0 | J36: =IF($N36=TRUE,$E36/J$13,$E36*(1+(1/J$13))) -> 0 | K36: =IF($N36=TRUE,$E36/K$13,$E36*(1+(1/K$13))) -> 0 | L36: =IF($N36=TRUE,$E36/L$13,$E36*(1+(1/L$13))) -> 0 | M36: =IF($N36=TRUE,$E36/M$13,$E36*(1+(1/M$13))) -> 0 | N36: FALSE | S36: =M13 -> 1000 | T36: =M63 -> 0
E37: =C37*D37 -> 0 | F37: =IF($N37=TRUE,$E37/F$13,$E37*(1+(1/F$13))) -> 0 | G37: =IF($N37=TRUE,$E37/G$13,$E37*(1+(1/G$13))) -> 0 | H37: =IF($N37=TRUE,$E37/H$13,$E37*(1+(1/H$13))) -> 0 | I37: =IF($N37=TRUE,$E37/I$13,$E37*(1+(1/I$13))) -> 0 | J37: =IF($N37=TRUE,$E37/J$13,$E37*(1+(1/J$13))) -> 0 | K37: =IF($N37=TRUE,$E37/K$13,$E37*(1+(1/K$13))) -> 0 | L37: =IF($N37=TRUE,$E37/L$13,$E37*(1+(1/L$13))) -> 0 | M37: =IF($N37=TRUE,$E37/M$13,$E37*(1+(1/M$13))) -> 0 | N37: FALSE | S37: =L13 -> 500 | T37: =L63 -> 0
E38: =C38*D38 -> 0 | F38: =IF($N38=TRUE,$E38/F$13,$E38*(1+(1/F$13))) -> 0 | G38: =IF($N38=TRUE,$E38/G$13,$E38*(1+(1/G$13))) -> 0 | H38: =IF($N38=TRUE,$E38/H$13,$E38*(1+(1/H$13))) -> 0 | I38: =IF($N38=TRUE,$E38/I$13,$E38*(1+(1/I$13))) -> 0 | J38: =IF($N38=TRUE,$E38/J$13,$E38*(1+(1/J$13))) -> 0 | K38: =IF($N38=TRUE,$E38/K$13,$E38*(1+(1/K$13))) -> 0 | L38: =IF($N38=TRUE,$E38/L$13,$E38*(1+(1/L$13))) -> 0 | M38: =IF($N38=TRUE,$E38/M$13,$E38*(1+(1/M$13))) -> 0 | N38: FALSE | S38: =K13 -> 250 | T38: =K63 -> 0
E39: =C39*D39 -> 0 | F39: =IF($N39=TRUE,$E39/F$13,$E39*(1+(1/F$13))) -> 0 | G39: =IF($N39=TRUE,$E39/G$13,$E39*(1+(1/G$13))) -> 0 | H39: =IF($N39=TRUE,$E39/H$13,$E39*(1+(1/H$13))) -> 0 | I39: =IF($N39=TRUE,$E39/I$13,$E39*(1+(1/I$13))) -> 0 | J39: =IF($N39=TRUE,$E39/J$13,$E39*(1+(1/J$13))) -> 0 | K39: =IF($N39=TRUE,$E39/K$13,$E39*(1+(1/K$13))) -> 0 | L39: =IF($N39=TRUE,$E39/L$13,$E39*(1+(1/L$13))) -> 0 | M39: =IF($N39=TRUE,$E39/M$13,$E39*(1+(1/M$13))) -> 0 | N39: FALSE | S39: =H13 -> 50 | T39: =H63 -> 0
E40: =C40*D40 -> 0 | F40: =IF($N40=TRUE,$E40/F$13,$E40*(1+(1/F$13))) -> 0 | G40: =IF($N40=TRUE,$E40/G$13,$E40*(1+(1/G$13))) -> 0 | H40: =IF($N40=TRUE,$E40/H$13,$E40*(1+(1/H$13))) -> 0 | I40: =IF($N40=TRUE,$E40/I$13,$E40*(1+(1/I$13))) -> 0 | J40: =IF($N40=TRUE,$E40/J$13,$E40*(1+(1/J$13))) -> 0 | K40: =IF($N40=TRUE,$E40/K$13,$E40*(1+(1/K$13))) -> 0 | L40: =IF($N40=TRUE,$E40/L$13,$E40*(1+(1/L$13))) -> 0 | M40: =IF($N40=TRUE,$E40/M$13,$E40*(1+(1/M$13))) -> 0 | N40: FALSE | S40: =G13 -> 25 | T40: =G63 -> 0
E41: =C41*D41 -> 0 | F41: =IF($N41=TRUE,$E41/F$13,$E41*(1+(1/F$13))) -> 0 | G41: =IF($N41=TRUE,$E41/G$13,$E41*(1+(1/G$13))) -> 0 | H41: =IF($N41=TRUE,$E41/H$13,$E41*(1+(1/H$13))) -> 0 | I41: =IF($N41=TRUE,$E41/I$13,$E41*(1+(1/I$13))) -> 0 | J41: =IF($N41=TRUE,$E41/J$13,$E41*(1+(1/J$13))) -> 0 | K41: =IF($N41=TRUE,$E41/K$13,$E41*(1+(1/K$13))) -> 0 | L41: =IF($N41=TRUE,$E41/L$13,$E41*(1+(1/L$13))) -> 0 | M41: =IF($N41=TRUE,$E41/M$13,$E41*(1+(1/M$13))) -> 0 | N41: FALSE | S41: =F13 -> 10 | T41: =F63 -> 0
E42: =C42*D42 -> 0 | F42: =IF($N42=TRUE,$E42/F$13,$E42*(1+(1/F$13))) -> 0 | G42: =IF($N42=TRUE,$E42/G$13,$E42*(1+(1/G$13))) -> 0 | H42: =IF($N42=TRUE,$E42/H$13,$E42*(1+(1/H$13))) -> 0 | I42: =IF($N42=TRUE,$E42/I$13,$E42*(1+(1/I$13))) -> 0 | J42: =IF($N42=TRUE,$E42/J$13,$E42*(1+(1/J$13))) -> 0 | K42: =IF($N42=TRUE,$E42/K$13,$E42*(1+(1/K$13))) -> 0 | L42: =IF($N42=TRUE,$E42/L$13,$E42*(1+(1/L$13))) -> 0 | M42: =IF($N42=TRUE,$E42/M$13,$E42*(1+(1/M$13))) -> 0 | N42: FALSE
E43: =C43*D43 -> 0 | F43: =IF($N43=TRUE,$E43/F$13,$E43*(1+(1/F$13))) -> 0 | G43: =IF($N43=TRUE,$E43/G$13,$E43*(1+(1/G$13))) -> 0 | H43: =IF($N43=TRUE,$E43/H$13,$E43*(1+(1/H$13))) -> 0 | I43: =IF($N43=TRUE,$E43/I$13,$E43*(1+(1/I$13))) -> 0 | J43: =IF($N43=TRUE,$E43/J$13,$E43*(1+(1/J$13))) -> 0 | K43: =IF($N43=TRUE,$E43/K$13,$E43*(1+(1/K$13))) -> 0 | L43: =IF($N43=TRUE,$E43/L$13,$E43*(1+(1/L$13))) -> 0 | M43: =IF($N43=TRUE,$E43/M$13,$E43*(1+(1/M$13))) -> 0 | N43: FALSE
E44: =C44*D44 -> 0 | F44: =IF($N44=TRUE,$E44/F$13,$E44*(1+(1/F$13))) -> 0 | G44: =IF($N44=TRUE,$E44/G$13,$E44*(1+(1/G$13))) -> 0 | H44: =IF($N44=TRUE,$E44/H$13,$E44*(1+(1/H$13))) -> 0 | I44: =IF($N44=TRUE,$E44/I$13,$E44*(1+(1/I$13))) -> 0 | J44: =IF($N44=TRUE,$E44/J$13,$E44*(1+(1/J$13))) -> 0 | K44: =IF($N44=TRUE,$E44/K$13,$E44*(1+(1/K$13))) -> 0 | L44: =IF($N44=TRUE,$E44/L$13,$E44*(1+(1/L$13))) -> 0 | M44: =IF($N44=TRUE,$E44/M$13,$E44*(1+(1/M$13))) -> 0 | N44: FALSE
A45: PROCESSES/COMPONENTS | D45: SETUP $ | E45: RUN$ EA.
F46: =($D46/F$13)+$E46 -> 0 | G46: =($D46/G$13)+$E46 -> 0 | H46: =($D46/H$13)+$E46 -> 0 | I46: =($D46/I$13)+$E46 -> 0 | J46: =($D46/J$13)+$E46 -> 0 | K46: =($D46/K$13)+$E46 -> 0 | L46: =($D46/L$13)+$E46 -> 0 | M46: =($D46/M$13)+$E46 -> 0
F47: =($D47/F$13)+$E47 -> 0 | G47: =($D47/G$13)+$E47 -> 0 | H47: =($D47/H$13)+$E47 -> 0 | I47: =($D47/I$13)+$E47 -> 0 | J47: =($D47/J$13)+$E47 -> 0 | K47: =($D47/K$13)+$E47 -> 0 | L47: =($D47/L$13)+$E47 -> 0 | M47: =($D47/M$13)+$E47 -> 0
F48: =($D48/F$13)+$E48 -> 0 | G48: =($D48/G$13)+$E48 -> 0 | H48: =($D48/H$13)+$E48 -> 0 | I48: =($D48/I$13)+$E48 -> 0 | J48: =($D48/J$13)+$E48 -> 0 | K48: =($D48/K$13)+$E48 -> 0 | L48: =($D48/L$13)+$E48 -> 0 | M48: =($D48/M$13)+$E48 -> 0
F49: =($D49/F$13)+$E49 -> 0 | G49: =($D49/G$13)+$E49 -> 0 | H49: =($D49/H$13)+$E49 -> 0 | I49: =($D49/I$13)+$E49 -> 0 | J49: =($D49/J$13)+$E49 -> 0 | K49: =($D49/K$13)+$E49 -> 0 | L49: =($D49/L$13)+$E49 -> 0 | M49: =($D49/M$13)+$E49 -> 0
F50: =($D50/F$13)+$E50 -> 0 | G50: =($D50/G$13)+$E50 -> 0 | H50: =($D50/H$13)+$E50 -> 0 | I50: =($D50/I$13)+$E50 -> 0 | J50: =($D50/J$13)+$E50 -> 0 | K50: =($D50/K$13)+$E50 -> 0 | L50: =($D50/L$13)+$E50 -> 0 | M50: =($D50/M$13)+$E50 -> 0
B51: MATERIAL & HARDWARE TOTAL | F51: =SUM(F33:F44) -> 0 | G51: =SUM(G33:G44) -> 0 | H51: =SUM(H33:H44) -> 0 | I51: =SUM(I33:I44) -> 0 | J51: =SUM(J33:J44) -> 0 | K51: =SUM(K33:K44) -> 0 | L51: =SUM(L33:L44) -> 0 | M51: =SUM(M33:M44) -> 0 | N51: =IF(N13=0,0,SUM(N42:N44)) -> 0
B52: PROCESSES TOTAL | F52: =SUM(F46:F50) -> 0 | G52: =SUM(G46:G50) -> 0 | H52: =SUM(H46:H50) -> 0 | I52: =SUM(I46:I50) -> 0 | J52: =SUM(J46:J50) -> 0 | K52: =SUM(K46:K50) -> 0 | L52: =SUM(L46:L50) -> 0 | M52: =SUM(M46:M50) -> 0 | N52: =IF(N13=0,0,SUM(N46:N50)) -> 0
B53: M+L Subtotal | F53: =SUM(F30+F51+F52) -> 0 | G53: =SUM(G30+G51+G52) -> 0 | H53: =SUM(H30+H51+H52) -> 0 | I53: =SUM(I30+I51+I52) -> 0 | J53: =SUM(J30+J51+J52) -> 0 | K53: =SUM(K30+K51+K52) -> 0 | L53: =SUM(L30+L51+L52) -> 0 | M53: =SUM(M30+M51+M52) -> 0 | N53: =IF(N13=0,0,SUM(N30+N51+N52)) -> 0
E55: REFERENCE | F55: =SUM(F53+#REF!+#REF!) -> #REF! | G55: =SUM(G53+#REF!+#REF!) -> #REF! | H55: =SUM(H53+#REF!+#REF!) -> #REF! | I55: =SUM(I53+#REF!+#REF!) -> #REF! | J55: =SUM(J53+#REF!+#REF!) -> #REF! | K55: =SUM(K53+#REF!+#REF!) -> #REF! | L55: =SUM(L53+#REF!+#REF!) -> #REF! | M55: =SUM(M53+#REF!+#REF!) -> #REF! | N55: =SUM(N53+#REF!+#REF!) -> #REF!
D56: MARGIN | F56: =(F55-F53)/F55 -> #REF! | G56: =(G55-G53)/G55 -> #REF! | H56: =(H55-H53)/H55 -> #REF! | I56: =(I55-I53)/I55 -> #REF! | J56: =(J55-J53)/J55 -> #REF! | K56: =(K55-K53)/K55 -> #REF! | L56: =(L55-L53)/L55 -> #REF! | M56: =(M55-M53)/M55 -> #REF!
D57: LABOR | F57: =F30 -> 0 | G57: =G30 -> 0 | H57: =H30 -> 0 | I57: =I30 -> 0 | J57: =J30 -> 0 | K57: =K30 -> 0 | L57: =L30 -> 0 | M57: =M30 -> 0 | N57: =SUM((N30)) -> 0
C58: MAT'ls &HARDWARE | F58: =F51 -> 0 | G58: =G51 -> 0 | H58: =H51 -> 0 | I58: =I51 -> 0 | J58: =J51 -> 0 | K58: =K51 -> 0 | L58: =L51 -> 0 | M58: =M51 -> 0 | N58: =(N51) -> 0
D59: PROCESS | F59: =F52 -> 0 | G59: =G52 -> 0 | H59: =H52 -> 0 | I59: =I52 -> 0 | J59: =J52 -> 0 | K59: =K52 -> 0 | L59: =L52 -> 0 | M59: =M52 -> 0 | N59: =N52 -> 0
D60: Subtotal | F60: =SUM(F57:F59) -> 0 | G60: =SUM(G57:G59) -> 0 | H60: =SUM(H57:H59) -> 0 | I60: =SUM(I57:I59) -> 0 | J60: =SUM(J57:J59) -> 0 | K60: =SUM(K57:K59) -> 0 | L60: =SUM(L57:L59) -> 0 | M60: =SUM(M57:M59) -> 0 | N60: =SUM(N57:N59) -> 0
D61: AMORTIZED | F61: =$N$60/F13 -> 0 | G61: =$N$60/G13 -> 0 | H61: =$N$60/H13 -> 0 | I61: =$N$60/I13 -> 0 | J61: =$N$60/J13 -> 0 | K61: =$N$60/K13 -> 0 | L61: =$N$60/L13 -> 0 | M61: =$N$60/M13 -> 0
D62: Facilities | F62: 0 | G62: 0 | H62: 0 | I62: 0 | J62: 0 | K62: 0 | L62: 0 | M62: 0
D63: =B3 -> 2 | F63: =SUM(F60:F62) -> 0 | G63: =SUM(G60:G62) -> 0 | H63: =SUM(H60:H62) -> 0 | I63: =SUM(I60:I62) -> 0 | J63: =SUM(J60:J62) -> 0 | K63: =SUM(K60:K62) -> 0 | L63: =SUM(L60:L62) -> 0 | M63: =SUM(M60:M62) -> 0
A66: NRESC/TOOLING
A67: SETUPS
A68: FAIR
A69: SOURCE

Sheet Subassy 3
A2: CUSTOMER: | F2: Comments:
A3: P/N: | B3: 3 | D3: NSN #:
A4: REV: | D4: SOL #:
A5: QUOTE LOG No.: | D5: RFQ #:
A6: QTY: | B6: =F13&", "&G13&", "&H13&", "&I13&", "&J13&", "&K13&", "&L13&", "&M13 -> 10, 25, 50, 75, 100, 250, 500, 1000
A7: DATE:
A8: ESTIMATOR:
A11: MANUFACTURING OPERATIONS | F11: COST ESTIMATED QUANTITIES | N11: NRE/SET-UP
B13: SET-UP TIME | C13: RUN TIME | E13: LABOR RATE | F13: ='Top Assy'!F13 -> 10 | G13: ='Top Assy'!G13 -> 25 | H13: ='Top Assy'!H13 -> 50 | I13: ='Top Assy'!I13 -> 75 | J13: ='Top Assy'!J13 -> 100 | K13: ='Top Assy'!K13 -> 250 | L13: ='Top Assy'!L13 -> 500 | M13: ='Top Assy'!M13 -> 1000 | N13: 1
A14: Program | E14: 0 | N14: =(($B14/N$13*$E14)+($C14*$E14)) -> 0
A15: Fixtures | E15: 0 | N15: =(($B15/N$13*$E15)+($C15*$E15)) -> 0
A16: Mill/Turn | E16: 0 | F16: =(($B16/F$13*$E16)+($C16*$E16)) -> 0 | G16: =(($B16/G$13*$E16)+($C16*$E16)) -> 0 | H16: =(($B16/H$13*$E16)+($C16*$E16)) -> 0 | I16: =(($B16/I$13*$E16)+($C16*$E16)) -> 0 | J16: =(($B16/J$13*$E16)+($C16*$E16)) -> 0 | K16: =(($B16/K$13*$E16)+($C16*$E16)) -> 0 | L16: =(($B16/L$13*$E16)+($C16*$E16)) -> 0 | M16: =(($B16/M$13*$E16)+($C16*$E16)) -> 0
A17: Metals - Mills | E17: 0 | F17: =(($B17/F$13*$E17)+($C17*$E17)) -> 0 | G17: =(($B17/G$13*$E17)+($C17*$E17)) -> 0 | H17: =(($B17/H$13*$E17)+($C17*$E17)) -> 0 | I17: =(($B17/I$13*$E17)+($C17*$E17)) -> 0 | J17: =(($B17/J$13*$E17)+($C17*$E17)) -> 0 | K17: =(($B17/K$13*$E17)+($C17*$E17)) -> 0 | L17: =(($B17/L$13*$E17)+($C17*$E17)) -> 0 | M17: =(($B17/M$13*$E17)+($C17*$E17)) -> 0
A18: Metals - Lathe | E18: 0 | F18: =(($B18/F$13*$E18)+($C18*$E18)) -> 0 | G18: =(($B18/G$13*$E18)+($C18*$E18)) -> 0 | H18: =(($B18/H$13*$E18)+($C18*$E18)) -> 0 | I18: =(($B18/I$13*$E18)+($C18*$E18)) -> 0 | J18: =(($B18/J$13*$E18)+($C18*$E18)) -> 0 | K18: =(($B18/K$13*$E18)+($C18*$E18)) -> 0 | L18: =(($B18/L$13*$E18)+($C18*$E18)) -> 0 | M18: =(($B18/M$13*$E18)+($C18*$E18)) -> 0
A19: Rubber Mold | E19: 0 | F19: =(($B19/F$13*$E19)+($C19*$E19)) -> 0 | G19: =(($B19/G$13*$E19)+($C19*$E19)) -> 0 | H19: =(($B19/H$13*$E19)+($C19*$E19)) -> 0 | I19: =(($B19/I$13*$E19)+($C19*$E19)) -> 0 | J19: =(($B19/J$13*$E19)+($C19*$E19)) -> 0 | K19: =(($B19/K$13*$E19)+($C19*$E19)) -> 0 | L19: =(($B19/L$13*$E19)+($C19*$E19)) -> 0 | M19: =(($B19/M$13*$E19)+($C19*$E19)) -> 0
A20: Plastic Injection Mold | E20: 0 | F20: =(($B20/F$13*$E20)+($C20*$E20)) -> 0 | G20: =(($B20/G$13*$E20)+($C20*$E20)) -> 0 | H20: =(($B20/H$13*$E20)+($C20*$E20)) -> 0 | I20: =(($B20/I$13*$E20)+($C20*$E20)) -> 0 | J20: =(($B20/J$13*$E20)+($C20*$E20)) -> 0 | K20: =(($B20/K$13*$E20)+($C20*$E20)) -> 0 | L20: =(($B20/L$13*$E20)+($C20*$E20)) -> 0 | M20: =(($B20/M$13*$E20)+($C20*$E20)) -> 0
A21: Plastic Compression Mold | E21: 0 | F21: =(($B21/F$13*$E21)+($C21*$E21)) -> 0 | G21: =(($B21/G$13*$E21)+($C21*$E21)) -> 0 | H21: =(($B21/H$13*$E21)+($C21*$E21)) -> 0 | I21: =(($B21/I$13*$E21)+($C21*$E21)) -> 0 | J21: =(($B21/J$13*$E21)+($C21*$E21)) -> 0 | K21: =(($B21/K$13*$E21)+($C21*$E21)) -> 0 | L21: =(($B21/L$13*$E21)+($C21*$E21)) -> 0 | M21: =(($B21/M$13*$E21)+($C21*$E21)) -> 0
A22: Waterjet - Setup | E22: 0 | F22: =(($B22/F$13*$E22)+($C22*$E22)) -> 0 | G22: =(($B22/G$13*$E22)+($C22*$E22)) -> 0 | H22: =(($B22/H$13*$E22)+($C22*$E22)) -> 0 | I22: =(($B22/I$13*$E22)+($C22*$E22)) -> 0 | J22: =(($B22/J$13*$E22)+($C22*$E22)) -> 0 | K22: =(($B22/K$13*$E22)+($C22*$E22)) -> 0 | L22: =(($B22/L$13*$E22)+($C22*$E22)) -> 0 | M22: =(($B22/M$13*$E22)+($C22*$E22)) -> 0
A23: Waterjet - Operator | E23: 0 | F23: =(($B23/F$13*$E23)+($C23*$E23)) -> 0 | G23: =(($B23/G$13*$E23)+($C23*$E23)) -> 0 | H23: =(($B23/H$13*$E23)+($C23*$E23)) -> 0 | I23: =(($B23/I$13*$E23)+($C23*$E23)) -> 0 | J23: =(($B23/J$13*$E23)+($C23*$E23)) -> 0 | K23: =(($B23/K$13*$E23)+($C23*$E23)) -> 0 | L23: =(($B23/L$13*$E23)+($C23*$E23)) -> 0 | M23: =(($B23/M$13*$E23)+($C23*$E23)) -> 0
A24: Assembly, Die Punch, Deburr | E24: 0 | F24: =(($B24/F$13*$E24)+($C24*$E24)) -> 0 | G24: =(($B24/G$13*$E24)+($C24*$E24)) -> 0 | H24: =(($B24/H$13*$E24)+($C24*$E24)) -> 0 | I24: =(($B24/I$13*$E24)+($C24*$E24)) -> 0 | J24: =(($B24/J$13*$E24)+($C24*$E24)) -> 0 | K24: =(($B24/K$13*$E24)+($C24*$E24)) -> 0 | L24: =(($B24/L$13*$E24)+($C24*$E24)) -> 0 | M24: =(($B24/M$13*$E24)+($C24*$E24)) -> 0
A25: Quality Inspection | E25: 0 | F25: =(($B25/F$13*$E25)+($C25*$E25)) -> 0 | G25: =(($B25/G$13*$E25)+($C25*$E25)) -> 0 | H25: =(($B25/H$13*$E25)+($C25*$E25)) -> 0 | I25: =(($B25/I$13*$E25)+($C25*$E25)) -> 0 | J25: =(($B25/J$13*$E25)+($C25*$E25)) -> 0 | K25: =(($B25/K$13*$E25)+($C25*$E25)) -> 0 | L25: =(($B25/L$13*$E25)+($C25*$E25)) -> 0 | M25: =(($B25/M$13*$E25)+($C25*$E25)) -> 0
C26: Labor | E26: Basic LABOR | F26: =SUM(F16:F25) -> 0 | G26: =SUM(G16:G25) -> 0 | H26: =SUM(H16:H25) -> 0 | I26: =SUM(I16:I25) -> 0 | J26: =SUM(J16:J25) -> 0 | K26: =SUM(K16:K25) -> 0 | L26: =SUM(L16:L25) -> 0 | M26: =SUM(M16:M25) -> 0 | N26: =SUM(N14:N25) -> 0
B27: T. setup | C27: T.RUN | E27: hrs | F27: =(($B$28/F13)+$C$28)/60 -> 0 | G27: =(($B$28/G13)+$C$28)/60 -> 0 | H27: =(($B$28/H13)+$C$28)/60 -> 0 | I27: =(($B$28/I13)+$C$28)/60 -> 0 | J27: =(($B$28/J13)+$C$28)/60 -> 0 | K27: =(($B$28/K13)+$C$28)/60 -> 0 | L27: =(($B$28/L13)+$C$28)/60 -> 0 | M27: =(($B$28/M13)+$C$28)/60 -> 0
B28: =SUM(B16:B25) -> 0 | C28: =SUM(C16:C25) -> 0 | D28: 0 | E28: BURDEN | F28: =F26*$D$28 -> 0 | G28: =G26*$D$28 -> 0 | H28: =H26*$D$28 -> 0 | I28: =I26*$D$28 -> 0 | J28: =J26*$D$28 -> 0 | K28: =K26*$D$28 -> 0 | L28: =L26*$D$28 -> 0 | M28: =M26*$D$28 -> 0
E30: Total | F30: =F26+F28 -> 0 | G30: =G26+G28 -> 0 | H30: =H26+H28 -> 0 | I30: =I26+I28 -> 0 | J30: =J26+J28 -> 0 | K30: =K26+K28 -> 0 | L30: =L26+L28 -> 0 | M30: =M26+M28 -> 0 | N30: =N26 -> 0
A32: RAW MATERIALS & HARDWARE | B32: Matl UoM | C32: PARTS QTY | D32: UNIT PRICE | E32: MAT'l BURDEN | F32: ="Qty: "& F13 -> Qty: 10 | G32: ="Qty: "& G13 -> Qty: 25 | H32: ="Qty: "& H13 -> Qty: 50 | I32: ="Qty: "& I13 -> Qty: 75 | J32: ="Qty: "& J13 -> Qty: 100 | K32: ="Qty: "& K13 -> Qty: 250 | L32: ="Qty: "& L13 -> Qty: 500 | M32: ="Qty: "& M13 -> Qty: 1000 | N32: Amortize/ Min Buy
E33: =C33*D33 -> 0 | F33: =IF($N33=TRUE,$E33/F$13,$E33*(1+(1/F$13))) -> 0 | G33: =IF($N33=TRUE,$E33/G$13,$E33*(1+(1/G$13))) -> 0 | H33: =IF($N33=TRUE,$E33/H$13,$E33*(1+(1/H$13))) -> 0 | I33: =IF($N33=TRUE,$E33/I$13,$E33*(1+(1/I$13))) -> 0 | J33: =IF($N33=TRUE,$E33/J$13,$E33*(1+(1/J$13))) -> 0 | K33: =IF($N33=TRUE,$E33/K$13,$E33*(1+(1/K$13))) -> 0 | L33: =IF($N33=TRUE,$E33/L$13,$E33*(1+(1/L$13))) -> 0 | M33: =IF($N33=TRUE,$E33/M$13,$E33*(1+(1/M$13))) -> 0 | N33: FALSE
E34: =C34*D34 -> 0 | F34: =IF($N34=TRUE,$E34/F$13,$E34*(1+(1/F$13))) -> 0 | G34: =IF($N34=TRUE,$E34/G$13,$E34*(1+(1/G$13))) -> 0 | H34: =IF($N34=TRUE,$E34/H$13,$E34*(1+(1/H$13))) -> 0 | I34: =IF($N34=TRUE,$E34/I$13,$E34*(1+(1/I$13))) -> 0 | J34: =IF($N34=TRUE,$E34/J$13,$E34*(1+(1/J$13))) -> 0 | K34: =IF($N34=TRUE,$E34/K$13,$E34*(1+(1/K$13))) -> 0 | L34: =IF($N34=TRUE,$E34/L$13,$E34*(1+(1/L$13))) -> 0 | M34: =IF($N34=TRUE,$E34/M$13,$E34*(1+(1/M$13))) -> 0 | N34: FALSE
E35: =C35*D35 -> 0 | F35: =IF($N35=TRUE,$E35/F$13,$E35*(1+(1/F$13))) -> 0 | G35: =IF($N35=TRUE,$E35/G$13,$E35*(1+(1/G$13))) -> 0 | H35: =IF($N35=TRUE,$E35/H$13,$E35*(1+(1/H$13))) -> 0 | I35: =IF($N35=TRUE,$E35/I$13,$E35*(1+(1/I$13))) -> 0 | J35: =IF($N35=TRUE,$E35/J$13,$E35*(1+(1/J$13))) -> 0 | K35: =IF($N35=TRUE,$E35/K$13,$E35*(1+(1/K$13))) -> 0 | L35: =IF($N35=TRUE,$E35/L$13,$E35*(1+(1/L$13))) -> 0 | M35: =IF($N35=TRUE,$E35/M$13,$E35*(1+(1/M$13))) -> 0 | N35: FALSE | S35: QTY | T35: Total
E36: =C36*D36 -> 0 | F36: =IF($N36=TRUE,$E36/F$13,$E36*(1+(1/F$13))) -> 0 | G36: =IF($N36=TRUE,$E36/G$13,$E36*(1+(1/G$13))) -> 0 | H36: =IF($N36=TRUE,$E36/H$13,$E36*(1+(1/H$13))) -> 0 | I36: =IF($N36=TRUE,$E36/I$13,$E36*(1+(1/I$13))) -> 0 | J36: =IF($N36=TRUE,$E36/J$13,$E36*(1+(1/J$13))) -> 0 | K36: =IF($N36=TRUE,$E36/K$13,$E36*(1+(1/K$13))) -> 0 | L36: =IF($N36=TRUE,$E36/L$13,$E36*(1+(1/L$13))) -> 0 | M36: =IF($N36=TRUE,$E36/M$13,$E36*(1+(1/M$13))) -> 0 | N36: FALSE | S36: =M13 -> 1000 | T36: =M63 -> 0
E37: =C37*D37 -> 0 | F37: =IF($N37=TRUE,$E37/F$13,$E37*(1+(1/F$13))) -> 0 | G37: =IF($N37=TRUE,$E37/G$13,$E37*(1+(1/G$13))) -> 0 | H37: =IF($N37=TRUE,$E37/H$13,$E37*(1+(1/H$13))) -> 0 | I37: =IF($N37=TRUE,$E37/I$13,$E37*(1+(1/I$13))) -> 0 | J37: =IF($N37=TRUE,$E37/J$13,$E37*(1+(1/J$13))) -> 0 | K37: =IF($N37=TRUE,$E37/K$13,$E37*(1+(1/K$13))) -> 0 | L37: =IF($N37=TRUE,$E37/L$13,$E37*(1+(1/L$13))) -> 0 | M37: =IF($N37=TRUE,$E37/M$13,$E37*(1+(1/M$13))) -> 0 | N37: FALSE | S37: =L13 -> 500 | T37: =L63 -> 0
E38: =C38*D38 -> 0 | F38: =IF($N38=TRUE,$E38/F$13,$E38*(1+(1/F$13))) -> 0 | G38: =IF($N38=TRUE,$E38/G$13,$E38*(1+(1/G$13))) -> 0 | H38: =IF($N38=TRUE,$E38/H$13,$E38*(1+(1/H$13))) -> 0 | I38: =IF($N38=TRUE,$E38/I$13,$E38*(1+(1/I$13))) -> 0 | J38: =IF($N38=TRUE,$E38/J$13,$E38*(1+(1/J$13))) -> 0 | K38: =IF($N38=TRUE,$E38/K$13,$E38*(1+(1/K$13))) -> 0 | L38: =IF($N38=TRUE,$E38/L$13,$E38*(1+(1/L$13))) -> 0 | M38: =IF($N38=TRUE,$E38/M$13,$E38*(1+(1/M$13))) -> 0 | N38: FALSE | S38: =K13 -> 250 | T38: =K63 -> 0
E39: =C39*D39 -> 0 | F39: =IF($N39=TRUE,$E39/F$13,$E39*(1+(1/F$13))) -> 0 | G39: =IF($N39=TRUE,$E39/G$13,$E39*(1+(1/G$13))) -> 0 | H39: =IF($N39=TRUE,$E39/H$13,$E39*(1+(1/H$13))) -> 0 | I39: =IF($N39=TRUE,$E39/I$13,$E39*(1+(1/I$13))) -> 0 | J39: =IF($N39=TRUE,$E39/J$13,$E39*(1+(1/J$13))) -> 0 | K39: =IF($N39=TRUE,$E39/K$13,$E39*(1+(1/K$13))) -> 0 | L39: =IF($N39=TRUE,$E39/L$13,$E39*(1+(1/L$13))) -> 0 | M39: =IF($N39=TRUE,$E39/M$13,$E39*(1+(1/M$13))) -> 0 | N39: FALSE | S39: =H13 -> 50 | T39: =H63 -> 0
E40: =C40*D40 -> 0 | F40: =IF($N40=TRUE,$E40/F$13,$E40*(1+(1/F$13))) -> 0 | G40: =IF($N40=TRUE,$E40/G$13,$E40*(1+(1/G$13))) -> 0 | H40: =IF($N40=TRUE,$E40/H$13,$E40*(1+(1/H$13))) -> 0 | I40: =IF($N40=TRUE,$E40/I$13,$E40*(1+(1/I$13))) -> 0 | J40: =IF($N40=TRUE,$E40/J$13,$E40*(1+(1/J$13))) -> 0 | K40: =IF($N40=TRUE,$E40/K$13,$E40*(1+(1/K$13))) -> 0 | L40: =IF($N40=TRUE,$E40/L$13,$E40*(1+(1/L$13))) -> 0 | M40: =IF($N40=TRUE,$E40/M$13,$E40*(1+(1/M$13))) -> 0 | N40: FALSE | S40: =G13 -> 25 | T40: =G63 -> 0
E41: =C41*D41 -> 0 | F41: =IF($N41=TRUE,$E41/F$13,$E41*(1+(1/F$13))) -> 0 | G41: =IF($N41=TRUE,$E41/G$13,$E41*(1+(1/G$13))) -> 0 | H41: =IF($N41=TRUE,$E41/H$13,$E41*(1+(1/H$13))) -> 0 | I41: =IF($N41=TRUE,$E41/I$13,$E41*(1+(1/I$13))) -> 0 | J41: =IF($N41=TRUE,$E41/J$13,$E41*(1+(1/J$13))) -> 0 | K41: =IF($N41=TRUE,$E41/K$13,$E41*(1+(1/K$13))) -> 0 | L41: =IF($N41=TRUE,$E41/L$13,$E41*(1+(1/L$13))) -> 0 | M41: =IF($N41=TRUE,$E41/M$13,$E41*(1+(1/M$13))) -> 0 | N41: FALSE | S41: =F13 -> 10 | T41: =F63 -> 0
E42: =C42*D42 -> 0 | F42: =IF($N42=TRUE,$E42/F$13,$E42*(1+(1/F$13))) -> 0 | G42: =IF($N42=TRUE,$E42/G$13,$E42*(1+(1/G$13))) -> 0 | H42: =IF($N42=TRUE,$E42/H$13,$E42*(1+(1/H$13))) -> 0 | I42: =IF($N42=TRUE,$E42/I$13,$E42*(1+(1/I$13))) -> 0 | J42: =IF($N42=TRUE,$E42/J$13,$E42*(1+(1/J$13))) -> 0 | K42: =IF($N42=TRUE,$E42/K$13,$E42*(1+(1/K$13))) -> 0 | L42: =IF($N42=TRUE,$E42/L$13,$E42*(1+(1/L$13))) -> 0 | M42: =IF($N42=TRUE,$E42/M$13,$E42*(1+(1/M$13))) -> 0 | N42: FALSE
E43: =C43*D43 -> 0 | F43: =IF($N43=TRUE,$E43/F$13,$E43*(1+(1/F$13))) -> 0 | G43: =IF($N43=TRUE,$E43/G$13,$E43*(1+(1/G$13))) -> 0 | H43: =IF($N43=TRUE,$E43/H$13,$E43*(1+(1/H$13))) -> 0 | I43: =IF($N43=TRUE,$E43/I$13,$E43*(1+(1/I$13))) -> 0 | J43: =IF($N43=TRUE,$E43/J$13,$E43*(1+(1/J$13))) -> 0 | K43: =IF($N43=TRUE,$E43/K$13,$E43*(1+(1/K$13))) -> 0 | L43: =IF($N43=TRUE,$E43/L$13,$E43*(1+(1/L$13))) -> 0 | M43: =IF($N43=TRUE,$E43/M$13,$E43*(1+(1/M$13))) -> 0 | N43: FALSE
E44: =C44*D44 -> 0 | F44: =IF($N44=TRUE,$E44/F$13,$E44*(1+(1/F$13))) -> 0 | G44: =IF($N44=TRUE,$E44/G$13,$E44*(1+(1/G$13))) -> 0 | H44: =IF($N44=TRUE,$E44/H$13,$E44*(1+(1/H$13))) -> 0 | I44: =IF($N44=TRUE,$E44/I$13,$E44*(1+(1/I$13))) -> 0 | J44: =IF($N44=TRUE,$E44/J$13,$E44*(1+(1/J$13))) -> 0 | K44: =IF($N44=TRUE,$E44/K$13,$E44*(1+(1/K$13))) -> 0 | L44: =IF($N44=TRUE,$E44/L$13,$E44*(1+(1/L$13))) -> 0 | M44: =IF($N44=TRUE,$E44/M$13,$E44*(1+(1/M$13))) -> 0 | N44: FALSE
A45: PROCESSES/COMPONENTS | D45: SETUP $ | E45: RUN$ EA.
F46: =($D46/F$13)+$E46 -> 0 | G46: =($D46/G$13)+$E46 -> 0 | H46: =($D46/H$13)+$E46 -> 0 | I46: =($D46/I$13)+$E46 -> 0 | J46: =($D46/J$13)+$E46 -> 0 | K46: =($D46/K$13)+$E46 -> 0 | L46: =($D46/L$13)+$E46 -> 0 | M46: =($D46/M$13)+$E46 -> 0
F47: =($D47/F$13)+$E47 -> 0 | G47: =($D47/G$13)+$E47 -> 0 | H47: =($D47/H$13)+$E47 -> 0 | I47: =($D47/I$13)+$E47 -> 0 | J47: =($D47/J$13)+$E47 -> 0 | K47: =($D47/K$13)+$E47 -> 0 | L47: =($D47/L$13)+$E47 -> 0 | M47: =($D47/M$13)+$E47 -> 0
F48: =($D48/F$13)+$E48 -> 0 | G48: =($D48/G$13)+$E48 -> 0 | H48: =($D48/H$13)+$E48 -> 0 | I48: =($D48/I$13)+$E48 -> 0 | J48: =($D48/J$13)+$E48 -> 0 | K48: =($D48/K$13)+$E48 -> 0 | L48: =($D48/L$13)+$E48 -> 0 | M48: =($D48/M$13)+$E48 -> 0
F49: =($D49/F$13)+$E49 -> 0 | G49: =($D49/G$13)+$E49 -> 0 | H49: =($D49/H$13)+$E49 -> 0 | I49: =($D49/I$13)+$E49 -> 0 | J49: =($D49/J$13)+$E49 -> 0 | K49: =($D49/K$13)+$E49 -> 0 | L49: =($D49/L$13)+$E49 -> 0 | M49: =($D49/M$13)+$E49 -> 0
F50: =($D50/F$13)+$E50 -> 0 | G50: =($D50/G$13)+$E50 -> 0 | H50: =($D50/H$13)+$E50 -> 0 | I50: =($D50/I$13)+$E50 -> 0 | J50: =($D50/J$13)+$E50 -> 0 | K50: =($D50/K$13)+$E50 -> 0 | L50: =($D50/L$13)+$E50 -> 0 | M50: =($D50/M$13)+$E50 -> 0
B51: MATERIAL & HARDWARE TOTAL | F51: =SUM(F33:F44) -> 0 | G51: =SUM(G33:G44) -> 0 | H51: =SUM(H33:H44) -> 0 | I51: =SUM(I33:I44) -> 0 | J51: =SUM(J33:J44) -> 0 | K51: =SUM(K33:K44) -> 0 | L51: =SUM(L33:L44) -> 0 | M51: =SUM(M33:M44) -> 0 | N51: =IF(N13=0,0,SUM(N42:N44)) -> 0
B52: PROCESSES TOTAL | F52: =SUM(F46:F50) -> 0 | G52: =SUM(G46:G50) -> 0 | H52: =SUM(H46:H50) -> 0 | I52: =SUM(I46:I50) -> 0 | J52: =SUM(J46:J50) -> 0 | K52: =SUM(K46:K50) -> 0 | L52: =SUM(L46:L50) -> 0 | M52: =SUM(M46:M50) -> 0 | N52: =IF(N13=0,0,SUM(N46:N50)) -> 0
B53: M+L Subtotal | F53: =SUM(F30+F51+F52) -> 0 | G53: =SUM(G30+G51+G52) -> 0 | H53: =SUM(H30+H51+H52) -> 0 | I53: =SUM(I30+I51+I52) -> 0 | J53: =SUM(J30+J51+J52) -> 0 | K53: =SUM(K30+K51+K52) -> 0 | L53: =SUM(L30+L51+L52) -> 0 | M53: =SUM(M30+M51+M52) -> 0 | N53: =IF(N13=0,0,SUM(N30+N51+N52)) -> 0
E55: REFERENCE | F55: =SUM(F53+#REF!+#REF!) -> #REF! | G55: =SUM(G53+#REF!+#REF!) -> #REF! | H55: =SUM(H53+#REF!+#REF!) -> #REF! | I55: =SUM(I53+#REF!+#REF!) -> #REF! | J55: =SUM(J53+#REF!+#REF!) -> #REF! | K55: =SUM(K53+#REF!+#REF!) -> #REF! | L55: =SUM(L53+#REF!+#REF!) -> #REF! | M55: =SUM(M53+#REF!+#REF!) -> #REF! | N55: =SUM(N53+#REF!+#REF!) -> #REF!
D56: MARGIN | F56: =(F55-F53)/F55 -> #REF! | G56: =(G55-G53)/G55 -> #REF! | H56: =(H55-H53)/H55 -> #REF! | I56: =(I55-I53)/I55 -> #REF! | J56: =(J55-J53)/J55 -> #REF! | K56: =(K55-K53)/K55 -> #REF! | L56: =(L55-L53)/L55 -> #REF! | M56: =(M55-M53)/M55 -> #REF!
D57: LABOR | F57: =F30 -> 0 | G57: =G30 -> 0 | H57: =H30 -> 0 | I57: =I30 -> 0 | J57: =J30 -> 0 | K57: =K30 -> 0 | L57: =L30 -> 0 | M57: =M30 -> 0 | N57: =SUM((N30)) -> 0
C58: MAT'ls &HARDWARE | F58: =F51 -> 0 | G58: =G51 -> 0 | H58: =H51 -> 0 | I58: =I51 -> 0 | J58: =J51 -> 0 | K58: =K51 -> 0 | L58: =L51 -> 0 | M58: =M51 -> 0 | N58: =(N51) -> 0
D59: PROCESS | F59: =F52 -> 0 | G59: =G52 -> 0 | H59: =H52 -> 0 | I59: =I52 -> 0 | J59: =J52 -> 0 | K59: =K52 -> 0 | L59: =L52 -> 0 | M59: =M52 -> 0 | N59: =N52 -> 0
D60: Subtotal | F60: =SUM(F57:F59) -> 0 | G60: =SUM(G57:G59) -> 0 | H60: =SUM(H57:H59) -> 0 | I60: =SUM(I57:I59) -> 0 | J60: =SUM(J57:J59) -> 0 | K60: =SUM(K57:K59) -> 0 | L60: =SUM(L57:L59) -> 0 | M60: =SUM(M57:M59) -> 0 | N60: =SUM(N57:N59) -> 0
D61: AMORTIZED | F61: =$N$60/F13 -> 0 | G61: =$N$60/G13 -> 0 | H61: =$N$60/H13 -> 0 | I61: =$N$60/I13 -> 0 | J61: =$N$60/J13 -> 0 | K61: =$N$60/K13 -> 0 | L61: =$N$60/L13 -> 0 | M61: =$N$60/M13 -> 0
D62: Facilities | F62: 0 | G62: 0 | H62: 0 | I62: 0 | J62: 0 | K62: 0 | L62: 0 | M62: 0
D63: =B3 -> 3 | F63: =SUM(F60:F62) -> 0 | G63: =SUM(G60:G62) -> 0 | H63: =SUM(H60:H62) -> 0 | I63: =SUM(I60:I62) -> 0 | J63: =SUM(J60:J62) -> 0 | K63: =SUM(K60:K62) -> 0 | L63: =SUM(L60:L62) -> 0 | M63: =SUM(M60:M62) -> 0
A66: NRESC/TOOLING
A67: SETUPS
A68: FAIR
A69: SOURCE

Sheet Subassy 4
A2: CUSTOMER: | F2: Comments:
A3: P/N: | B3: 4 | D3: NSN #:
A4: REV: | D4: SOL #:
A5: QUOTE LOG No.: | D5: RFQ #:
A6: QTY: | B6: =F13&", "&G13&", "&H13&", "&I13&", "&J13&", "&K13&", "&L13&", "&M13 -> 10, 25, 50, 75, 100, 250, 500, 1000
A7: DATE:
A8: ESTIMATOR:
A11: MANUFACTURING OPERATIONS | F11: COST ESTIMATED QUANTITIES | N11: NRE/SET-UP
B13: SET-UP TIME | C13: RUN TIME | E13: LABOR RATE | F13: ='Top Assy'!F13 -> 10 | G13: ='Top Assy'!G13 -> 25 | H13: ='Top Assy'!H13 -> 50 | I13: ='Top Assy'!I13 -> 75 | J13: ='Top Assy'!J13 -> 100 | K13: ='Top Assy'!K13 -> 250 | L13: ='Top Assy'!L13 -> 500 | M13: ='Top Assy'!M13 -> 1000 | N13: 1
A14: Program | E14: 0 | N14: =(($B14/N$13*$E14)+($C14*$E14)) -> 0
A15: Fixtures | E15: 0 | N15: =(($B15/N$13*$E15)+($C15*$E15)) -> 0
A16: Mill/Turn | E16: 0 | F16: =(($B16/F$13*$E16)+($C16*$E16)) -> 0 | G16: =(($B16/G$13*$E16)+($C16*$E16)) -> 0 | H16: =(($B16/H$13*$E16)+($C16*$E16)) -> 0 | I16: =(($B16/I$13*$E16)+($C16*$E16)) -> 0 | J16: =(($B16/J$13*$E16)+($C16*$E16)) -> 0 | K16: =(($B16/K$13*$E16)+($C16*$E16)) -> 0 | L16: =(($B16/L$13*$E16)+($C16*$E16)) -> 0 | M16: =(($B16/M$13*$E16)+($C16*$E16)) -> 0
A17: Metals - Mills | E17: 0 | F17: =(($B17/F$13*$E17)+($C17*$E17)) -> 0 | G17: =(($B17/G$13*$E17)+($C17*$E17)) -> 0 | H17: =(($B17/H$13*$E17)+($C17*$E17)) -> 0 | I17: =(($B17/I$13*$E17)+($C17*$E17)) -> 0 | J17: =(($B17/J$13*$E17)+($C17*$E17)) -> 0 | K17: =(($B17/K$13*$E17)+($C17*$E17)) -> 0 | L17: =(($B17/L$13*$E17)+($C17*$E17)) -> 0 | M17: =(($B17/M$13*$E17)+($C17*$E17)) -> 0
A18: Metals - Lathe | E18: 0 | F18: =(($B18/F$13*$E18)+($C18*$E18)) -> 0 | G18: =(($B18/G$13*$E18)+($C18*$E18)) -> 0 | H18: =(($B18/H$13*$E18)+($C18*$E18)) -> 0 | I18: =(($B18/I$13*$E18)+($C18*$E18)) -> 0 | J18: =(($B18/J$13*$E18)+($C18*$E18)) -> 0 | K18: =(($B18/K$13*$E18)+($C18*$E18)) -> 0 | L18: =(($B18/L$13*$E18)+($C18*$E18)) -> 0 | M18: =(($B18/M$13*$E18)+($C18*$E18)) -> 0
A19: Rubber Mold | E19: 0 | F19: =(($B19/F$13*$E19)+($C19*$E19)) -> 0 | G19: =(($B19/G$13*$E19)+($C19*$E19)) -> 0 | H19: =(($B19/H$13*$E19)+($C19*$E19)) -> 0 | I19: =(($B19/I$13*$E19)+($C19*$E19)) -> 0 | J19: =(($B19/J$13*$E19)+($C19*$E19)) -> 0 | K19: =(($B19/K$13*$E19)+($C19*$E19)) -> 0 | L19: =(($B19/L$13*$E19)+($C19*$E19)) -> 0 | M19: =(($B19/M$13*$E19)+($C19*$E19)) -> 0
A20: Plastic Injection Mold | E20: 0 | F20: =(($B20/F$13*$E20)+($C20*$E20)) -> 0 | G20: =(($B20/G$13*$E20)+($C20*$E20)) -> 0 | H20: =(($B20/H$13*$E20)+($C20*$E20)) -> 0 | I20: =(($B20/I$13*$E20)+($C20*$E20)) -> 0 | J20: =(($B20/J$13*$E20)+($C20*$E20)) -> 0 | K20: =(($B20/K$13*$E20)+($C20*$E20)) -> 0 | L20: =(($B20/L$13*$E20)+($C20*$E20)) -> 0 | M20: =(($B20/M$13*$E20)+($C20*$E20)) -> 0
A21: Plastic Compression Mold | E21: 0 | F21: =(($B21/F$13*$E21)+($C21*$E21)) -> 0 | G21: =(($B21/G$13*$E21)+($C21*$E21)) -> 0 | H21: =(($B21/H$13*$E21)+($C21*$E21)) -> 0 | I21: =(($B21/I$13*$E21)+($C21*$E21)) -> 0 | J21: =(($B21/J$13*$E21)+($C21*$E21)) -> 0 | K21: =(($B21/K$13*$E21)+($C21*$E21)) -> 0 | L21: =(($B21/L$13*$E21)+($C21*$E21)) -> 0 | M21: =(($B21/M$13*$E21)+($C21*$E21)) -> 0
A22: Waterjet - Setup | E22: 0 | F22: =(($B22/F$13*$E22)+($C22*$E22)) -> 0 | G22: =(($B22/G$13*$E22)+($C22*$E22)) -> 0 | H22: =(($B22/H$13*$E22)+($C22*$E22)) -> 0 | I22: =(($B22/I$13*$E22)+($C22*$E22)) -> 0 | J22: =(($B22/J$13*$E22)+($C22*$E22)) -> 0 | K22: =(($B22/K$13*$E22)+($C22*$E22)) -> 0 | L22: =(($B22/L$13*$E22)+($C22*$E22)) -> 0 | M22: =(($B22/M$13*$E22)+($C22*$E22)) -> 0
A23: Waterjet - Operator | E23: 0 | F23: =(($B23/F$13*$E23)+($C23*$E23)) -> 0 | G23: =(($B23/G$13*$E23)+($C23*$E23)) -> 0 | H23: =(($B23/H$13*$E23)+($C23*$E23)) -> 0 | I23: =(($B23/I$13*$E23)+($C23*$E23)) -> 0 | J23: =(($B23/J$13*$E23)+($C23*$E23)) -> 0 | K23: =(($B23/K$13*$E23)+($C23*$E23)) -> 0 | L23: =(($B23/L$13*$E23)+($C23*$E23)) -> 0 | M23: =(($B23/M$13*$E23)+($C23*$E23)) -> 0
A24: Assembly, Die Punch, Deburr | E24: 0 | F24: =(($B24/F$13*$E24)+($C24*$E24)) -> 0 | G24: =(($B24/G$13*$E24)+($C24*$E24)) -> 0 | H24: =(($B24/H$13*$E24)+($C24*$E24)) -> 0 | I24: =(($B24/I$13*$E24)+($C24*$E24)) -> 0 | J24: =(($B24/J$13*$E24)+($C24*$E24)) -> 0 | K24: =(($B24/K$13*$E24)+($C24*$E24)) -> 0 | L24: =(($B24/L$13*$E24)+($C24*$E24)) -> 0 | M24: =(($B24/M$13*$E24)+($C24*$E24)) -> 0
A25: Quality Inspection | E25: 0 | F25: =(($B25/F$13*$E25)+($C25*$E25)) -> 0 | G25: =(($B25/G$13*$E25)+($C25*$E25)) -> 0 | H25: =(($B25/H$13*$E25)+($C25*$E25)) -> 0 | I25: =(($B25/I$13*$E25)+($C25*$E25)) -> 0 | J25: =(($B25/J$13*$E25)+($C25*$E25)) -> 0 | K25: =(($B25/K$13*$E25)+($C25*$E25)) -> 0 | L25: =(($B25/L$13*$E25)+($C25*$E25)) -> 0 | M25: =(($B25/M$13*$E25)+($C25*$E25)) -> 0
C26: Labor | E26: Basic LABOR | F26: =SUM(F16:F25) -> 0 | G26: =SUM(G16:G25) -> 0 | H26: =SUM(H16:H25) -> 0 | I26: =SUM(I16:I25) -> 0 | J26: =SUM(J16:J25) -> 0 | K26: =SUM(K16:K25) -> 0 | L26: =SUM(L16:L25) -> 0 | M26: =SUM(M16:M25) -> 0 | N26: =SUM(N14:N25) -> 0
B27: T. setup | C27: T.RUN | E27: hrs | F27: =(($B$28/F13)+$C$28)/60 -> 0 | G27: =(($B$28/G13)+$C$28)/60 -> 0 | H27: =(($B$28/H13)+$C$28)/60 -> 0 | I27: =(($B$28/I13)+$C$28)/60 -> 0 | J27: =(($B$28/J13)+$C$28)/60 -> 0 | K27: =(($B$28/K13)+$C$28)/60 -> 0 | L27: =(($B$28/L13)+$C$28)/60 -> 0 | M27: =(($B$28/M13)+$C$28)/60 -> 0
B28: =SUM(B16:B25) -> 0 | C28: =SUM(C16:C25) -> 0 | D28: 0 | E28: BURDEN | F28: =F26*$D$28 -> 0 | G28: =G26*$D$28 -> 0 | H28: =H26*$D$28 -> 0 | I28: =I26*$D$28 -> 0 | J28: =J26*$D$28 -> 0 | K28: =K26*$D$28 -> 0 | L28: =L26*$D$28 -> 0 | M28: =M26*$D$28 -> 0
E30: Total | F30: =F26+F28 -> 0 | G30: =G26+G28 -> 0 | H30: =H26+H28 -> 0 | I30: =I26+I28 -> 0 | J30: =J26+J28 -> 0 | K30: =K26+K28 -> 0 | L30: =L26+L28 -> 0 | M30: =M26+M28 -> 0 | N30: =N26 -> 0
A32: RAW MATERIALS & HARDWARE | B32: Matl UoM | C32: PARTS QTY | D32: UNIT PRICE | E32: MAT'l BURDEN | F32: ="Qty: "& F13 -> Qty: 10 | G32: ="Qty: "& G13 -> Qty: 25 | H32: ="Qty: "& H13 -> Qty: 50 | I32: ="Qty: "& I13 -> Qty: 75 | J32: ="Qty: "& J13 -> Qty: 100 | K32: ="Qty: "& K13 -> Qty: 250 | L32: ="Qty: "& L13 -> Qty: 500 | M32: ="Qty: "& M13 -> Qty: 1000 | N32: Amortize/ Min Buy
E33: =C33*D33 -> 0 | F33: =IF($N33=TRUE,$E33/F$13,$E33*(1+(1/F$13))) -> 0 | G33: =IF($N33=TRUE,$E33/G$13,$E33*(1+(1/G$13))) -> 0 | H33: =IF($N33=TRUE,$E33/H$13,$E33*(1+(1/H$13))) -> 0 | I33: =IF($N33=TRUE,$E33/I$13,$E33*(1+(1/I$13))) -> 0 | J33: =IF($N33=TRUE,$E33/J$13,$E33*(1+(1/J$13))) -> 0 | K33: =IF($N33=TRUE,$E33/K$13,$E33*(1+(1/K$13))) -> 0 | L33: =IF($N33=TRUE,$E33/L$13,$E33*(1+(1/L$13))) -> 0 | M33: =IF($N33=TRUE,$E33/M$13,$E33*(1+(1/M$13))) -> 0 | N33: FALSE
E34: =C34*D34 -> 0 | F34: =IF($N34=TRUE,$E34/F$13,$E34*(1+(1/F$13))) -> 0 | G34: =IF($N34=TRUE,$E34/G$13,$E34*(1+(1/G$13))) -> 0 | H34: =IF($N34=TRUE,$E34/H$13,$E34*(1+(1/H$13))) -> 0 | I34: =IF($N34=TRUE,$E34/I$13,$E34*(1+(1/I$13))) -> 0 | J34: =IF($N34=TRUE,$E34/J$13,$E34*(1+(1/J$13))) -> 0 | K34: =IF($N34=TRUE,$E34/K$13,$E34*(1+(1/K$13))) -> 0 | L34: =IF($N34=TRUE,$E34/L$13,$E34*(1+(1/L$13))) -> 0 | M34: =IF($N34=TRUE,$E34/M$13,$E34*(1+(1/M$13))) -> 0 | N34: FALSE
E35: =C35*D35 -> 0 | F35: =IF($N35=TRUE,$E35/F$13,$E35*(1+(1/F$13))) -> 0 | G35: =IF($N35=TRUE,$E35/G$13,$E35*(1+(1/G$13))) -> 0 | H35: =IF($N35=TRUE,$E35/H$13,$E35*(1+(1/H$13))) -> 0 | I35: =IF($N35=TRUE,$E35/I$13,$E35*(1+(1/I$13))) -> 0 | J35: =IF($N35=TRUE,$E35/J$13,$E35*(1+(1/J$13))) -> 0 | K35: =IF($N35=TRUE,$E35/K$13,$E35*(1+(1/K$13))) -> 0 | L35: =IF($N35=TRUE,$E35/L$13,$E35*(1+(1/L$13))) -> 0 | M35: =IF($N35=TRUE,$E35/M$13,$E35*(1+(1/M$13))) -> 0 | N35: FALSE | S35: QTY | T35: Total
E36: =C36*D36 -> 0 | F36: =IF($N36=TRUE,$E36/F$13,$E36*(1+(1/F$13))) -> 0 | G36: =IF($N36=TRUE,$E36/G$13,$E36*(1+(1/G$13))) -> 0 | H36: =IF($N36=TRUE,$E36/H$13,$E36*(1+(1/H$13))) -> 0 | I36: =IF($N36=TRUE,$E36/I$13,$E36*(1+(1/I$13))) -> 0 | J36: =IF($N36=TRUE,$E36/J$13,$E36*(1+(1/J$13))) -> 0 | K36: =IF($N36=TRUE,$E36/K$13,$E36*(1+(1/K$13))) -> 0 | L36: =IF($N36=TRUE,$E36/L$13,$E36*(1+(1/L$13))) -> 0 | M36: =IF($N36=TRUE,$E36/M$13,$E36*(1+(1/M$13))) -> 0 | N36: FALSE | S36: =M13 -> 1000 | T36: =M63 -> 0
E37: =C37*D37 -> 0 | F37: =IF($N37=TRUE,$E37/F$13,$E37*(1+(1/F$13))) -> 0 | G37: =IF($N37=TRUE,$E37/G$13,$E37*(1+(1/G$13))) -> 0 | H37: =IF($N37=TRUE,$E37/H$13,$E37*(1+(1/H$13))) -> 0 | I37: =IF($N37=TRUE,$E37/I$13,$E37*(1+(1/I$13))) -> 0 | J37: =IF($N37=TRUE,$E37/J$13,$E37*(1+(1/J$13))) -> 0 | K37: =IF($N37=TRUE,$E37/K$13,$E37*(1+(1/K$13))) -> 0 | L37: =IF($N37=TRUE,$E37/L$13,$E37*(1+(1/L$13))) -> 0 | M37: =IF($N37=TRUE,$E37/M$13,$E37*(1+(1/M$13))) -> 0 | N37: FALSE | S37: =L13 -> 500 | T37: =L63 -> 0
E38: =C38*D38 -> 0 | F38: =IF($N38=TRUE,$E38/F$13,$E38*(1+(1/F$13))) -> 0 | G38: =IF($N38=TRUE,$E38/G$13,$E38*(1+(1/G$13))) -> 0 | H38: =IF($N38=TRUE,$E38/H$13,$E38*(1+(1/H$13))) -> 0 | I38: =IF($N38=TRUE,$E38/I$13,$E38*(1+(1/I$13))) -> 0 | J38: =IF($N38=TRUE,$E38/J$13,$E38*(1+(1/J$13))) -> 0 | K38: =IF($N38=TRUE,$E38/K$13,$E38*(1+(1/K$13))) -> 0 | L38: =IF($N38=TRUE,$E38/L$13,$E38*(1+(1/L$13))) -> 0 | M38: =IF($N38=TRUE,$E38/M$13,$E38*(1+(1/M$13))) -> 0 | N38: FALSE | S38: =I13 -> 75 | T38: =I63 -> 0
E39: =C39*D39 -> 0 | F39: =IF($N39=TRUE,$E39/F$13,$E39*(1+(1/F$13))) -> 0 | G39: =IF($N39=TRUE,$E39/G$13,$E39*(1+(1/G$13))) -> 0 | H39: =IF($N39=TRUE,$E39/H$13,$E39*(1+(1/H$13))) -> 0 | I39: =IF($N39=TRUE,$E39/I$13,$E39*(1+(1/I$13))) -> 0 | J39: =IF($N39=TRUE,$E39/J$13,$E39*(1+(1/J$13))) -> 0 | K39: =IF($N39=TRUE,$E39/K$13,$E39*(1+(1/K$13))) -> 0 | L39: =IF($N39=TRUE,$E39/L$13,$E39*(1+(1/L$13))) -> 0 | M39: =IF($N39=TRUE,$E39/M$13,$E39*(1+(1/M$13))) -> 0 | N39: FALSE | S39: =H13 -> 50 | T39: =H63 -> 0
E40: =C40*D40 -> 0 | F40: =IF($N40=TRUE,$E40/F$13,$E40*(1+(1/F$13))) -> 0 | G40: =IF($N40=TRUE,$E40/G$13,$E40*(1+(1/G$13))) -> 0 | H40: =IF($N40=TRUE,$E40/H$13,$E40*(1+(1/H$13))) -> 0 | I40: =IF($N40=TRUE,$E40/I$13,$E40*(1+(1/I$13))) -> 0 | J40: =IF($N40=TRUE,$E40/J$13,$E40*(1+(1/J$13))) -> 0 | K40: =IF($N40=TRUE,$E40/K$13,$E40*(1+(1/K$13))) -> 0 | L40: =IF($N40=TRUE,$E40/L$13,$E40*(1+(1/L$13))) -> 0 | M40: =IF($N40=TRUE,$E40/M$13,$E40*(1+(1/M$13))) -> 0 | N40: FALSE | S40: =G13 -> 25 | T40: =G63 -> 0
E41: =C41*D41 -> 0 | F41: =IF($N41=TRUE,$E41/F$13,$E41*(1+(1/F$13))) -> 0 | G41: =IF($N41=TRUE,$E41/G$13,$E41*(1+(1/G$13))) -> 0 | H41: =IF($N41=TRUE,$E41/H$13,$E41*(1+(1/H$13))) -> 0 | I41: =IF($N41=TRUE,$E41/I$13,$E41*(1+(1/I$13))) -> 0 | J41: =IF($N41=TRUE,$E41/J$13,$E41*(1+(1/J$13))) -> 0 | K41: =IF($N41=TRUE,$E41/K$13,$E41*(1+(1/K$13))) -> 0 | L41: =IF($N41=TRUE,$E41/L$13,$E41*(1+(1/L$13))) -> 0 | M41: =IF($N41=TRUE,$E41/M$13,$E41*(1+(1/M$13))) -> 0 | N41: FALSE | S41: =F13 -> 10 | T41: =F63 -> 0
E42: =C42*D42 -> 0 | F42: =IF($N42=TRUE,$E42/F$13,$E42*(1+(1/F$13))) -> 0 | G42: =IF($N42=TRUE,$E42/G$13,$E42*(1+(1/G$13))) -> 0 | H42: =IF($N42=TRUE,$E42/H$13,$E42*(1+(1/H$13))) -> 0 | I42: =IF($N42=TRUE,$E42/I$13,$E42*(1+(1/I$13))) -> 0 | J42: =IF($N42=TRUE,$E42/J$13,$E42*(1+(1/J$13))) -> 0 | K42: =IF($N42=TRUE,$E42/K$13,$E42*(1+(1/K$13))) -> 0 | L42: =IF($N42=TRUE,$E42/L$13,$E42*(1+(1/L$13))) -> 0 | M42: =IF($N42=TRUE,$E42/M$13,$E42*(1+(1/M$13))) -> 0 | N42: FALSE
E43: =C43*D43 -> 0 | F43: =IF($N43=TRUE,$E43/F$13,$E43*(1+(1/F$13))) -> 0 | G43: =IF($N43=TRUE,$E43/G$13,$E43*(1+(1/G$13))) -> 0 | H43: =IF($N43=TRUE,$E43/H$13,$E43*(1+(1/H$13))) -> 0 | I43: =IF($N43=TRUE,$E43/I$13,$E43*(1+(1/I$13))) -> 0 | J43: =IF($N43=TRUE,$E43/J$13,$E43*(1+(1/J$13))) -> 0 | K43: =IF($N43=TRUE,$E43/K$13,$E43*(1+(1/K$13))) -> 0 | L43: =IF($N43=TRUE,$E43/L$13,$E43*(1+(1/L$13))) -> 0 | M43: =IF($N43=TRUE,$E43/M$13,$E43*(1+(1/M$13))) -> 0 | N43: FALSE
E44: =C44*D44 -> 0 | F44: =IF($N44=TRUE,$E44/F$13,$E44*(1+(1/F$13))) -> 0 | G44: =IF($N44=TRUE,$E44/G$13,$E44*(1+(1/G$13))) -> 0 | H44: =IF($N44=TRUE,$E44/H$13,$E44*(1+(1/H$13))) -> 0 | I44: =IF($N44=TRUE,$E44/I$13,$E44*(1+(1/I$13))) -> 0 | J44: =IF($N44=TRUE,$E44/J$13,$E44*(1+(1/J$13))) -> 0 | K44: =IF($N44=TRUE,$E44/K$13,$E44*(1+(1/K$13))) -> 0 | L44: =IF($N44=TRUE,$E44/L$13,$E44*(1+(1/L$13))) -> 0 | M44: =IF($N44=TRUE,$E44/M$13,$E44*(1+(1/M$13))) -> 0 | N44: FALSE
A45: PROCESSES/COMPONENTS | D45: SETUP $ | E45: RUN$ EA.
F46: =($D46/F$13)+$E46 -> 0 | G46: =($D46/G$13)+$E46 -> 0 | H46: =($D46/H$13)+$E46 -> 0 | I46: =($D46/I$13)+$E46 -> 0 | J46: =($D46/J$13)+$E46 -> 0 | K46: =($D46/K$13)+$E46 -> 0 | L46: =($D46/L$13)+$E46 -> 0 | M46: =($D46/M$13)+$E46 -> 0
F47: =($D47/F$13)+$E47 -> 0 | G47: =($D47/G$13)+$E47 -> 0 | H47: =($D47/H$13)+$E47 -> 0 | I47: =($D47/I$13)+$E47 -> 0 | J47: =($D47/J$13)+$E47 -> 0 | K47: =($D47/K$13)+$E47 -> 0 | L47: =($D47/L$13)+$E47 -> 0 | M47: =($D47/M$13)+$E47 -> 0
F48: =($D48/F$13)+$E48 -> 0 | G48: =($D48/G$13)+$E48 -> 0 | H48: =($D48/H$13)+$E48 -> 0 | I48: =($D48/I$13)+$E48 -> 0 | J48: =($D48/J$13)+$E48 -> 0 | K48: =($D48/K$13)+$E48 -> 0 | L48: =($D48/L$13)+$E48 -> 0 | M48: =($D48/M$13)+$E48 -> 0
F49: =($D49/F$13)+$E49 -> 0 | G49: =($D49/G$13)+$E49 -> 0 | H49: =($D49/H$13)+$E49 -> 0 | I49: =($D49/I$13)+$E49 -> 0 | J49: =($D49/J$13)+$E49 -> 0 | K49: =($D49/K$13)+$E49 -> 0 | L49: =($D49/L$13)+$E49 -> 0 | M49: =($D49/M$13)+$E49 -> 0
F50: =($D50/F$13)+$E50 -> 0 | G50: =($D50/G$13)+$E50 -> 0 | H50: =($D50/H$13)+$E50 -> 0 | I50: =($D50/I$13)+$E50 -> 0 | J50: =($D50/J$13)+$E50 -> 0 | K50: =($D50/K$13)+$E50 -> 0 | L50: =($D50/L$13)+$E50 -> 0 | M50: =($D50/M$13)+$E50 -> 0
B51: MATERIAL & HARDWARE TOTAL | F51: =SUM(F33:F44) -> 0 | G51: =SUM(G33:G44) -> 0 | H51: =SUM(H33:H44) -> 0 | I51: =SUM(I33:I44) -> 0 | J51: =SUM(J33:J44) -> 0 | K51: =SUM(K33:K44) -> 0 | L51: =SUM(L33:L44) -> 0 | M51: =SUM(M33:M44) -> 0 | N51: =IF(N13=0,0,SUM(N42:N44)) -> 0
B52: PROCESSES TOTAL | F52: =SUM(F46:F50) -> 0 | G52: =SUM(G46:G50) -> 0 | H52: =SUM(H46:H50) -> 0 | I52: =SUM(I46:I50) -> 0 | J52: =SUM(J46:J50) -> 0 | K52: =SUM(K46:K50) -> 0 | L52: =SUM(L46:L50) -> 0 | M52: =SUM(M46:M50) -> 0 | N52: =IF(N13=0,0,SUM(N46:N50)) -> 0
B53: M+L Subtotal | F53: =SUM(F30+F51+F52) -> 0 | G53: =SUM(G30+G51+G52) -> 0 | H53: =SUM(H30+H51+H52) -> 0 | I53: =SUM(I30+I51+I52) -> 0 | J53: =SUM(J30+J51+J52) -> 0 | K53: =SUM(K30+K51+K52) -> 0 | L53: =SUM(L30+L51+L52) -> 0 | M53: =SUM(M30+M51+M52) -> 0 | N53: =IF(N13=0,0,SUM(N30+N51+N52)) -> 0
E55: REFERENCE | F55: =SUM(F53+#REF!+#REF!) -> #REF! | G55: =SUM(G53+#REF!+#REF!) -> #REF! | H55: =SUM(H53+#REF!+#REF!) -> #REF! | I55: =SUM(I53+#REF!+#REF!) -> #REF! | J55: =SUM(J53+#REF!+#REF!) -> #REF! | K55: =SUM(K53+#REF!+#REF!) -> #REF! | L55: =SUM(L53+#REF!+#REF!) -> #REF! | M55: =SUM(M53+#REF!+#REF!) -> #REF! | N55: =SUM(N53+#REF!+#REF!) -> #REF!
D56: MARGIN | F56: =(F55-F53)/F55 -> #REF! | G56: =(G55-G53)/G55 -> #REF! | H56: =(H55-H53)/H55 -> #REF! | I56: =(I55-I53)/I55 -> #REF! | J56: =(J55-J53)/J55 -> #REF! | K56: =(K55-K53)/K55 -> #REF! | L56: =(L55-L53)/L55 -> #REF! | M56: =(M55-M53)/M55 -> #REF!
D57: LABOR | F57: =F30 -> 0 | G57: =G30 -> 0 | H57: =H30 -> 0 | I57: =I30 -> 0 | J57: =J30 -> 0 | K57: =K30 -> 0 | L57: =L30 -> 0 | M57: =M30 -> 0 | N57: =SUM((N30)) -> 0
C58: MAT'ls &HARDWARE | F58: =F51 -> 0 | G58: =G51 -> 0 | H58: =H51 -> 0 | I58: =I51 -> 0 | J58: =J51 -> 0 | K58: =K51 -> 0 | L58: =L51 -> 0 | M58: =M51 -> 0 | N58: =(N51) -> 0
D59: PROCESS | F59: =F52 -> 0 | G59: =G52 -> 0 | H59: =H52 -> 0 | I59: =I52 -> 0 | J59: =J52 -> 0 | K59: =K52 -> 0 | L59: =L52 -> 0 | M59: =M52 -> 0 | N59: =N52 -> 0
D60: Subtotal | F60: =SUM(F57:F59) -> 0 | G60: =SUM(G57:G59) -> 0 | H60: =SUM(H57:H59) -> 0 | I60: =SUM(I57:I59) -> 0 | J60: =SUM(J57:J59) -> 0 | K60: =SUM(K57:K59) -> 0 | L60: =SUM(L57:L59) -> 0 | M60: =SUM(M57:M59) -> 0 | N60: =SUM(N57:N59) -> 0
D61: AMORTIZED | F61: =$N$60/F13 -> 0 | G61: =$N$60/G13 -> 0 | H61: =$N$60/H13 -> 0 | I61: =$N$60/I13 -> 0 | J61: =$N$60/J13 -> 0 | K61: =$N$60/K13 -> 0 | L61: =$N$60/L13 -> 0 | M61: =$N$60/M13 -> 0
D62: Facilities | F62: 0 | G62: 0 | H62: 0 | I62: 0 | J62: 0 | K62: 0 | L62: 0 | M62: 0
D63: =B3 -> 4 | F63: =SUM(F60:F62) -> 0 | G63: =SUM(G60:G62) -> 0 | H63: =SUM(H60:H62) -> 0 | I63: =SUM(I60:I62) -> 0 | J63: =SUM(J60:J62) -> 0 | K63: =SUM(K60:K62) -> 0 | L63: =SUM(L60:L62) -> 0 | M63: =SUM(M60:M62) -> 0
A66: NRESC/TOOLING
A67: SETUPS
A68: FAIR
A69: SOURCE

Sheet Subassy 5
A2: CUSTOMER: | F2: Comments:
A3: P/N: | B3: 5 | D3: NSN #:
A4: REV: | D4: SOL #:
A5: QUOTE LOG No.: | D5: RFQ #:
A6: QTY: | B6: =F13&", "&G13&", "&H13&", "&I13&", "&J13&", "&K13&", "&L13&", "&M13 -> 10, 25, 50, 75, 100, 250, 500, 1000
A7: DATE:
A8: ESTIMATOR:
A11: MANUFACTURING OPERATIONS | F11: COST ESTIMATED QUANTITIES | N11: NRE/SET-UP
B13: SET-UP TIME | C13: RUN TIME | E13: LABOR RATE | F13: ='Top Assy'!F13 -> 10 | G13: ='Top Assy'!G13 -> 25 | H13: ='Top Assy'!H13 -> 50 | I13: ='Top Assy'!I13 -> 75 | J13: ='Top Assy'!J13 -> 100 | K13: ='Top Assy'!K13 -> 250 | L13: ='Top Assy'!L13 -> 500 | M13: ='Top Assy'!M13 -> 1000 | N13: 1
A14: Program | E14: 0 | N14: =(($B14/N$13*$E14)+($C14*$E14)) -> 0
A15: Fixtures | E15: 0 | N15: =(($B15/N$13*$E15)+($C15*$E15)) -> 0
A16: Mill/Turn | E16: 0 | F16: =(($B16/F$13*$E16)+($C16*$E16)) -> 0 | G16: =(($B16/G$13*$E16)+($C16*$E16)) -> 0 | H16: =(($B16/H$13*$E16)+($C16*$E16)) -> 0 | I16: =(($B16/I$13*$E16)+($C16*$E16)) -> 0 | J16: =(($B16/J$13*$E16)+($C16*$E16)) -> 0 | K16: =(($B16/K$13*$E16)+($C16*$E16)) -> 0 | L16: =(($B16/L$13*$E16)+($C16*$E16)) -> 0 | M16: =(($B16/M$13*$E16)+($C16*$E16)) -> 0
A17: Metals - Mills | E17: 0 | F17: =(($B17/F$13*$E17)+($C17*$E17)) -> 0 | G17: =(($B17/G$13*$E17)+($C17*$E17)) -> 0 | H17: =(($B17/H$13*$E17)+($C17*$E17)) -> 0 | I17: =(($B17/I$13*$E17)+($C17*$E17)) -> 0 | J17: =(($B17/J$13*$E17)+($C17*$E17)) -> 0 | K17: =(($B17/K$13*$E17)+($C17*$E17)) -> 0 | L17: =(($B17/L$13*$E17)+($C17*$E17)) -> 0 | M17: =(($B17/M$13*$E17)+($C17*$E17)) -> 0
A18: Metals - Lathe | E18: 0 | F18: =(($B18/F$13*$E18)+($C18*$E18)) -> 0 | G18: =(($B18/G$13*$E18)+($C18*$E18)) -> 0 | H18: =(($B18/H$13*$E18)+($C18*$E18)) -> 0 | I18: =(($B18/I$13*$E18)+($C18*$E18)) -> 0 | J18: =(($B18/J$13*$E18)+($C18*$E18)) -> 0 | K18: =(($B18/K$13*$E18)+($C18*$E18)) -> 0 | L18: =(($B18/L$13*$E18)+($C18*$E18)) -> 0 | M18: =(($B18/M$13*$E18)+($C18*$E18)) -> 0
A19: Rubber Mold | E19: 0 | F19: =(($B19/F$13*$E19)+($C19*$E19)) -> 0 | G19: =(($B19/G$13*$E19)+($C19*$E19)) -> 0 | H19: =(($B19/H$13*$E19)+($C19*$E19)) -> 0 | I19: =(($B19/I$13*$E19)+($C19*$E19)) -> 0 | J19: =(($B19/J$13*$E19)+($C19*$E19)) -> 0 | K19: =(($B19/K$13*$E19)+($C19*$E19)) -> 0 | L19: =(($B19/L$13*$E19)+($C19*$E19)) -> 0 | M19: =(($B19/M$13*$E19)+($C19*$E19)) -> 0
A20: Plastic Injection Mold | E20: 0 | F20: =(($B20/F$13*$E20)+($C20*$E20)) -> 0 | G20: =(($B20/G$13*$E20)+($C20*$E20)) -> 0 | H20: =(($B20/H$13*$E20)+($C20*$E20)) -> 0 | I20: =(($B20/I$13*$E20)+($C20*$E20)) -> 0 | J20: =(($B20/J$13*$E20)+($C20*$E20)) -> 0 | K20: =(($B20/K$13*$E20)+($C20*$E20)) -> 0 | L20: =(($B20/L$13*$E20)+($C20*$E20)) -> 0 | M20: =(($B20/M$13*$E20)+($C20*$E20)) -> 0
A21: Plastic Compression Mold | E21: 0 | F21: =(($B21/F$13*$E21)+($C21*$E21)) -> 0 | G21: =(($B21/G$13*$E21)+($C21*$E21)) -> 0 | H21: =(($B21/H$13*$E21)+($C21*$E21)) -> 0 | I21: =(($B21/I$13*$E21)+($C21*$E21)) -> 0 | J21: =(($B21/J$13*$E21)+($C21*$E21)) -> 0 | K21: =(($B21/K$13*$E21)+($C21*$E21)) -> 0 | L21: =(($B21/L$13*$E21)+($C21*$E21)) -> 0 | M21: =(($B21/M$13*$E21)+($C21*$E21)) -> 0
A22: Waterjet - Setup | E22: 0 | F22: =(($B22/F$13*$E22)+($C22*$E22)) -> 0 | G22: =(($B22/G$13*$E22)+($C22*$E22)) -> 0 | H22: =(($B22/H$13*$E22)+($C22*$E22)) -> 0 | I22: =(($B22/I$13*$E22)+($C22*$E22)) -> 0 | J22: =(($B22/J$13*$E22)+($C22*$E22)) -> 0 | K22: =(($B22/K$13*$E22)+($C22*$E22)) -> 0 | L22: =(($B22/L$13*$E22)+($C22*$E22)) -> 0 | M22: =(($B22/M$13*$E22)+($C22*$E22)) -> 0
A23: Waterjet - Operator | E23: 0 | F23: =(($B23/F$13*$E23)+($C23*$E23)) -> 0 | G23: =(($B23/G$13*$E23)+($C23*$E23)) -> 0 | H23: =(($B23/H$13*$E23)+($C23*$E23)) -> 0 | I23: =(($B23/I$13*$E23)+($C23*$E23)) -> 0 | J23: =(($B23/J$13*$E23)+($C23*$E23)) -> 0 | K23: =(($B23/K$13*$E23)+($C23*$E23)) -> 0 | L23: =(($B23/L$13*$E23)+($C23*$E23)) -> 0 | M23: =(($B23/M$13*$E23)+($C23*$E23)) -> 0
A24: Assembly, Die Punch, Deburr | E24: 0 | F24: =(($B24/F$13*$E24)+($C24*$E24)) -> 0 | G24: =(($B24/G$13*$E24)+($C24*$E24)) -> 0 | H24: =(($B24/H$13*$E24)+($C24*$E24)) -> 0 | I24: =(($B24/I$13*$E24)+($C24*$E24)) -> 0 | J24: =(($B24/J$13*$E24)+($C24*$E24)) -> 0 | K24: =(($B24/K$13*$E24)+($C24*$E24)) -> 0 | L24: =(($B24/L$13*$E24)+($C24*$E24)) -> 0 | M24: =(($B24/M$13*$E24)+($C24*$E24)) -> 0
A25: Quality Inspection | E25: 0 | F25: =(($B25/F$13*$E25)+($C25*$E25)) -> 0 | G25: =(($B25/G$13*$E25)+($C25*$E25)) -> 0 | H25: =(($B25/H$13*$E25)+($C25*$E25)) -> 0 | I25: =(($B25/I$13*$E25)+($C25*$E25)) -> 0 | J25: =(($B25/J$13*$E25)+($C25*$E25)) -> 0 | K25: =(($B25/K$13*$E25)+($C25*$E25)) -> 0 | L25: =(($B25/L$13*$E25)+($C25*$E25)) -> 0 | M25: =(($B25/M$13*$E25)+($C25*$E25)) -> 0
C26: Labor | E26: Basic LABOR | F26: =SUM(F16:F25) -> 0 | G26: =SUM(G16:G25) -> 0 | H26: =SUM(H16:H25) -> 0 | I26: =SUM(I16:I25) -> 0 | J26: =SUM(J16:J25) -> 0 | K26: =SUM(K16:K25) -> 0 | L26: =SUM(L16:L25) -> 0 | M26: =SUM(M16:M25) -> 0 | N26: =SUM(N14:N25) -> 0
B27: T. setup | C27: T.RUN | E27: hrs | F27: =(($B$28/F13)+$C$28)/60 -> 0 | G27: =(($B$28/G13)+$C$28)/60 -> 0 | H27: =(($B$28/H13)+$C$28)/60 -> 0 | I27: =(($B$28/I13)+$C$28)/60 -> 0 | J27: =(($B$28/J13)+$C$28)/60 -> 0 | K27: =(($B$28/K13)+$C$28)/60 -> 0 | L27: =(($B$28/L13)+$C$28)/60 -> 0 | M27: =(($B$28/M13)+$C$28)/60 -> 0
B28: =SUM(B16:B25) -> 0 | C28: =SUM(C16:C25) -> 0 | D28: 0 | E28: BURDEN | F28: =F26*$D$28 -> 0 | G28: =G26*$D$28 -> 0 | H28: =H26*$D$28 -> 0 | I28: =I26*$D$28 -> 0 | J28: =J26*$D$28 -> 0 | K28: =K26*$D$28 -> 0 | L28: =L26*$D$28 -> 0 | M28: =M26*$D$28 -> 0
E30: Total | F30: =F26+F28 -> 0 | G30: =G26+G28 -> 0 | H30: =H26+H28 -> 0 | I30: =I26+I28 -> 0 | J30: =J26+J28 -> 0 | K30: =K26+K28 -> 0 | L30: =L26+L28 -> 0 | M30: =M26+M28 -> 0 | N30: =N26 -> 0
A32: RAW MATERIALS & HARDWARE | B32: Matl UoM | C32: PARTS QTY | D32: UNIT PRICE | E32: MAT'l BURDEN | F32: ="Qty: "& F13 -> Qty: 10 | G32: ="Qty: "& G13 -> Qty: 25 | H32: ="Qty: "& H13 -> Qty: 50 | I32: ="Qty: "& I13 -> Qty: 75 | J32: ="Qty: "& J13 -> Qty: 100 | K32: ="Qty: "& K13 -> Qty: 250 | L32: ="Qty: "& L13 -> Qty: 500 | M32: ="Qty: "& M13 -> Qty: 1000 | N32: Amortize/ Min Buy
E33: =C33*D33 -> 0 | F33: =IF($N33=TRUE,$E33/F$13,$E33*(1+(1/F$13))) -> 0 | G33: =IF($N33=TRUE,$E33/G$13,$E33*(1+(1/G$13))) -> 0 | H33: =IF($N33=TRUE,$E33/H$13,$E33*(1+(1/H$13))) -> 0 | I33: =IF($N33=TRUE,$E33/I$13,$E33*(1+(1/I$13))) -> 0 | J33: =IF($N33=TRUE,$E33/J$13,$E33*(1+(1/J$13))) -> 0 | K33: =IF($N33=TRUE,$E33/K$13,$E33*(1+(1/K$13))) -> 0 | L33: =IF($N33=TRUE,$E33/L$13,$E33*(1+(1/L$13))) -> 0 | M33: =IF($N33=TRUE,$E33/M$13,$E33*(1+(1/M$13))) -> 0 | N33: FALSE
E34: =C34*D34 -> 0 | F34: =IF($N34=TRUE,$E34/F$13,$E34*(1+(1/F$13))) -> 0 | G34: =IF($N34=TRUE,$E34/G$13,$E34*(1+(1/G$13))) -> 0 | H34: =IF($N34=TRUE,$E34/H$13,$E34*(1+(1/H$13))) -> 0 | I34: =IF($N34=TRUE,$E34/I$13,$E34*(1+(1/I$13))) -> 0 | J34: =IF($N34=TRUE,$E34/J$13,$E34*(1+(1/J$13))) -> 0 | K34: =IF($N34=TRUE,$E34/K$13,$E34*(1+(1/K$13))) -> 0 | L34: =IF($N34=TRUE,$E34/L$13,$E34*(1+(1/L$13))) -> 0 | M34: =IF($N34=TRUE,$E34/M$13,$E34*(1+(1/M$13))) -> 0 | N34: FALSE
E35: =C35*D35 -> 0 | F35: =IF($N35=TRUE,$E35/F$13,$E35*(1+(1/F$13))) -> 0 | G35: =IF($N35=TRUE,$E35/G$13,$E35*(1+(1/G$13))) -> 0 | H35: =IF($N35=TRUE,$E35/H$13,$E35*(1+(1/H$13))) -> 0 | I35: =IF($N35=TRUE,$E35/I$13,$E35*(1+(1/I$13))) -> 0 | J35: =IF($N35=TRUE,$E35/J$13,$E35*(1+(1/J$13))) -> 0 | K35: =IF($N35=TRUE,$E35/K$13,$E35*(1+(1/K$13))) -> 0 | L35: =IF($N35=TRUE,$E35/L$13,$E35*(1+(1/L$13))) -> 0 | M35: =IF($N35=TRUE,$E35/M$13,$E35*(1+(1/M$13))) -> 0 | N35: FALSE | S35: QTY | T35: Total
E36: =C36*D36 -> 0 | F36: =IF($N36=TRUE,$E36/F$13,$E36*(1+(1/F$13))) -> 0 | G36: =IF($N36=TRUE,$E36/G$13,$E36*(1+(1/G$13))) -> 0 | H36: =IF($N36=TRUE,$E36/H$13,$E36*(1+(1/H$13))) -> 0 | I36: =IF($N36=TRUE,$E36/I$13,$E36*(1+(1/I$13))) -> 0 | J36: =IF($N36=TRUE,$E36/J$13,$E36*(1+(1/J$13))) -> 0 | K36: =IF($N36=TRUE,$E36/K$13,$E36*(1+(1/K$13))) -> 0 | L36: =IF($N36=TRUE,$E36/L$13,$E36*(1+(1/L$13))) -> 0 | M36: =IF($N36=TRUE,$E36/M$13,$E36*(1+(1/M$13))) -> 0 | N36: FALSE | S36: =M13 -> 1000 | T36: =M63 -> 0
E37: =C37*D37 -> 0 | F37: =IF($N37=TRUE,$E37/F$13,$E37*(1+(1/F$13))) -> 0 | G37: =IF($N37=TRUE,$E37/G$13,$E37*(1+(1/G$13))) -> 0 | H37: =IF($N37=TRUE,$E37/H$13,$E37*(1+(1/H$13))) -> 0 | I37: =IF($N37=TRUE,$E37/I$13,$E37*(1+(1/I$13))) -> 0 | J37: =IF($N37=TRUE,$E37/J$13,$E37*(1+(1/J$13))) -> 0 | K37: =IF($N37=TRUE,$E37/K$13,$E37*(1+(1/K$13))) -> 0 | L37: =IF($N37=TRUE,$E37/L$13,$E37*(1+(1/L$13))) -> 0 | M37: =IF($N37=TRUE,$E37/M$13,$E37*(1+(1/M$13))) -> 0 | N37: FALSE | S37: =L13 -> 500 | T37: =L63 -> 0
E38: =C38*D38 -> 0 | F38: =IF($N38=TRUE,$E38/F$13,$E38*(1+(1/F$13))) -> 0 | G38: =IF($N38=TRUE,$E38/G$13,$E38*(1+(1/G$13))) -> 0 | H38: =IF($N38=TRUE,$E38/H$13,$E38*(1+(1/H$13))) -> 0 | I38: =IF($N38=TRUE,$E38/I$13,$E38*(1+(1/I$13))) -> 0 | J38: =IF($N38=TRUE,$E38/J$13,$E38*(1+(1/J$13))) -> 0 | K38: =IF($N38=TRUE,$E38/K$13,$E38*(1+(1/K$13))) -> 0 | L38: =IF($N38=TRUE,$E38/L$13,$E38*(1+(1/L$13))) -> 0 | M38: =IF($N38=TRUE,$E38/M$13,$E38*(1+(1/M$13))) -> 0 | N38: FALSE | S38: =I13 -> 75 | T38: =I63 -> 0
E39: =C39*D39 -> 0 | F39: =IF($N39=TRUE,$E39/F$13,$E39*(1+(1/F$13))) -> 0 | G39: =IF($N39=TRUE,$E39/G$13,$E39*(1+(1/G$13))) -> 0 | H39: =IF($N39=TRUE,$E39/H$13,$E39*(1+(1/H$13))) -> 0 | I39: =IF($N39=TRUE,$E39/I$13,$E39*(1+(1/I$13))) -> 0 | J39: =IF($N39=TRUE,$E39/J$13,$E39*(1+(1/J$13))) -> 0 | K39: =IF($N39=TRUE,$E39/K$13,$E39*(1+(1/K$13))) -> 0 | L39: =IF($N39=TRUE,$E39/L$13,$E39*(1+(1/L$13))) -> 0 | M39: =IF($N39=TRUE,$E39/M$13,$E39*(1+(1/M$13))) -> 0 | N39: FALSE | S39: =H13 -> 50 | T39: =H63 -> 0
E40: =C40*D40 -> 0 | F40: =IF($N40=TRUE,$E40/F$13,$E40*(1+(1/F$13))) -> 0 | G40: =IF($N40=TRUE,$E40/G$13,$E40*(1+(1/G$13))) -> 0 | H40: =IF($N40=TRUE,$E40/H$13,$E40*(1+(1/H$13))) -> 0 | I40: =IF($N40=TRUE,$E40/I$13,$E40*(1+(1/I$13))) -> 0 | J40: =IF($N40=TRUE,$E40/J$13,$E40*(1+(1/J$13))) -> 0 | K40: =IF($N40=TRUE,$E40/K$13,$E40*(1+(1/K$13))) -> 0 | L40: =IF($N40=TRUE,$E40/L$13,$E40*(1+(1/L$13))) -> 0 | M40: =IF($N40=TRUE,$E40/M$13,$E40*(1+(1/M$13))) -> 0 | N40: FALSE | S40: =G13 -> 25 | T40: =G63 -> 0
E41: =C41*D41 -> 0 | F41: =IF($N41=TRUE,$E41/F$13,$E41*(1+(1/F$13))) -> 0 | G41: =IF($N41=TRUE,$E41/G$13,$E41*(1+(1/G$13))) -> 0 | H41: =IF($N41=TRUE,$E41/H$13,$E41*(1+(1/H$13))) -> 0 | I41: =IF($N41=TRUE,$E41/I$13,$E41*(1+(1/I$13))) -> 0 | J41: =IF($N41=TRUE,$E41/J$13,$E41*(1+(1/J$13))) -> 0 | K41: =IF($N41=TRUE,$E41/K$13,$E41*(1+(1/K$13))) -> 0 | L41: =IF($N41=TRUE,$E41/L$13,$E41*(1+(1/L$13))) -> 0 | M41: =IF($N41=TRUE,$E41/M$13,$E41*(1+(1/M$13))) -> 0 | N41: FALSE | S41: =F13 -> 10 | T41: =F63 -> 0
E42: =C42*D42 -> 0 | F42: =IF($N42=TRUE,$E42/F$13,$E42*(1+(1/F$13))) -> 0 | G42: =IF($N42=TRUE,$E42/G$13,$E42*(1+(1/G$13))) -> 0 | H42: =IF($N42=TRUE,$E42/H$13,$E42*(1+(1/H$13))) -> 0 | I42: =IF($N42=TRUE,$E42/I$13,$E42*(1+(1/I$13))) -> 0 | J42: =IF($N42=TRUE,$E42/J$13,$E42*(1+(1/J$13))) -> 0 | K42: =IF($N42=TRUE,$E42/K$13,$E42*(1+(1/K$13))) -> 0 | L42: =IF($N42=TRUE,$E42/L$13,$E42*(1+(1/L$13))) -> 0 | M42: =IF($N42=TRUE,$E42/M$13,$E42*(1+(1/M$13))) -> 0 | N42: FALSE
E43: =C43*D43 -> 0 | F43: =IF($N43=TRUE,$E43/F$13,$E43*(1+(1/F$13))) -> 0 | G43: =IF($N43=TRUE,$E43/G$13,$E43*(1+(1/G$13))) -> 0 | H43: =IF($N43=TRUE,$E43/H$13,$E43*(1+(1/H$13))) -> 0 | I43: =IF($N43=TRUE,$E43/I$13,$E43*(1+(1/I$13))) -> 0 | J43: =IF($N43=TRUE,$E43/J$13,$E43*(1+(1/J$13))) -> 0 | K43: =IF($N43=TRUE,$E43/K$13,$E43*(1+(1/K$13))) -> 0 | L43: =IF($N43=TRUE,$E43/L$13,$E43*(1+(1/L$13))) -> 0 | M43: =IF($N43=TRUE,$E43/M$13,$E43*(1+(1/M$13))) -> 0 | N43: FALSE
E44: =C44*D44 -> 0 | F44: =IF($N44=TRUE,$E44/F$13,$E44*(1+(1/F$13))) -> 0 | G44: =IF($N44=TRUE,$E44/G$13,$E44*(1+(1/G$13))) -> 0 | H44: =IF($N44=TRUE,$E44/H$13,$E44*(1+(1/H$13))) -> 0 | I44: =IF($N44=TRUE,$E44/I$13,$E44*(1+(1/I$13))) -> 0 | J44: =IF($N44=TRUE,$E44/J$13,$E44*(1+(1/J$13))) -> 0 | K44: =IF($N44=TRUE,$E44/K$13,$E44*(1+(1/K$13))) -> 0 | L44: =IF($N44=TRUE,$E44/L$13,$E44*(1+(1/L$13))) -> 0 | M44: =IF($N44=TRUE,$E44/M$13,$E44*(1+(1/M$13))) -> 0 | N44: FALSE
A45: PROCESSES/COMPONENTS | D45: SETUP $ | E45: RUN$ EA.
F46: =($D46/F$13)+$E46 -> 0 | G46: =($D46/G$13)+$E46 -> 0 | H46: =($D46/H$13)+$E46 -> 0 | I46: =($D46/I$13)+$E46 -> 0 | J46: =($D46/J$13)+$E46 -> 0 | K46: =($D46/K$13)+$E46 -> 0 | L46: =($D46/L$13)+$E46 -> 0 | M46: =($D46/M$13)+$E46 -> 0
F47: =($D47/F$13)+$E47 -> 0 | G47: =($D47/G$13)+$E47 -> 0 | H47: =($D47/H$13)+$E47 -> 0 | I47: =($D47/I$13)+$E47 -> 0 | J47: =($D47/J$13)+$E47 -> 0 | K47: =($D47/K$13)+$E47 -> 0 | L47: =($D47/L$13)+$E47 -> 0 | M47: =($D47/M$13)+$E47 -> 0
F48: =($D48/F$13)+$E48 -> 0 | G48: =($D48/G$13)+$E48 -> 0 | H48: =($D48/H$13)+$E48 -> 0 | I48: =($D48/I$13)+$E48 -> 0 | J48: =($D48/J$13)+$E48 -> 0 | K48: =($D48/K$13)+$E48 -> 0 | L48: =($D48/L$13)+$E48 -> 0 | M48: =($D48/M$13)+$E48 -> 0
F49: =($D49/F$13)+$E49 -> 0 | G49: =($D49/G$13)+$E49 -> 0 | H49: =($D49/H$13)+$E49 -> 0 | I49: =($D49/I$13)+$E49 -> 0 | J49: =($D49/J$13)+$E49 -> 0 | K49: =($D49/K$13)+$E49 -> 0 | L49: =($D49/L$13)+$E49 -> 0 | M49: =($D49/M$13)+$E49 -> 0
F50: =($D50/F$13)+$E50 -> 0 | G50: =($D50/G$13)+$E50 -> 0 | H50: =($D50/H$13)+$E50 -> 0 | I50: =($D50/I$13)+$E50 -> 0 | J50: =($D50/J$13)+$E50 -> 0 | K50: =($D50/K$13)+$E50 -> 0 | L50: =($D50/L$13)+$E50 -> 0 | M50: =($D50/M$13)+$E50 -> 0
B51: MATERIAL & HARDWARE TOTAL | F51: =SUM(F33:F44) -> 0 | G51: =SUM(G33:G44) -> 0 | H51: =SUM(H33:H44) -> 0 | I51: =SUM(I33:I44) -> 0 | J51: =SUM(J33:J44) -> 0 | K51: =SUM(K33:K44) -> 0 | L51: =SUM(L33:L44) -> 0 | M51: =SUM(M33:M44) -> 0 | N51: =IF(N13=0,0,SUM(N42:N44)) -> 0
B52: PROCESSES TOTAL | F52: =SUM(F46:F50) -> 0 | G52: =SUM(G46:G50) -> 0 | H52: =SUM(H46:H50) -> 0 | I52: =SUM(I46:I50) -> 0 | J52: =SUM(J46:J50) -> 0 | K52: =SUM(K46:K50) -> 0 | L52: =SUM(L46:L50) -> 0 | M52: =SUM(M46:M50) -> 0 | N52: =IF(N13=0,0,SUM(N46:N50)) -> 0
B53: M+L Subtotal | F53: =SUM(F30+F51+F52) -> 0 | G53: =SUM(G30+G51+G52) -> 0 | H53: =SUM(H30+H51+H52) -> 0 | I53: =SUM(I30+I51+I52) -> 0 | J53: =SUM(J30+J51+J52) -> 0 | K53: =SUM(K30+K51+K52) -> 0 | L53: =SUM(L30+L51+L52) -> 0 | M53: =SUM(M30+M51+M52) -> 0 | N53: =IF(N13=0,0,SUM(N30+N51+N52)) -> 0
E55: REFERENCE | F55: =SUM(F53+#REF!+#REF!) -> #REF! | G55: =SUM(G53+#REF!+#REF!) -> #REF! | H55: =SUM(H53+#REF!+#REF!) -> #REF! | I55: =SUM(I53+#REF!+#REF!) -> #REF! | J55: =SUM(J53+#REF!+#REF!) -> #REF! | K55: =SUM(K53+#REF!+#REF!) -> #REF! | L55: =SUM(L53+#REF!+#REF!) -> #REF! | M55: =SUM(M53+#REF!+#REF!) -> #REF! | N55: =SUM(N53+#REF!+#REF!) -> #REF!
D56: MARGIN | F56: =(F55-F53)/F55 -> #REF! | G56: =(G55-G53)/G55 -> #REF! | H56: =(H55-H53)/H55 -> #REF! | I56: =(I55-I53)/I55 -> #REF! | J56: =(J55-J53)/J55 -> #REF! | K56: =(K55-K53)/K55 -> #REF! | L56: =(L55-L53)/L55 -> #REF! | M56: =(M55-M53)/M55 -> #REF!
D57: LABOR | F57: =F30 -> 0 | G57: =G30 -> 0 | H57: =H30 -> 0 | I57: =I30 -> 0 | J57: =J30 -> 0 | K57: =K30 -> 0 | L57: =L30 -> 0 | M57: =M30 -> 0 | N57: =SUM((N30)) -> 0
C58: MAT'ls &HARDWARE | F58: =F51 -> 0 | G58: =G51 -> 0 | H58: =H51 -> 0 | I58: =I51 -> 0 | J58: =J51 -> 0 | K58: =K51 -> 0 | L58: =L51 -> 0 | M58: =M51 -> 0 | N58: =(N51) -> 0
D59: PROCESS | F59: =F52 -> 0 | G59: =G52 -> 0 | H59: =H52 -> 0 | I59: =I52 -> 0 | J59: =J52 -> 0 | K59: =K52 -> 0 | L59: =L52 -> 0 | M59: =M52 -> 0 | N59: =N52 -> 0
D60: Subtotal | F60: =SUM(F57:F59) -> 0 | G60: =SUM(G57:G59) -> 0 | H60: =SUM(H57:H59) -> 0 | I60: =SUM(I57:I59) -> 0 | J60: =SUM(J57:J59) -> 0 | K60: =SUM(K57:K59) -> 0 | L60: =SUM(L57:L59) -> 0 | M60: =SUM(M57:M59) -> 0 | N60: =SUM(N57:N59) -> 0
D61: AMORTIZED | F61: =$N$60/F13 -> 0 | G61: =$N$60/G13 -> 0 | H61: =$N$60/H13 -> 0 | I61: =$N$60/I13 -> 0 | J61: =$N$60/J13 -> 0 | K61: =$N$60/K13 -> 0 | L61: =$N$60/L13 -> 0 | M61: =$N$60/M13 -> 0
D62: Facilities | F62: 0 | G62: 0 | H62: 0 | I62: 0 | J62: 0 | K62: 0 | L62: 0 | M62: 0
D63: =B3 -> 5 | F63: =SUM(F60:F62) -> 0 | G63: =SUM(G60:G62) -> 0 | H63: =SUM(H60:H62) -> 0 | I63: =SUM(I60:I62) -> 0 | J63: =SUM(J60:J62) -> 0 | K63: =SUM(K60:K62) -> 0 | L63: =SUM(L60:L62) -> 0 | M63: =SUM(M60:M62) -> 0
A66: NRESC/TOOLING
A67: SETUPS
A68: FAIR
A69: SOURCE

Sheet Subassy 6
A2: CUSTOMER: | F2: Comments:
A3: P/N: | B3: 6 | D3: NSN #:
A4: REV: | D4: SOL #:
A5: QUOTE LOG No.: | D5: RFQ #:
A6: QTY: | B6: =F13&", "&G13&", "&H13&", "&I13&", "&J13&", "&K13&", "&L13&", "&M13 -> 10, 25, 50, 75, 100, 250, 500, 1000
A7: DATE:
A8: ESTIMATOR:
A11: MANUFACTURING OPERATIONS | F11: COST ESTIMATED QUANTITIES | N11: NRE/SET-UP
B13: SET-UP TIME | C13: RUN TIME | E13: LABOR RATE | F13: ='Top Assy'!F13 -> 10 | G13: ='Top Assy'!G13 -> 25 | H13: ='Top Assy'!H13 -> 50 | I13: ='Top Assy'!I13 -> 75 | J13: ='Top Assy'!J13 -> 100 | K13: ='Top Assy'!K13 -> 250 | L13: ='Top Assy'!L13 -> 500 | M13: ='Top Assy'!M13 -> 1000 | N13: 1
A14: Program | E14: 0 | N14: =(($B14/N$13*$E14)+($C14*$E14)) -> 0
A15: Fixtures | E15: 0 | N15: =(($B15/N$13*$E15)+($C15*$E15)) -> 0
A16: Mill/Turn | E16: 0 | F16: =(($B16/F$13*$E16)+($C16*$E16)) -> 0 | G16: =(($B16/G$13*$E16)+($C16*$E16)) -> 0 | H16: =(($B16/H$13*$E16)+($C16*$E16)) -> 0 | I16: =(($B16/I$13*$E16)+($C16*$E16)) -> 0 | J16: =(($B16/J$13*$E16)+($C16*$E16)) -> 0 | K16: =(($B16/K$13*$E16)+($C16*$E16)) -> 0 | L16: =(($B16/L$13*$E16)+($C16*$E16)) -> 0 | M16: =(($B16/M$13*$E16)+($C16*$E16)) -> 0
A17: Metals - Mills | E17: 0 | F17: =(($B17/F$13*$E17)+($C17*$E17)) -> 0 | G17: =(($B17/G$13*$E17)+($C17*$E17)) -> 0 | H17: =(($B17/H$13*$E17)+($C17*$E17)) -> 0 | I17: =(($B17/I$13*$E17)+($C17*$E17)) -> 0 | J17: =(($B17/J$13*$E17)+($C17*$E17)) -> 0 | K17: =(($B17/K$13*$E17)+($C17*$E17)) -> 0 | L17: =(($B17/L$13*$E17)+($C17*$E17)) -> 0 | M17: =(($B17/M$13*$E17)+($C17*$E17)) -> 0
A18: Metals - Lathe | E18: 0 | F18: =(($B18/F$13*$E18)+($C18*$E18)) -> 0 | G18: =(($B18/G$13*$E18)+($C18*$E18)) -> 0 | H18: =(($B18/H$13*$E18)+($C18*$E18)) -> 0 | I18: =(($B18/I$13*$E18)+($C18*$E18)) -> 0 | J18: =(($B18/J$13*$E18)+($C18*$E18)) -> 0 | K18: =(($B18/K$13*$E18)+($C18*$E18)) -> 0 | L18: =(($B18/L$13*$E18)+($C18*$E18)) -> 0 | M18: =(($B18/M$13*$E18)+($C18*$E18)) -> 0
A19: Rubber Mold | E19: 0 | F19: =(($B19/F$13*$E19)+($C19*$E19)) -> 0 | G19: =(($B19/G$13*$E19)+($C19*$E19)) -> 0 | H19: =(($B19/H$13*$E19)+($C19*$E19)) -> 0 | I19: =(($B19/I$13*$E19)+($C19*$E19)) -> 0 | J19: =(($B19/J$13*$E19)+($C19*$E19)) -> 0 | K19: =(($B19/K$13*$E19)+($C19*$E19)) -> 0 | L19: =(($B19/L$13*$E19)+($C19*$E19)) -> 0 | M19: =(($B19/M$13*$E19)+($C19*$E19)) -> 0
A20: Plastic Injection Mold | E20: 0 | F20: =(($B20/F$13*$E20)+($C20*$E20)) -> 0 | G20: =(($B20/G$13*$E20)+($C20*$E20)) -> 0 | H20: =(($B20/H$13*$E20)+($C20*$E20)) -> 0 | I20: =(($B20/I$13*$E20)+($C20*$E20)) -> 0 | J20: =(($B20/J$13*$E20)+($C20*$E20)) -> 0 | K20: =(($B20/K$13*$E20)+($C20*$E20)) -> 0 | L20: =(($B20/L$13*$E20)+($C20*$E20)) -> 0 | M20: =(($B20/M$13*$E20)+($C20*$E20)) -> 0
A21: Plastic Compression Mold | E21: 0 | F21: =(($B21/F$13*$E21)+($C21*$E21)) -> 0 | G21: =(($B21/G$13*$E21)+($C21*$E21)) -> 0 | H21: =(($B21/H$13*$E21)+($C21*$E21)) -> 0 | I21: =(($B21/I$13*$E21)+($C21*$E21)) -> 0 | J21: =(($B21/J$13*$E21)+($C21*$E21)) -> 0 | K21: =(($B21/K$13*$E21)+($C21*$E21)) -> 0 | L21: =(($B21/L$13*$E21)+($C21*$E21)) -> 0 | M21: =(($B21/M$13*$E21)+($C21*$E21)) -> 0
A22: Waterjet - Setup | E22: 0 | F22: =(($B22/F$13*$E22)+($C22*$E22)) -> 0 | G22: =(($B22/G$13*$E22)+($C22*$E22)) -> 0 | H22: =(($B22/H$13*$E22)+($C22*$E22)) -> 0 | I22: =(($B22/I$13*$E22)+($C22*$E22)) -> 0 | J22: =(($B22/J$13*$E22)+($C22*$E22)) -> 0 | K22: =(($B22/K$13*$E22)+($C22*$E22)) -> 0 | L22: =(($B22/L$13*$E22)+($C22*$E22)) -> 0 | M22: =(($B22/M$13*$E22)+($C22*$E22)) -> 0
A23: Waterjet - Operator | E23: 0 | F23: =(($B23/F$13*$E23)+($C23*$E23)) -> 0 | G23: =(($B23/G$13*$E23)+($C23*$E23)) -> 0 | H23: =(($B23/H$13*$E23)+($C23*$E23)) -> 0 | I23: =(($B23/I$13*$E23)+($C23*$E23)) -> 0 | J23: =(($B23/J$13*$E23)+($C23*$E23)) -> 0 | K23: =(($B23/K$13*$E23)+($C23*$E23)) -> 0 | L23: =(($B23/L$13*$E23)+($C23*$E23)) -> 0 | M23: =(($B23/M$13*$E23)+($C23*$E23)) -> 0
A24: Assembly, Die Punch, Deburr | E24: 0 | F24: =(($B24/F$13*$E24)+($C24*$E24)) -> 0 | G24: =(($B24/G$13*$E24)+($C24*$E24)) -> 0 | H24: =(($B24/H$13*$E24)+($C24*$E24)) -> 0 | I24: =(($B24/I$13*$E24)+($C24*$E24)) -> 0 | J24: =(($B24/J$13*$E24)+($C24*$E24)) -> 0 | K24: =(($B24/K$13*$E24)+($C24*$E24)) -> 0 | L24: =(($B24/L$13*$E24)+($C24*$E24)) -> 0 | M24: =(($B24/M$13*$E24)+($C24*$E24)) -> 0
A25: Quality Inspection | E25: 0 | F25: =(($B25/F$13*$E25)+($C25*$E25)) -> 0 | G25: =(($B25/G$13*$E25)+($C25*$E25)) -> 0 | H25: =(($B25/H$13*$E25)+($C25*$E25)) -> 0 | I25: =(($B25/I$13*$E25)+($C25*$E25)) -> 0 | J25: =(($B25/J$13*$E25)+($C25*$E25)) -> 0 | K25: =(($B25/K$13*$E25)+($C25*$E25)) -> 0 | L25: =(($B25/L$13*$E25)+($C25*$E25)) -> 0 | M25: =(($B25/M$13*$E25)+($C25*$E25)) -> 0
C26: Labor | E26: Basic LABOR | F26: =SUM(F16:F25) -> 0 | G26: =SUM(G16:G25) -> 0 | H26: =SUM(H16:H25) -> 0 | I26: =SUM(I16:I25) -> 0 | J26: =SUM(J16:J25) -> 0 | K26: =SUM(K16:K25) -> 0 | L26: =SUM(L16:L25) -> 0 | M26: =SUM(M16:M25) -> 0 | N26: =SUM(N14:N25) -> 0
B27: T. setup | C27: T.RUN | E27: hrs | F27: =(($B$28/F13)+$C$28)/60 -> 0 | G27: =(($B$28/G13)+$C$28)/60 -> 0 | H27: =(($B$28/H13)+$C$28)/60 -> 0 | I27: =(($B$28/I13)+$C$28)/60 -> 0 | J27: =(($B$28/J13)+$C$28)/60 -> 0 | K27: =(($B$28/K13)+$C$28)/60 -> 0 | L27: =(($B$28/L13)+$C$28)/60 -> 0 | M27: =(($B$28/M13)+$C$28)/60 -> 0
B28: =SUM(B16:B25) -> 0 | C28: =SUM(C16:C25) -> 0 | D28: 0 | E28: BURDEN | F28: =F26*$D$28 -> 0 | G28: =G26*$D$28 -> 0 | H28: =H26*$D$28 -> 0 | I28: =I26*$D$28 -> 0 | J28: =J26*$D$28 -> 0 | K28: =K26*$D$28 -> 0 | L28: =L26*$D$28 -> 0 | M28: =M26*$D$28 -> 0
E30: Total | F30: =F26+F28 -> 0 | G30: =G26+G28 -> 0 | H30: =H26+H28 -> 0 | I30: =I26+I28 -> 0 | J30: =J26+J28 -> 0 | K30: =K26+K28 -> 0 | L30: =L26+L28 -> 0 | M30: =M26+M28 -> 0 | N30: =N26 -> 0
A32: RAW MATERIALS & HARDWARE | B32: Matl UoM | C32: PARTS QTY | D32: UNIT PRICE | E32: MAT'l BURDEN | F32: ="Qty: "& F13 -> Qty: 10 | G32: ="Qty: "& G13 -> Qty: 25 | H32: ="Qty: "& H13 -> Qty: 50 | I32: ="Qty: "& I13 -> Qty: 75 | J32: ="Qty: "& J13 -> Qty: 100 | K32: ="Qty: "& K13 -> Qty: 250 | L32: ="Qty: "& L13 -> Qty: 500 | M32: ="Qty: "& M13 -> Qty: 1000 | N32: Amortize/ Min Buy
E33: =C33*D33 -> 0 | F33: =IF($N33=TRUE,$E33/F$13,$E33*(1+(1/F$13))) -> 0 | G33: =IF($N33=TRUE,$E33/G$13,$E33*(1+(1/G$13))) -> 0 | H33: =IF($N33=TRUE,$E33/H$13,$E33*(1+(1/H$13))) -> 0 | I33: =IF($N33=TRUE,$E33/I$13,$E33*(1+(1/I$13))) -> 0 | J33: =IF($N33=TRUE,$E33/J$13,$E33*(1+(1/J$13))) -> 0 | K33: =IF($N33=TRUE,$E33/K$13,$E33*(1+(1/K$13))) -> 0 | L33: =IF($N33=TRUE,$E33/L$13,$E33*(1+(1/L$13))) -> 0 | M33: =IF($N33=TRUE,$E33/M$13,$E33*(1+(1/M$13))) -> 0 | N33: FALSE
E34: =C34*D34 -> 0 | F34: =IF($N34=TRUE,$E34/F$13,$E34*(1+(1/F$13))) -> 0 | G34: =IF($N34=TRUE,$E34/G$13,$E34*(1+(1/G$13))) -> 0 | H34: =IF($N34=TRUE,$E34/H$13,$E34*(1+(1/H$13))) -> 0 | I34: =IF($N34=TRUE,$E34/I$13,$E34*(1+(1/I$13))) -> 0 | J34: =IF($N34=TRUE,$E34/J$13,$E34*(1+(1/J$13))) -> 0 | K34: =IF($N34=TRUE,$E34/K$13,$E34*(1+(1/K$13))) -> 0 | L34: =IF($N34=TRUE,$E34/L$13,$E34*(1+(1/L$13))) -> 0 | M34: =IF($N34=TRUE,$E34/M$13,$E34*(1+(1/M$13))) -> 0 | N34: FALSE
E35: =C35*D35 -> 0 | F35: =IF($N35=TRUE,$E35/F$13,$E35*(1+(1/F$13))) -> 0 | G35: =IF($N35=TRUE,$E35/G$13,$E35*(1+(1/G$13))) -> 0 | H35: =IF($N35=TRUE,$E35/H$13,$E35*(1+(1/H$13))) -> 0 | I35: =IF($N35=TRUE,$E35/I$13,$E35*(1+(1/I$13))) -> 0 | J35: =IF($N35=TRUE,$E35/J$13,$E35*(1+(1/J$13))) -> 0 | K35: =IF($N35=TRUE,$E35/K$13,$E35*(1+(1/K$13))) -> 0 | L35: =IF($N35=TRUE,$E35/L$13,$E35*(1+(1/L$13))) -> 0 | M35: =IF($N35=TRUE,$E35/M$13,$E35*(1+(1/M$13))) -> 0 | N35: FALSE | S35: QTY | T35: Total
E36: =C36*D36 -> 0 | F36: =IF($N36=TRUE,$E36/F$13,$E36*(1+(1/F$13))) -> 0 | G36: =IF($N36=TRUE,$E36/G$13,$E36*(1+(1/G$13))) -> 0 | H36: =IF($N36=TRUE,$E36/H$13,$E36*(1+(1/H$13))) -> 0 | I36: =IF($N36=TRUE,$E36/I$13,$E36*(1+(1/I$13))) -> 0 | J36: =IF($N36=TRUE,$E36/J$13,$E36*(1+(1/J$13))) -> 0 | K36: =IF($N36=TRUE,$E36/K$13,$E36*(1+(1/K$13))) -> 0 | L36: =IF($N36=TRUE,$E36/L$13,$E36*(1+(1/L$13))) -> 0 | M36: =IF($N36=TRUE,$E36/M$13,$E36*(1+(1/M$13))) -> 0 | N36: FALSE | S36: =M13 -> 1000 | T36: =M63 -> 0
E37: =C37*D37 -> 0 | F37: =IF($N37=TRUE,$E37/F$13,$E37*(1+(1/F$13))) -> 0 | G37: =IF($N37=TRUE,$E37/G$13,$E37*(1+(1/G$13))) -> 0 | H37: =IF($N37=TRUE,$E37/H$13,$E37*(1+(1/H$13))) -> 0 | I37: =IF($N37=TRUE,$E37/I$13,$E37*(1+(1/I$13))) -> 0 | J37: =IF($N37=TRUE,$E37/J$13,$E37*(1+(1/J$13))) -> 0 | K37: =IF($N37=TRUE,$E37/K$13,$E37*(1+(1/K$13))) -> 0 | L37: =IF($N37=TRUE,$E37/L$13,$E37*(1+(1/L$13))) -> 0 | M37: =IF($N37=TRUE,$E37/M$13,$E37*(1+(1/M$13))) -> 0 | N37: FALSE | S37: =L13 -> 500 | T37: =L63 -> 0
E38: =C38*D38 -> 0 | F38: =IF($N38=TRUE,$E38/F$13,$E38*(1+(1/F$13))) -> 0 | G38: =IF($N38=TRUE,$E38/G$13,$E38*(1+(1/G$13))) -> 0 | H38: =IF($N38=TRUE,$E38/H$13,$E38*(1+(1/H$13))) -> 0 | I38: =IF($N38=TRUE,$E38/I$13,$E38*(1+(1/I$13))) -> 0 | J38: =IF($N38=TRUE,$E38/J$13,$E38*(1+(1/J$13))) -> 0 | K38: =IF($N38=TRUE,$E38/K$13,$E38*(1+(1/K$13))) -> 0 | L38: =IF($N38=TRUE,$E38/L$13,$E38*(1+(1/L$13))) -> 0 | M38: =IF($N38=TRUE,$E38/M$13,$E38*(1+(1/M$13))) -> 0 | N38: FALSE | S38: =I13 -> 75 | T38: =I63 -> 0
E39: =C39*D39 -> 0 | F39: =IF($N39=TRUE,$E39/F$13,$E39*(1+(1/F$13))) -> 0 | G39: =IF($N39=TRUE,$E39/G$13,$E39*(1+(1/G$13))) -> 0 | H39: =IF($N39=TRUE,$E39/H$13,$E39*(1+(1/H$13))) -> 0 | I39: =IF($N39=TRUE,$E39/I$13,$E39*(1+(1/I$13))) -> 0 | J39: =IF($N39=TRUE,$E39/J$13,$E39*(1+(1/J$13))) -> 0 | K39: =IF($N39=TRUE,$E39/K$13,$E39*(1+(1/K$13))) -> 0 | L39: =IF($N39=TRUE,$E39/L$13,$E39*(1+(1/L$13))) -> 0 | M39: =IF($N39=TRUE,$E39/M$13,$E39*(1+(1/M$13))) -> 0 | N39: FALSE | S39: =H13 -> 50 | T39: =H63 -> 0
E40: =C40*D40 -> 0 | F40: =IF($N40=TRUE,$E40/F$13,$E40*(1+(1/F$13))) -> 0 | G40: =IF($N40=TRUE,$E40/G$13,$E40*(1+(1/G$13))) -> 0 | H40: =IF($N40=TRUE,$E40/H$13,$E40*(1+(1/H$13))) -> 0 | I40: =IF($N40=TRUE,$E40/I$13,$E40*(1+(1/I$13))) -> 0 | J40: =IF($N40=TRUE,$E40/J$13,$E40*(1+(1/J$13))) -> 0 | K40: =IF($N40=TRUE,$E40/K$13,$E40*(1+(1/K$13))) -> 0 | L40: =IF($N40=TRUE,$E40/L$13,$E40*(1+(1/L$13))) -> 0 | M40: =IF($N40=TRUE,$E40/M$13,$E40*(1+(1/M$13))) -> 0 | N40: FALSE | S40: =G13 -> 25 | T40: =G63 -> 0
E41: =C41*D41 -> 0 | F41: =IF($N41=TRUE,$E41/F$13,$E41*(1+(1/F$13))) -> 0 | G41: =IF($N41=TRUE,$E41/G$13,$E41*(1+(1/G$13))) -> 0 | H41: =IF($N41=TRUE,$E41/H$13,$E41*(1+(1/H$13))) -> 0 | I41: =IF($N41=TRUE,$E41/I$13,$E41*(1+(1/I$13))) -> 0 | J41: =IF($N41=TRUE,$E41/J$13,$E41*(1+(1/J$13))) -> 0 | K41: =IF($N41=TRUE,$E41/K$13,$E41*(1+(1/K$13))) -> 0 | L41: =IF($N41=TRUE,$E41/L$13,$E41*(1+(1/L$13))) -> 0 | M41: =IF($N41=TRUE,$E41/M$13,$E41*(1+(1/M$13))) -> 0 | N41: FALSE | S41: =F13 -> 10 | T41: =F63 -> 0
E42: =C42*D42 -> 0 | F42: =IF($N42=TRUE,$E42/F$13,$E42*(1+(1/F$13))) -> 0 | G42: =IF($N42=TRUE,$E42/G$13,$E42*(1+(1/G$13))) -> 0 | H42: =IF($N42=TRUE,$E42/H$13,$E42*(1+(1/H$13))) -> 0 | I42: =IF($N42=TRUE,$E42/I$13,$E42*(1+(1/I$13))) -> 0 | J42: =IF($N42=TRUE,$E42/J$13,$E42*(1+(1/J$13))) -> 0 | K42: =IF($N42=TRUE,$E42/K$13,$E42*(1+(1/K$13))) -> 0 | L42: =IF($N42=TRUE,$E42/L$13,$E42*(1+(1/L$13))) -> 0 | M42: =IF($N42=TRUE,$E42/M$13,$E42*(1+(1/M$13))) -> 0 | N42: FALSE
E43: =C43*D43 -> 0 | F43: =IF($N43=TRUE,$E43/F$13,$E43*(1+(1/F$13))) -> 0 | G43: =IF($N43=TRUE,$E43/G$13,$E43*(1+(1/G$13))) -> 0 | H43: =IF($N43=TRUE,$E43/H$13,$E43*(1+(1/H$13))) -> 0 | I43: =IF($N43=TRUE,$E43/I$13,$E43*(1+(1/I$13))) -> 0 | J43: =IF($N43=TRUE,$E43/J$13,$E43*(1+(1/J$13))) -> 0 | K43: =IF($N43=TRUE,$E43/K$13,$E43*(1+(1/K$13))) -> 0 | L43: =IF($N43=TRUE,$E43/L$13,$E43*(1+(1/L$13))) -> 0 | M43: =IF($N43=TRUE,$E43/M$13,$E43*(1+(1/M$13))) -> 0 | N43: FALSE
E44: =C44*D44 -> 0 | F44: =IF($N44=TRUE,$E44/F$13,$E44*(1+(1/F$13))) -> 0 | G44: =IF($N44=TRUE,$E44/G$13,$E44*(1+(1/G$13))) -> 0 | H44: =IF($N44=TRUE,$E44/H$13,$E44*(1+(1/H$13))) -> 0 | I44: =IF($N44=TRUE,$E44/I$13,$E44*(1+(1/I$13))) -> 0 | J44: =IF($N44=TRUE,$E44/J$13,$E44*(1+(1/J$13))) -> 0 | K44: =IF($N44=TRUE,$E44/K$13,$E44*(1+(1/K$13))) -> 0 | L44: =IF($N44=TRUE,$E44/L$13,$E44*(1+(1/L$13))) -> 0 | M44: =IF($N44=TRUE,$E44/M$13,$E44*(1+(1/M$13))) -> 0 | N44: FALSE
A45: PROCESSES/COMPONENTS | D45: SETUP $ | E45: RUN$ EA.
F46: =($D46/F$13)+$E46 -> 0 | G46: =($D46/G$13)+$E46 -> 0 | H46: =($D46/H$13)+$E46 -> 0 | I46: =($D46/I$13)+$E46 -> 0 | J46: =($D46/J$13)+$E46 -> 0 | K46: =($D46/K$13)+$E46 -> 0 | L46: =($D46/L$13)+$E46 -> 0 | M46: =($D46/M$13)+$E46 -> 0
F47: =($D47/F$13)+$E47 -> 0 | G47: =($D47/G$13)+$E47 -> 0 | H47: =($D47/H$13)+$E47 -> 0 | I47: =($D47/I$13)+$E47 -> 0 | J47: =($D47/J$13)+$E47 -> 0 | K47: =($D47/K$13)+$E47 -> 0 | L47: =($D47/L$13)+$E47 -> 0 | M47: =($D47/M$13)+$E47 -> 0
F48: =($D48/F$13)+$E48 -> 0 | G48: =($D48/G$13)+$E48 -> 0 | H48: =($D48/H$13)+$E48 -> 0 | I48: =($D48/I$13)+$E48 -> 0 | J48: =($D48/J$13)+$E48 -> 0 | K48: =($D48/K$13)+$E48 -> 0 | L48: =($D48/L$13)+$E48 -> 0 | M48: =($D48/M$13)+$E48 -> 0
F49: =($D49/F$13)+$E49 -> 0 | G49: =($D49/G$13)+$E49 -> 0 | H49: =($D49/H$13)+$E49 -> 0 | I49: =($D49/I$13)+$E49 -> 0 | J49: =($D49/J$13)+$E49 -> 0 | K49: =($D49/K$13)+$E49 -> 0 | L49: =($D49/L$13)+$E49 -> 0 | M49: =($D49/M$13)+$E49 -> 0
F50: =($D50/F$13)+$E50 -> 0 | G50: =($D50/G$13)+$E50 -> 0 | H50: =($D50/H$13)+$E50 -> 0 | I50: =($D50/I$13)+$E50 -> 0 | J50: =($D50/J$13)+$E50 -> 0 | K50: =($D50/K$13)+$E50 -> 0 | L50: =($D50/L$13)+$E50 -> 0 | M50: =($D50/M$13)+$E50 -> 0
B51: MATERIAL & HARDWARE TOTAL | F51: =SUM(F33:F44) -> 0 | G51: =SUM(G33:G44) -> 0 | H51: =SUM(H33:H44) -> 0 | I51: =SUM(I33:I44) -> 0 | J51: =SUM(J33:J44) -> 0 | K51: =SUM(K33:K44) -> 0 | L51: =SUM(L33:L44) -> 0 | M51: =SUM(M33:M44) -> 0 | N51: =IF(N13=0,0,SUM(N42:N44)) -> 0
B52: PROCESSES TOTAL | F52: =SUM(F46:F50) -> 0 | G52: =SUM(G46:G50) -> 0 | H52: =SUM(H46:H50) -> 0 | I52: =SUM(I46:I50) -> 0 | J52: =SUM(J46:J50) -> 0 | K52: =SUM(K46:K50) -> 0 | L52: =SUM(L46:L50) -> 0 | M52: =SUM(M46:M50) -> 0 | N52: =IF(N13=0,0,SUM(N46:N50)) -> 0
B53: M+L Subtotal | F53: =SUM(F30+F51+F52) -> 0 | G53: =SUM(G30+G51+G52) -> 0 | H53: =SUM(H30+H51+H52) -> 0 | I53: =SUM(I30+I51+I52) -> 0 | J53: =SUM(J30+J51+J52) -> 0 | K53: =SUM(K30+K51+K52) -> 0 | L53: =SUM(L30+L51+L52) -> 0 | M53: =SUM(M30+M51+M52) -> 0 | N53: =IF(N13=0,0,SUM(N30+N51+N52)) -> 0
E55: REFERENCE | F55: =SUM(F53+#REF!+#REF!) -> #REF! | G55: =SUM(G53+#REF!+#REF!) -> #REF! | H55: =SUM(H53+#REF!+#REF!) -> #REF! | I55: =SUM(I53+#REF!+#REF!) -> #REF! | J55: =SUM(J53+#REF!+#REF!) -> #REF! | K55: =SUM(K53+#REF!+#REF!) -> #REF! | L55: =SUM(L53+#REF!+#REF!) -> #REF! | M55: =SUM(M53+#REF!+#REF!) -> #REF! | N55: =SUM(N53+#REF!+#REF!) -> #REF!
D56: MARGIN | F56: =(F55-F53)/F55 -> #REF! | G56: =(G55-G53)/G55 -> #REF! | H56: =(H55-H53)/H55 -> #REF! | I56: =(I55-I53)/I55 -> #REF! | J56: =(J55-J53)/J55 -> #REF! | K56: =(K55-K53)/K55 -> #REF! | L56: =(L55-L53)/L55 -> #REF! | M56: =(M55-M53)/M55 -> #REF!
D57: LABOR | F57: =F30 -> 0 | G57: =G30 -> 0 | H57: =H30 -> 0 | I57: =I30 -> 0 | J57: =J30 -> 0 | K57: =K30 -> 0 | L57: =L30 -> 0 | M57: =M30 -> 0 | N57: =SUM((N30)) -> 0
C58: MAT'ls &HARDWARE | F58: =F51 -> 0 | G58: =G51 -> 0 | H58: =H51 -> 0 | I58: =I51 -> 0 | J58: =J51 -> 0 | K58: =K51 -> 0 | L58: =L51 -> 0 | M58: =M51 -> 0 | N58: =(N51) -> 0
D59: PROCESS | F59: =F52 -> 0 | G59: =G52 -> 0 | H59: =H52 -> 0 | I59: =I52 -> 0 | J59: =J52 -> 0 | K59: =K52 -> 0 | L59: =L52 -> 0 | M59: =M52 -> 0 | N59: =N52 -> 0
D60: Subtotal | F60: =SUM(F57:F59) -> 0 | G60: =SUM(G57:G59) -> 0 | H60: =SUM(H57:H59) -> 0 | I60: =SUM(I57:I59) -> 0 | J60: =SUM(J57:J59) -> 0 | K60: =SUM(K57:K59) -> 0 | L60: =SUM(L57:L59) -> 0 | M60: =SUM(M57:M59) -> 0 | N60: =SUM(N57:N59) -> 0
D61: AMORTIZED | F61: =$N$60/F13 -> 0 | G61: =$N$60/G13 -> 0 | H61: =$N$60/H13 -> 0 | I61: =$N$60/I13 -> 0 | J61: =$N$60/J13 -> 0 | K61: =$N$60/K13 -> 0 | L61: =$N$60/L13 -> 0 | M61: =$N$60/M13 -> 0
D62: Facilities | F62: 0 | G62: 0 | H62: 0 | I62: 0 | J62: 0 | K62: 0 | L62: 0 | M62: 0
D63: =B3 -> 6 | F63: =SUM(F60:F62) -> 0 | G63: =SUM(G60:G62) -> 0 | H63: =SUM(H60:H62) -> 0 | I63: =SUM(I60:I62) -> 0 | J63: =SUM(J60:J62) -> 0 | K63: =SUM(K60:K62) -> 0 | L63: =SUM(L60:L62) -> 0 | M63: =SUM(M60:M62) -> 0
A66: NRESC/TOOLING
A67: SETUPS
A68: FAIR
A69: SOURCE

Sheet Subassy 7
A2: CUSTOMER: | F2: Comments:
A3: P/N: | B3: 7 | D3: NSN #:
A4: REV: | D4: SOL #:
A5: QUOTE LOG No.: | D5: RFQ #:
A6: QTY: | B6: =F13&", "&G13&", "&H13&", "&I13&", "&J13&", "&K13&", "&L13&", "&M13 -> 10, 25, 50, 75, 100, 250, 500, 1000
A7: DATE:
A8: ESTIMATOR:
A11: MANUFACTURING OPERATIONS | F11: COST ESTIMATED QUANTITIES | N11: NRE/SET-UP
B13: SET-UP TIME | C13: RUN TIME | E13: LABOR RATE | F13: ='Top Assy'!F13 -> 10 | G13: ='Top Assy'!G13 -> 25 | H13: ='Top Assy'!H13 -> 50 | I13: ='Top Assy'!I13 -> 75 | J13: ='Top Assy'!J13 -> 100 | K13: ='Top Assy'!K13 -> 250 | L13: ='Top Assy'!L13 -> 500 | M13: ='Top Assy'!M13 -> 1000 | N13: 1
A14: Program | E14: 0 | N14: =(($B14/N$13*$E14)+($C14*$E14)) -> 0
A15: Fixtures | E15: 0 | N15: =(($B15/N$13*$E15)+($C15*$E15)) -> 0
A16: Mill/Turn | E16: 0 | F16: =(($B16/F$13*$E16)+($C16*$E16)) -> 0 | G16: =(($B16/G$13*$E16)+($C16*$E16)) -> 0 | H16: =(($B16/H$13*$E16)+($C16*$E16)) -> 0 | I16: =(($B16/I$13*$E16)+($C16*$E16)) -> 0 | J16: =(($B16/J$13*$E16)+($C16*$E16)) -> 0 | K16: =(($B16/K$13*$E16)+($C16*$E16)) -> 0 | L16: =(($B16/L$13*$E16)+($C16*$E16)) -> 0 | M16: =(($B16/M$13*$E16)+($C16*$E16)) -> 0
A17: Metals - Mills | E17: 0 | F17: =(($B17/F$13*$E17)+($C17*$E17)) -> 0 | G17: =(($B17/G$13*$E17)+($C17*$E17)) -> 0 | H17: =(($B17/H$13*$E17)+($C17*$E17)) -> 0 | I17: =(($B17/I$13*$E17)+($C17*$E17)) -> 0 | J17: =(($B17/J$13*$E17)+($C17*$E17)) -> 0 | K17: =(($B17/K$13*$E17)+($C17*$E17)) -> 0 | L17: =(($B17/L$13*$E17)+($C17*$E17)) -> 0 | M17: =(($B17/M$13*$E17)+($C17*$E17)) -> 0
A18: Metals - Lathe | E18: 0 | F18: =(($B18/F$13*$E18)+($C18*$E18)) -> 0 | G18: =(($B18/G$13*$E18)+($C18*$E18)) -> 0 | H18: =(($B18/H$13*$E18)+($C18*$E18)) -> 0 | I18: =(($B18/I$13*$E18)+($C18*$E18)) -> 0 | J18: =(($B18/J$13*$E18)+($C18*$E18)) -> 0 | K18: =(($B18/K$13*$E18)+($C18*$E18)) -> 0 | L18: =(($B18/L$13*$E18)+($C18*$E18)) -> 0 | M18: =(($B18/M$13*$E18)+($C18*$E18)) -> 0
A19: Rubber Mold | E19: 0 | F19: =(($B19/F$13*$E19)+($C19*$E19)) -> 0 | G19: =(($B19/G$13*$E19)+($C19*$E19)) -> 0 | H19: =(($B19/H$13*$E19)+($C19*$E19)) -> 0 | I19: =(($B19/I$13*$E19)+($C19*$E19)) -> 0 | J19: =(($B19/J$13*$E19)+($C19*$E19)) -> 0 | K19: =(($B19/K$13*$E19)+($C19*$E19)) -> 0 | L19: =(($B19/L$13*$E19)+($C19*$E19)) -> 0 | M19: =(($B19/M$13*$E19)+($C19*$E19)) -> 0
A20: Plastic Injection Mold | E20: 0 | F20: =(($B20/F$13*$E20)+($C20*$E20)) -> 0 | G20: =(($B20/G$13*$E20)+($C20*$E20)) -> 0 | H20: =(($B20/H$13*$E20)+($C20*$E20)) -> 0 | I20: =(($B20/I$13*$E20)+($C20*$E20)) -> 0 | J20: =(($B20/J$13*$E20)+($C20*$E20)) -> 0 | K20: =(($B20/K$13*$E20)+($C20*$E20)) -> 0 | L20: =(($B20/L$13*$E20)+($C20*$E20)) -> 0 | M20: =(($B20/M$13*$E20)+($C20*$E20)) -> 0
A21: Plastic Compression Mold | E21: 0 | F21: =(($B21/F$13*$E21)+($C21*$E21)) -> 0 | G21: =(($B21/G$13*$E21)+($C21*$E21)) -> 0 | H21: =(($B21/H$13*$E21)+($C21*$E21)) -> 0 | I21: =(($B21/I$13*$E21)+($C21*$E21)) -> 0 | J21: =(($B21/J$13*$E21)+($C21*$E21)) -> 0 | K21: =(($B21/K$13*$E21)+($C21*$E21)) -> 0 | L21: =(($B21/L$13*$E21)+($C21*$E21)) -> 0 | M21: =(($B21/M$13*$E21)+($C21*$E21)) -> 0
A22: Waterjet - Setup | E22: 0 | F22: =(($B22/F$13*$E22)+($C22*$E22)) -> 0 | G22: =(($B22/G$13*$E22)+($C22*$E22)) -> 0 | H22: =(($B22/H$13*$E22)+($C22*$E22)) -> 0 | I22: =(($B22/I$13*$E22)+($C22*$E22)) -> 0 | J22: =(($B22/J$13*$E22)+($C22*$E22)) -> 0 | K22: =(($B22/K$13*$E22)+($C22*$E22)) -> 0 | L22: =(($B22/L$13*$E22)+($C22*$E22)) -> 0 | M22: =(($B22/M$13*$E22)+($C22*$E22)) -> 0
A23: Waterjet - Operator | E23: 0 | F23: =(($B23/F$13*$E23)+($C23*$E23)) -> 0 | G23: =(($B23/G$13*$E23)+($C23*$E23)) -> 0 | H23: =(($B23/H$13*$E23)+($C23*$E23)) -> 0 | I23: =(($B23/I$13*$E23)+($C23*$E23)) -> 0 | J23: =(($B23/J$13*$E23)+($C23*$E23)) -> 0 | K23: =(($B23/K$13*$E23)+($C23*$E23)) -> 0 | L23: =(($B23/L$13*$E23)+($C23*$E23)) -> 0 | M23: =(($B23/M$13*$E23)+($C23*$E23)) -> 0
A24: Assembly, Die Punch, Deburr | E24: 0 | F24: =(($B24/F$13*$E24)+($C24*$E24)) -> 0 | G24: =(($B24/G$13*$E24)+($C24*$E24)) -> 0 | H24: =(($B24/H$13*$E24)+($C24*$E24)) -> 0 | I24: =(($B24/I$13*$E24)+($C24*$E24)) -> 0 | J24: =(($B24/J$13*$E24)+($C24*$E24)) -> 0 | K24: =(($B24/K$13*$E24)+($C24*$E24)) -> 0 | L24: =(($B24/L$13*$E24)+($C24*$E24)) -> 0 | M24: =(($B24/M$13*$E24)+($C24*$E24)) -> 0
A25: Quality Inspection | E25: 0 | F25: =(($B25/F$13*$E25)+($C25*$E25)) -> 0 | G25: =(($B25/G$13*$E25)+($C25*$E25)) -> 0 | H25: =(($B25/H$13*$E25)+($C25*$E25)) -> 0 | I25: =(($B25/I$13*$E25)+($C25*$E25)) -> 0 | J25: =(($B25/J$13*$E25)+($C25*$E25)) -> 0 | K25: =(($B25/K$13*$E25)+($C25*$E25)) -> 0 | L25: =(($B25/L$13*$E25)+($C25*$E25)) -> 0 | M25: =(($B25/M$13*$E25)+($C25*$E25)) -> 0
C26: Labor | E26: Basic LABOR | F26: =SUM(F16:F25) -> 0 | G26: =SUM(G16:G25) -> 0 | H26: =SUM(H16:H25) -> 0 | I26: =SUM(I16:I25) -> 0 | J26: =SUM(J16:J25) -> 0 | K26: =SUM(K16:K25) -> 0 | L26: =SUM(L16:L25) -> 0 | M26: =SUM(M16:M25) -> 0 | N26: =SUM(N14:N25) -> 0
B27: T. setup | C27: T.RUN | E27: hrs | F27: =(($B$28/F13)+$C$28)/60 -> 0 | G27: =(($B$28/G13)+$C$28)/60 -> 0 | H27: =(($B$28/H13)+$C$28)/60 -> 0 | I27: =(($B$28/I13)+$C$28)/60 -> 0 | J27: =(($B$28/J13)+$C$28)/60 -> 0 | K27: =(($B$28/K13)+$C$28)/60 -> 0 | L27: =(($B$28/L13)+$C$28)/60 -> 0 | M27: =(($B$28/M13)+$C$28)/60 -> 0
B28: =SUM(B16:B25) -> 0 | C28: =SUM(C16:C25) -> 0 | D28: 0 | E28: BURDEN | F28: =F26*$D$28 -> 0 | G28: =G26*$D$28 -> 0 | H28: =H26*$D$28 -> 0 | I28: =I26*$D$28 -> 0 | J28: =J26*$D$28 -> 0 | K28: =K26*$D$28 -> 0 | L28: =L26*$D$28 -> 0 | M28: =M26*$D$28 -> 0
E30: Total | F30: =F26+F28 -> 0 | G30: =G26+G28 -> 0 | H30: =H26+H28 -> 0 | I30: =I26+I28 -> 0 | J30: =J26+J28 -> 0 | K30: =K26+K28 -> 0 | L30: =L26+L28 -> 0 | M30: =M26+M28 -> 0 | N30: =N26 -> 0
A32: RAW MATERIALS & HARDWARE | B32: Matl UoM | C32: PARTS QTY | D32: UNIT PRICE | E32: MAT'l BURDEN | F32: ="Qty: "& F13 -> Qty: 10 | G32: ="Qty: "& G13 -> Qty: 25 | H32: ="Qty: "& H13 -> Qty: 50 | I32: ="Qty: "& I13 -> Qty: 75 | J32: ="Qty: "& J13 -> Qty: 100 | K32: ="Qty: "& K13 -> Qty: 250 | L32: ="Qty: "& L13 -> Qty: 500 | M32: ="Qty: "& M13 -> Qty: 1000 | N32: Amortize/ Min Buy
E33: =C33*D33 -> 0 | F33: =IF($N33=TRUE,$E33/F$13,$E33*(1+(1/F$13))) -> 0 | G33: =IF($N33=TRUE,$E33/G$13,$E33*(1+(1/G$13))) -> 0 | H33: =IF($N33=TRUE,$E33/H$13,$E33*(1+(1/H$13))) -> 0 | I33: =IF($N33=TRUE,$E33/I$13,$E33*(1+(1/I$13))) -> 0 | J33: =IF($N33=TRUE,$E33/J$13,$E33*(1+(1/J$13))) -> 0 | K33: =IF($N33=TRUE,$E33/K$13,$E33*(1+(1/K$13))) -> 0 | L33: =IF($N33=TRUE,$E33/L$13,$E33*(1+(1/L$13))) -> 0 | M33: =IF($N33=TRUE,$E33/M$13,$E33*(1+(1/M$13))) -> 0 | N33: FALSE
E34: =C34*D34 -> 0 | F34: =IF($N34=TRUE,$E34/F$13,$E34*(1+(1/F$13))) -> 0 | G34: =IF($N34=TRUE,$E34/G$13,$E34*(1+(1/G$13))) -> 0 | H34: =IF($N34=TRUE,$E34/H$13,$E34*(1+(1/H$13))) -> 0 | I34: =IF($N34=TRUE,$E34/I$13,$E34*(1+(1/I$13))) -> 0 | J34: =IF($N34=TRUE,$E34/J$13,$E34*(1+(1/J$13))) -> 0 | K34: =IF($N34=TRUE,$E34/K$13,$E34*(1+(1/K$13))) -> 0 | L34: =IF($N34=TRUE,$E34/L$13,$E34*(1+(1/L$13))) -> 0 | M34: =IF($N34=TRUE,$E34/M$13,$E34*(1+(1/M$13))) -> 0 | N34: FALSE
E35: =C35*D35 -> 0 | F35: =IF($N35=TRUE,$E35/F$13,$E35*(1+(1/F$13))) -> 0 | G35: =IF($N35=TRUE,$E35/G$13,$E35*(1+(1/G$13))) -> 0 | H35: =IF($N35=TRUE,$E35/H$13,$E35*(1+(1/H$13))) -> 0 | I35: =IF($N35=TRUE,$E35/I$13,$E35*(1+(1/I$13))) -> 0 | J35: =IF($N35=TRUE,$E35/J$13,$E35*(1+(1/J$13))) -> 0 | K35: =IF($N35=TRUE,$E35/K$13,$E35*(1+(1/K$13))) -> 0 | L35: =IF($N35=TRUE,$E35/L$13,$E35*(1+(1/L$13))) -> 0 | M35: =IF($N35=TRUE,$E35/M$13,$E35*(1+(1/M$13))) -> 0 | N35: FALSE | S35: QTY | T35: Total
E36: =C36*D36 -> 0 | F36: =IF($N36=TRUE,$E36/F$13,$E36*(1+(1/F$13))) -> 0 | G36: =IF($N36=TRUE,$E36/G$13,$E36*(1+(1/G$13))) -> 0 | H36: =IF($N36=TRUE,$E36/H$13,$E36*(1+(1/H$13))) -> 0 | I36: =IF($N36=TRUE,$E36/I$13,$E36*(1+(1/I$13))) -> 0 | J36: =IF($N36=TRUE,$E36/J$13,$E36*(1+(1/J$13))) -> 0 | K36: =IF($N36=TRUE,$E36/K$13,$E36*(1+(1/K$13))) -> 0 | L36: =IF($N36=TRUE,$E36/L$13,$E36*(1+(1/L$13))) -> 0 | M36: =IF($N36=TRUE,$E36/M$13,$E36*(1+(1/M$13))) -> 0 | N36: FALSE | S36: =M13 -> 1000 | T36: =M63 -> 0
E37: =C37*D37 -> 0 | F37: =IF($N37=TRUE,$E37/F$13,$E37*(1+(1/F$13))) -> 0 | G37: =IF($N37=TRUE,$E37/G$13,$E37*(1+(1/G$13))) -> 0 | H37: =IF($N37=TRUE,$E37/H$13,$E37*(1+(1/H$13))) -> 0 | I37: =IF($N37=TRUE,$E37/I$13,$E37*(1+(1/I$13))) -> 0 | J37: =IF($N37=TRUE,$E37/J$13,$E37*(1+(1/J$13))) -> 0 | K37: =IF($N37=TRUE,$E37/K$13,$E37*(1+(1/K$13))) -> 0 | L37: =IF($N37=TRUE,$E37/L$13,$E37*(1+(1/L$13))) -> 0 | M37: =IF($N37=TRUE,$E37/M$13,$E37*(1+(1/M$13))) -> 0 | N37: FALSE | S37: =L13 -> 500 | T37: =L63 -> 0
E38: =C38*D38 -> 0 | F38: =IF($N38=TRUE,$E38/F$13,$E38*(1+(1/F$13))) -> 0 | G38: =IF($N38=TRUE,$E38/G$13,$E38*(1+(1/G$13))) -> 0 | H38: =IF($N38=TRUE,$E38/H$13,$E38*(1+(1/H$13))) -> 0 | I38: =IF($N38=TRUE,$E38/I$13,$E38*(1+(1/I$13))) -> 0 | J38: =IF($N38=TRUE,$E38/J$13,$E38*(1+(1/J$13))) -> 0 | K38: =IF($N38=TRUE,$E38/K$13,$E38*(1+(1/K$13))) -> 0 | L38: =IF($N38=TRUE,$E38/L$13,$E38*(1+(1/L$13))) -> 0 | M38: =IF($N38=TRUE,$E38/M$13,$E38*(1+(1/M$13))) -> 0 | N38: FALSE | S38: =I13 -> 75 | T38: =I63 -> 0
E39: =C39*D39 -> 0 | F39: =IF($N39=TRUE,$E39/F$13,$E39*(1+(1/F$13))) -> 0 | G39: =IF($N39=TRUE,$E39/G$13,$E39*(1+(1/G$13))) -> 0 | H39: =IF($N39=TRUE,$E39/H$13,$E39*(1+(1/H$13))) -> 0 | I39: =IF($N39=TRUE,$E39/I$13,$E39*(1+(1/I$13))) -> 0 | J39: =IF($N39=TRUE,$E39/J$13,$E39*(1+(1/J$13))) -> 0 | K39: =IF($N39=TRUE,$E39/K$13,$E39*(1+(1/K$13))) -> 0 | L39: =IF($N39=TRUE,$E39/L$13,$E39*(1+(1/L$13))) -> 0 | M39: =IF($N39=TRUE,$E39/M$13,$E39*(1+(1/M$13))) -> 0 | N39: FALSE | S39: =H13 -> 50 | T39: =H63 -> 0
E40: =C40*D40 -> 0 | F40: =IF($N40=TRUE,$E40/F$13,$E40*(1+(1/F$13))) -> 0 | G40: =IF($N40=TRUE,$E40/G$13,$E40*(1+(1/G$13))) -> 0 | H40: =IF($N40=TRUE,$E40/H$13,$E40*(1+(1/H$13))) -> 0 | I40: =IF($N40=TRUE,$E40/I$13,$E40*(1+(1/I$13))) -> 0 | J40: =IF($N40=TRUE,$E40/J$13,$E40*(1+(1/J$13))) -> 0 | K40: =IF($N40=TRUE,$E40/K$13,$E40*(1+(1/K$13))) -> 0 | L40: =IF($N40=TRUE,$E40/L$13,$E40*(1+(1/L$13))) -> 0 | M40: =IF($N40=TRUE,$E40/M$13,$E40*(1+(1/M$13))) -> 0 | N40: FALSE | S40: =G13 -> 25 | T40: =G63 -> 0
E41: =C41*D41 -> 0 | F41: =IF($N41=TRUE,$E41/F$13,$E41*(1+(1/F$13))) -> 0 | G41: =IF($N41=TRUE,$E41/G$13,$E41*(1+(1/G$13))) -> 0 | H41: =IF($N41=TRUE,$E41/H$13,$E41*(1+(1/H$13))) -> 0 | I41: =IF($N41=TRUE,$E41/I$13,$E41*(1+(1/I$13))) -> 0 | J41: =IF($N41=TRUE,$E41/J$13,$E41*(1+(1/J$13))) -> 0 | K41: =IF($N41=TRUE,$E41/K$13,$E41*(1+(1/K$13))) -> 0 | L41: =IF($N41=TRUE,$E41/L$13,$E41*(1+(1/L$13))) -> 0 | M41: =IF($N41=TRUE,$E41/M$13,$E41*(1+(1/M$13))) -> 0 | N41: FALSE | S41: =F13 -> 10 | T41: =F63 -> 0
E42: =C42*D42 -> 0 | F42: =IF($N42=TRUE,$E42/F$13,$E42*(1+(1/F$13))) -> 0 | G42: =IF($N42=TRUE,$E42/G$13,$E42*(1+(1/G$13))) -> 0 | H42: =IF($N42=TRUE,$E42/H$13,$E42*(1+(1/H$13))) -> 0 | I42: =IF($N42=TRUE,$E42/I$13,$E42*(1+(1/I$13))) -> 0 | J42: =IF($N42=TRUE,$E42/J$13,$E42*(1+(1/J$13))) -> 0 | K42: =IF($N42=TRUE,$E42/K$13,$E42*(1+(1/K$13))) -> 0 | L42: =IF($N42=TRUE,$E42/L$13,$E42*(1+(1/L$13))) -> 0 | M42: =IF($N42=TRUE,$E42/M$13,$E42*(1+(1/M$13))) -> 0 | N42: FALSE
E43: =C43*D43 -> 0 | F43: =IF($N43=TRUE,$E43/F$13,$E43*(1+(1/F$13))) -> 0 | G43: =IF($N43=TRUE,$E43/G$13,$E43*(1+(1/G$13))) -> 0 | H43: =IF($N43=TRUE,$E43/H$13,$E43*(1+(1/H$13))) -> 0 | I43: =IF($N43=TRUE,$E43/I$13,$E43*(1+(1/I$13))) -> 0 | J43: =IF($N43=TRUE,$E43/J$13,$E43*(1+(1/J$13))) -> 0 | K43: =IF($N43=TRUE,$E43/K$13,$E43*(1+(1/K$13))) -> 0 | L43: =IF($N43=TRUE,$E43/L$13,$E43*(1+(1/L$13))) -> 0 | M43: =IF($N43=TRUE,$E43/M$13,$E43*(1+(1/M$13))) -> 0 | N43: FALSE
E44: =C44*D44 -> 0 | F44: =IF($N44=TRUE,$E44/F$13,$E44*(1+(1/F$13))) -> 0 | G44: =IF($N44=TRUE,$E44/G$13,$E44*(1+(1/G$13))) -> 0 | H44: =IF($N44=TRUE,$E44/H$13,$E44*(1+(1/H$13))) -> 0 | I44: =IF($N44=TRUE,$E44/I$13,$E44*(1+(1/I$13))) -> 0 | J44: =IF($N44=TRUE,$E44/J$13,$E44*(1+(1/J$13))) -> 0 | K44: =IF($N44=TRUE,$E44/K$13,$E44*(1+(1/K$13))) -> 0 | L44: =IF($N44=TRUE,$E44/L$13,$E44*(1+(1/L$13))) -> 0 | M44: =IF($N44=TRUE,$E44/M$13,$E44*(1+(1/M$13))) -> 0 | N44: FALSE
A45: PROCESSES/COMPONENTS | D45: SETUP $ | E45: RUN$ EA.
F46: =($D46/F$13)+$E46 -> 0 | G46: =($D46/G$13)+$E46 -> 0 | H46: =($D46/H$13)+$E46 -> 0 | I46: =($D46/I$13)+$E46 -> 0 | J46: =($D46/J$13)+$E46 -> 0 | K46: =($D46/K$13)+$E46 -> 0 | L46: =($D46/L$13)+$E46 -> 0 | M46: =($D46/M$13)+$E46 -> 0
F47: =($D47/F$13)+$E47 -> 0 | G47: =($D47/G$13)+$E47 -> 0 | H47: =($D47/H$13)+$E47 -> 0 | I47: =($D47/I$13)+$E47 -> 0 | J47: =($D47/J$13)+$E47 -> 0 | K47: =($D47/K$13)+$E47 -> 0 | L47: =($D47/L$13)+$E47 -> 0 | M47: =($D47/M$13)+$E47 -> 0
F48: =($D48/F$13)+$E48 -> 0 | G48: =($D48/G$13)+$E48 -> 0 | H48: =($D48/H$13)+$E48 -> 0 | I48: =($D48/I$13)+$E48 -> 0 | J48: =($D48/J$13)+$E48 -> 0 | K48: =($D48/K$13)+$E48 -> 0 | L48: =($D48/L$13)+$E48 -> 0 | M48: =($D48/M$13)+$E48 -> 0
F49: =($D49/F$13)+$E49 -> 0 | G49: =($D49/G$13)+$E49 -> 0 | H49: =($D49/H$13)+$E49 -> 0 | I49: =($D49/I$13)+$E49 -> 0 | J49: =($D49/J$13)+$E49 -> 0 | K49: =($D49/K$13)+$E49 -> 0 | L49: =($D49/L$13)+$E49 -> 0 | M49: =($D49/M$13)+$E49 -> 0
F50: =($D50/F$13)+$E50 -> 0 | G50: =($D50/G$13)+$E50 -> 0 | H50: =($D50/H$13)+$E50 -> 0 | I50: =($D50/I$13)+$E50 -> 0 | J50: =($D50/J$13)+$E50 -> 0 | K50: =($D50/K$13)+$E50 -> 0 | L50: =($D50/L$13)+$E50 -> 0 | M50: =($D50/M$13)+$E50 -> 0
B51: MATERIAL & HARDWARE TOTAL | F51: =SUM(F33:F44) -> 0 | G51: =SUM(G33:G44) -> 0 | H51: =SUM(H33:H44) -> 0 | I51: =SUM(I33:I44) -> 0 | J51: =SUM(J33:J44) -> 0 | K51: =SUM(K33:K44) -> 0 | L51: =SUM(L33:L44) -> 0 | M51: =SUM(M33:M44) -> 0 | N51: =IF(N13=0,0,SUM(N42:N44)) -> 0
B52: PROCESSES TOTAL | F52: =SUM(F46:F50) -> 0 | G52: =SUM(G46:G50) -> 0 | H52: =SUM(H46:H50) -> 0 | I52: =SUM(I46:I50) -> 0 | J52: =SUM(J46:J50) -> 0 | K52: =SUM(K46:K50) -> 0 | L52: =SUM(L46:L50) -> 0 | M52: =SUM(M46:M50) -> 0 | N52: =IF(N13=0,0,SUM(N46:N50)) -> 0
B53: M+L Subtotal | F53: =SUM(F30+F51+F52) -> 0 | G53: =SUM(G30+G51+G52) -> 0 | H53: =SUM(H30+H51+H52) -> 0 | I53: =SUM(I30+I51+I52) -> 0 | J53: =SUM(J30+J51+J52) -> 0 | K53: =SUM(K30+K51+K52) -> 0 | L53: =SUM(L30+L51+L52) -> 0 | M53: =SUM(M30+M51+M52) -> 0 | N53: =IF(N13=0,0,SUM(N30+N51+N52)) -> 0
E55: REFERENCE | F55: =SUM(F53+#REF!+#REF!) -> #REF! | G55: =SUM(G53+#REF!+#REF!) -> #REF! | H55: =SUM(H53+#REF!+#REF!) -> #REF! | I55: =SUM(I53+#REF!+#REF!) -> #REF! | J55: =SUM(J53+#REF!+#REF!) -> #REF! | K55: =SUM(K53+#REF!+#REF!) -> #REF! | L55: =SUM(L53+#REF!+#REF!) -> #REF! | M55: =SUM(M53+#REF!+#REF!) -> #REF! | N55: =SUM(N53+#REF!+#REF!) -> #REF!
D56: MARGIN | F56: =(F55-F53)/F55 -> #REF! | G56: =(G55-G53)/G55 -> #REF! | H56: =(H55-H53)/H55 -> #REF! | I56: =(I55-I53)/I55 -> #REF! | J56: =(J55-J53)/J55 -> #REF! | K56: =(K55-K53)/K55 -> #REF! | L56: =(L55-L53)/L55 -> #REF! | M56: =(M55-M53)/M55 -> #REF!
D57: LABOR | F57: =F30 -> 0 | G57: =G30 -> 0 | H57: =H30 -> 0 | I57: =I30 -> 0 | J57: =J30 -> 0 | K57: =K30 -> 0 | L57: =L30 -> 0 | M57: =M30 -> 0 | N57: =SUM((N30)) -> 0
C58: MAT'ls &HARDWARE | F58: =F51 -> 0 | G58: =G51 -> 0 | H58: =H51 -> 0 | I58: =I51 -> 0 | J58: =J51 -> 0 | K58: =K51 -> 0 | L58: =L51 -> 0 | M58: =M51 -> 0 | N58: =(N51) -> 0
D59: PROCESS | F59: =F52 -> 0 | G59: =G52 -> 0 | H59: =H52 -> 0 | I59: =I52 -> 0 | J59: =J52 -> 0 | K59: =K52 -> 0 | L59: =L52 -> 0 | M59: =M52 -> 0 | N59: =N52 -> 0
D60: Subtotal | F60: =SUM(F57:F59) -> 0 | G60: =SUM(G57:G59) -> 0 | H60: =SUM(H57:H59) -> 0 | I60: =SUM(I57:I59) -> 0 | J60: =SUM(J57:J59) -> 0 | K60: =SUM(K57:K59) -> 0 | L60: =SUM(L57:L59) -> 0 | M60: =SUM(M57:M59) -> 0 | N60: =SUM(N57:N59) -> 0
D61: AMORTIZED | F61: =$N$60/F13 -> 0 | G61: =$N$60/G13 -> 0 | H61: =$N$60/H13 -> 0 | I61: =$N$60/I13 -> 0 | J61: =$N$60/J13 -> 0 | K61: =$N$60/K13 -> 0 | L61: =$N$60/L13 -> 0 | M61: =$N$60/M13 -> 0
D62: Facilities | F62: 0 | G62: 0 | H62: 0 | I62: 0 | J62: 0 | K62: 0 | L62: 0 | M62: 0
D63: =B3 -> 7 | F63: =SUM(F60:F62) -> 0 | G63: =SUM(G60:G62) -> 0 | H63: =SUM(H60:H62) -> 0 | I63: =SUM(I60:I62) -> 0 | J63: =SUM(J60:J62) -> 0 | K63: =SUM(K60:K62) -> 0 | L63: =SUM(L60:L62) -> 0 | M63: =SUM(M60:M62) -> 0
A66: NRESC/TOOLING
A67: SETUPS
A68: FAIR
A69: SOURCE

Sheet Subassy 8
A2: CUSTOMER: | F2: Comments:
A3: P/N: | B3: 8 | D3: NSN #:
A4: REV: | D4: SOL #:
A5: QUOTE LOG No.: | D5: RFQ #:
A6: QTY: | B6: =F13&", "&G13&", "&H13&", "&I13&", "&J13&", "&K13&", "&L13&", "&M13 -> 10, 25, 50, 75, 100, 250, 500, 1000
A7: DATE:
A8: ESTIMATOR:
A11: MANUFACTURING OPERATIONS | F11: COST ESTIMATED QUANTITIES | N11: NRE/SET-UP
B13: SET-UP TIME | C13: RUN TIME | E13: LABOR RATE | F13: ='Top Assy'!F13 -> 10 | G13: ='Top Assy'!G13 -> 25 | H13: ='Top Assy'!H13 -> 50 | I13: ='Top Assy'!I13 -> 75 | J13: ='Top Assy'!J13 -> 100 | K13: ='Top Assy'!K13 -> 250 | L13: ='Top Assy'!L13 -> 500 | M13: ='Top Assy'!M13 -> 1000 | N13: 1
A14: Program | E14: 0 | N14: =(($B14/N$13*$E14)+($C14*$E14)) -> 0
A15: Fixtures | E15: 0 | N15: =(($B15/N$13*$E15)+($C15*$E15)) -> 0
A16: Mill/Turn | E16: 0 | F16: =(($B16/F$13*$E16)+($C16*$E16)) -> 0 | G16: =(($B16/G$13*$E16)+($C16*$E16)) -> 0 | H16: =(($B16/H$13*$E16)+($C16*$E16)) -> 0 | I16: =(($B16/I$13*$E16)+($C16*$E16)) -> 0 | J16: =(($B16/J$13*$E16)+($C16*$E16)) -> 0 | K16: =(($B16/K$13*$E16)+($C16*$E16)) -> 0 | L16: =(($B16/L$13*$E16)+($C16*$E16)) -> 0 | M16: =(($B16/M$13*$E16)+($C16*$E16)) -> 0
A17: Metals - Mills | E17: 0 | F17: =(($B17/F$13*$E17)+($C17*$E17)) -> 0 | G17: =(($B17/G$13*$E17)+($C17*$E17)) -> 0 | H17: =(($B17/H$13*$E17)+($C17*$E17)) -> 0 | I17: =(($B17/I$13*$E17)+($C17*$E17)) -> 0 | J17: =(($B17/J$13*$E17)+($C17*$E17)) -> 0 | K17: =(($B17/K$13*$E17)+($C17*$E17)) -> 0 | L17: =(($B17/L$13*$E17)+($C17*$E17)) -> 0 | M17: =(($B17/M$13*$E17)+($C17*$E17)) -> 0
A18: Metals - Lathe | E18: 0 | F18: =(($B18/F$13*$E18)+($C18*$E18)) -> 0 | G18: =(($B18/G$13*$E18)+($C18*$E18)) -> 0 | H18: =(($B18/H$13*$E18)+($C18*$E18)) -> 0 | I18: =(($B18/I$13*$E18)+($C18*$E18)) -> 0 | J18: =(($B18/J$13*$E18)+($C18*$E18)) -> 0 | K18: =(($B18/K$13*$E18)+($C18*$E18)) -> 0 | L18: =(($B18/L$13*$E18)+($C18*$E18)) -> 0 | M18: =(($B18/M$13*$E18)+($C18*$E18)) -> 0
A19: Rubber Mold | E19: 0 | F19: =(($B19/F$13*$E19)+($C19*$E19)) -> 0 | G19: =(($B19/G$13*$E19)+($C19*$E19)) -> 0 | H19: =(($B19/H$13*$E19)+($C19*$E19)) -> 0 | I19: =(($B19/I$13*$E19)+($C19*$E19)) -> 0 | J19: =(($B19/J$13*$E19)+($C19*$E19)) -> 0 | K19: =(($B19/K$13*$E19)+($C19*$E19)) -> 0 | L19: =(($B19/L$13*$E19)+($C19*$E19)) -> 0 | M19: =(($B19/M$13*$E19)+($C19*$E19)) -> 0
A20: Plastic Injection Mold | E20: 0 | F20: =(($B20/F$13*$E20)+($C20*$E20)) -> 0 | G20: =(($B20/G$13*$E20)+($C20*$E20)) -> 0 | H20: =(($B20/H$13*$E20)+($C20*$E20)) -> 0 | I20: =(($B20/I$13*$E20)+($C20*$E20)) -> 0 | J20: =(($B20/J$13*$E20)+($C20*$E20)) -> 0 | K20: =(($B20/K$13*$E20)+($C20*$E20)) -> 0 | L20: =(($B20/L$13*$E20)+($C20*$E20)) -> 0 | M20: =(($B20/M$13*$E20)+($C20*$E20)) -> 0
A21: Plastic Compression Mold | E21: 0 | F21: =(($B21/F$13*$E21)+($C21*$E21)) -> 0 | G21: =(($B21/G$13*$E21)+($C21*$E21)) -> 0 | H21: =(($B21/H$13*$E21)+($C21*$E21)) -> 0 | I21: =(($B21/I$13*$E21)+($C21*$E21)) -> 0 | J21: =(($B21/J$13*$E21)+($C21*$E21)) -> 0 | K21: =(($B21/K$13*$E21)+($C21*$E21)) -> 0 | L21: =(($B21/L$13*$E21)+($C21*$E21)) -> 0 | M21: =(($B21/M$13*$E21)+($C21*$E21)) -> 0
A22: Waterjet - Setup | E22: 0 | F22: =(($B22/F$13*$E22)+($C22*$E22)) -> 0 | G22: =(($B22/G$13*$E22)+($C22*$E22)) -> 0 | H22: =(($B22/H$13*$E22)+($C22*$E22)) -> 0 | I22: =(($B22/I$13*$E22)+($C22*$E22)) -> 0 | J22: =(($B22/J$13*$E22)+($C22*$E22)) -> 0 | K22: =(($B22/K$13*$E22)+($C22*$E22)) -> 0 | L22: =(($B22/L$13*$E22)+($C22*$E22)) -> 0 | M22: =(($B22/M$13*$E22)+($C22*$E22)) -> 0
A23: Waterjet - Operator | E23: 0 | F23: =(($B23/F$13*$E23)+($C23*$E23)) -> 0 | G23: =(($B23/G$13*$E23)+($C23*$E23)) -> 0 | H23: =(($B23/H$13*$E23)+($C23*$E23)) -> 0 | I23: =(($B23/I$13*$E23)+($C23*$E23)) -> 0 | J23: =(($B23/J$13*$E23)+($C23*$E23)) -> 0 | K23: =(($B23/K$13*$E23)+($C23*$E23)) -> 0 | L23: =(($B23/L$13*$E23)+($C23*$E23)) -> 0 | M23: =(($B23/M$13*$E23)+($C23*$E23)) -> 0
A24: Assembly, Die Punch, Deburr | E24: 0 | F24: =(($B24/F$13*$E24)+($C24*$E24)) -> 0 | G24: =(($B24/G$13*$E24)+($C24*$E24)) -> 0 | H24: =(($B24/H$13*$E24)+($C24*$E24)) -> 0 | I24: =(($B24/I$13*$E24)+($C24*$E24)) -> 0 | J24: =(($B24/J$13*$E24)+($C24*$E24)) -> 0 | K24: =(($B24/K$13*$E24)+($C24*$E24)) -> 0 | L24: =(($B24/L$13*$E24)+($C24*$E24)) -> 0 | M24: =(($B24/M$13*$E24)+($C24*$E24)) -> 0
A25: Quality Inspection | E25: 0 | F25: =(($B25/F$13*$E25)+($C25*$E25)) -> 0 | G25: =(($B25/G$13*$E25)+($C25*$E25)) -> 0 | H25: =(($B25/H$13*$E25)+($C25*$E25)) -> 0 | I25: =(($B25/I$13*$E25)+($C25*$E25)) -> 0 | J25: =(($B25/J$13*$E25)+($C25*$E25)) -> 0 | K25: =(($B25/K$13*$E25)+($C25*$E25)) -> 0 | L25: =(($B25/L$13*$E25)+($C25*$E25)) -> 0 | M25: =(($B25/M$13*$E25)+($C25*$E25)) -> 0
C26: Labor | E26: Basic LABOR | F26: =SUM(F16:F25) -> 0 | G26: =SUM(G16:G25) -> 0 | H26: =SUM(H16:H25) -> 0 | I26: =SUM(I16:I25) -> 0 | J26: =SUM(J16:J25) -> 0 | K26: =SUM(K16:K25) -> 0 | L26: =SUM(L16:L25) -> 0 | M26: =SUM(M16:M25) -> 0 | N26: =SUM(N14:N25) -> 0
B27: T. setup | C27: T.RUN | E27: hrs | F27: =(($B$28/F13)+$C$28)/60 -> 0 | G27: =(($B$28/G13)+$C$28)/60 -> 0 | H27: =(($B$28/H13)+$C$28)/60 -> 0 | I27: =(($B$28/I13)+$C$28)/60 -> 0 | J27: =(($B$28/J13)+$C$28)/60 -> 0 | K27: =(($B$28/K13)+$C$28)/60 -> 0 | L27: =(($B$28/L13)+$C$28)/60 -> 0 | M27: =(($B$28/M13)+$C$28)/60 -> 0
B28: =SUM(B16:B25) -> 0 | C28: =SUM(C16:C25) -> 0 | D28: 0 | E28: BURDEN | F28: =F26*$D$28 -> 0 | G28: =G26*$D$28 -> 0 | H28: =H26*$D$28 -> 0 | I28: =I26*$D$28 -> 0 | J28: =J26*$D$28 -> 0 | K28: =K26*$D$28 -> 0 | L28: =L26*$D$28 -> 0 | M28: =M26*$D$28 -> 0
E30: Total | F30: =F26+F28 -> 0 | G30: =G26+G28 -> 0 | H30: =H26+H28 -> 0 | I30: =I26+I28 -> 0 | J30: =J26+J28 -> 0 | K30: =K26+K28 -> 0 | L30: =L26+L28 -> 0 | M30: =M26+M28 -> 0 | N30: =N26 -> 0
A32: RAW MATERIALS & HARDWARE | B32: Matl UoM | C32: PARTS QTY | D32: UNIT PRICE | E32: MAT'l BURDEN | F32: ="Qty: "& F13 -> Qty: 10 | G32: ="Qty: "& G13 -> Qty: 25 | H32: ="Qty: "& H13 -> Qty: 50 | I32: ="Qty: "& I13 -> Qty: 75 | J32: ="Qty: "& J13 -> Qty: 100 | K32: ="Qty: "& K13 -> Qty: 250 | L32: ="Qty: "& L13 -> Qty: 500 | M32: ="Qty: "& M13 -> Qty: 1000 | N32: Amortize/ Min Buy
E33: =C33*D33 -> 0 | F33: =IF($N33=TRUE,$E33/F$13,$E33*(1+(1/F$13))) -> 0 | G33: =IF($N33=TRUE,$E33/G$13,$E33*(1+(1/G$13))) -> 0 | H33: =IF($N33=TRUE,$E33/H$13,$E33*(1+(1/H$13))) -> 0 | I33: =IF($N33=TRUE,$E33/I$13,$E33*(1+(1/I$13))) -> 0 | J33: =IF($N33=TRUE,$E33/J$13,$E33*(1+(1/J$13))) -> 0 | K33: =IF($N33=TRUE,$E33/K$13,$E33*(1+(1/K$13))) -> 0 | L33: =IF($N33=TRUE,$E33/L$13,$E33*(1+(1/L$13))) -> 0 | M33: =IF($N33=TRUE,$E33/M$13,$E33*(1+(1/M$13))) -> 0 | N33: FALSE
E34: =C34*D34 -> 0 | F34: =IF($N34=TRUE,$E34/F$13,$E34*(1+(1/F$13))) -> 0 | G34: =IF($N34=TRUE,$E34/G$13,$E34*(1+(1/G$13))) -> 0 | H34: =IF($N34=TRUE,$E34/H$13,$E34*(1+(1/H$13))) -> 0 | I34: =IF($N34=TRUE,$E34/I$13,$E34*(1+(1/I$13))) -> 0 | J34: =IF($N34=TRUE,$E34/J$13,$E34*(1+(1/J$13))) -> 0 | K34: =IF($N34=TRUE,$E34/K$13,$E34*(1+(1/K$13))) -> 0 | L34: =IF($N34=TRUE,$E34/L$13,$E34*(1+(1/L$13))) -> 0 | M34: =IF($N34=TRUE,$E34/M$13,$E34*(1+(1/M$13))) -> 0 | N34: FALSE
E35: =C35*D35 -> 0 | F35: =IF($N35=TRUE,$E35/F$13,$E35*(1+(1/F$13))) -> 0 | G35: =IF($N35=TRUE,$E35/G$13,$E35*(1+(1/G$13))) -> 0 | H35: =IF($N35=TRUE,$E35/H$13,$E35*(1+(1/H$13))) -> 0 | I35: =IF($N35=TRUE,$E35/I$13,$E35*(1+(1/I$13))) -> 0 | J35: =IF($N35=TRUE,$E35/J$13,$E35*(1+(1/J$13))) -> 0 | K35: =IF($N35=TRUE,$E35/K$13,$E35*(1+(1/K$13))) -> 0 | L35: =IF($N35=TRUE,$E35/L$13,$E35*(1+(1/L$13))) -> 0 | M35: =IF($N35=TRUE,$E35/M$13,$E35*(1+(1/M$13))) -> 0 | N35: FALSE | S35: QTY | T35: Total
E36: =C36*D36 -> 0 | F36: =IF($N36=TRUE,$E36/F$13,$E36*(1+(1/F$13))) -> 0 | G36: =IF($N36=TRUE,$E36/G$13,$E36*(1+(1/G$13))) -> 0 | H36: =IF($N36=TRUE,$E36/H$13,$E36*(1+(1/H$13))) -> 0 | I36: =IF($N36=TRUE,$E36/I$13,$E36*(1+(1/I$13))) -> 0 | J36: =IF($N36=TRUE,$E36/J$13,$E36*(1+(1/J$13))) -> 0 | K36: =IF($N36=TRUE,$E36/K$13,$E36*(1+(1/K$13))) -> 0 | L36: =IF($N36=TRUE,$E36/L$13,$E36*(1+(1/L$13))) -> 0 | M36: =IF($N36=TRUE,$E36/M$13,$E36*(1+(1/M$13))) -> 0 | N36: FALSE | S36: =M13 -> 1000 | T36: =M63 -> 0
E37: =C37*D37 -> 0 | F37: =IF($N37=TRUE,$E37/F$13,$E37*(1+(1/F$13))) -> 0 | G37: =IF($N37=TRUE,$E37/G$13,$E37*(1+(1/G$13))) -> 0 | H37: =IF($N37=TRUE,$E37/H$13,$E37*(1+(1/H$13))) -> 0 | I37: =IF($N37=TRUE,$E37/I$13,$E37*(1+(1/I$13))) -> 0 | J37: =IF($N37=TRUE,$E37/J$13,$E37*(1+(1/J$13))) -> 0 | K37: =IF($N37=TRUE,$E37/K$13,$E37*(1+(1/K$13))) -> 0 | L37: =IF($N37=TRUE,$E37/L$13,$E37*(1+(1/L$13))) -> 0 | M37: =IF($N37=TRUE,$E37/M$13,$E37*(1+(1/M$13))) -> 0 | N37: FALSE | S37: =L13 -> 500 | T37: =L63 -> 0
E38: =C38*D38 -> 0 | F38: =IF($N38=TRUE,$E38/F$13,$E38*(1+(1/F$13))) -> 0 | G38: =IF($N38=TRUE,$E38/G$13,$E38*(1+(1/G$13))) -> 0 | H38: =IF($N38=TRUE,$E38/H$13,$E38*(1+(1/H$13))) -> 0 | I38: =IF($N38=TRUE,$E38/I$13,$E38*(1+(1/I$13))) -> 0 | J38: =IF($N38=TRUE,$E38/J$13,$E38*(1+(1/J$13))) -> 0 | K38: =IF($N38=TRUE,$E38/K$13,$E38*(1+(1/K$13))) -> 0 | L38: =IF($N38=TRUE,$E38/L$13,$E38*(1+(1/L$13))) -> 0 | M38: =IF($N38=TRUE,$E38/M$13,$E38*(1+(1/M$13))) -> 0 | N38: FALSE | S38: =I13 -> 75 | T38: =I63 -> 0
E39: =C39*D39 -> 0 | F39: =IF($N39=TRUE,$E39/F$13,$E39*(1+(1/F$13))) -> 0 | G39: =IF($N39=TRUE,$E39/G$13,$E39*(1+(1/G$13))) -> 0 | H39: =IF($N39=TRUE,$E39/H$13,$E39*(1+(1/H$13))) -> 0 | I39: =IF($N39=TRUE,$E39/I$13,$E39*(1+(1/I$13))) -> 0 | J39: =IF($N39=TRUE,$E39/J$13,$E39*(1+(1/J$13))) -> 0 | K39: =IF($N39=TRUE,$E39/K$13,$E39*(1+(1/K$13))) -> 0 | L39: =IF($N39=TRUE,$E39/L$13,$E39*(1+(1/L$13))) -> 0 | M39: =IF($N39=TRUE,$E39/M$13,$E39*(1+(1/M$13))) -> 0 | N39: FALSE | S39: =H13 -> 50 | T39: =H63 -> 0
E40: =C40*D40 -> 0 | F40: =IF($N40=TRUE,$E40/F$13,$E40*(1+(1/F$13))) -> 0 | G40: =IF($N40=TRUE,$E40/G$13,$E40*(1+(1/G$13))) -> 0 | H40: =IF($N40=TRUE,$E40/H$13,$E40*(1+(1/H$13))) -> 0 | I40: =IF($N40=TRUE,$E40/I$13,$E40*(1+(1/I$13))) -> 0 | J40: =IF($N40=TRUE,$E40/J$13,$E40*(1+(1/J$13))) -> 0 | K40: =IF($N40=TRUE,$E40/K$13,$E40*(1+(1/K$13))) -> 0 | L40: =IF($N40=TRUE,$E40/L$13,$E40*(1+(1/L$13))) -> 0 | M40: =IF($N40=TRUE,$E40/M$13,$E40*(1+(1/M$13))) -> 0 | N40: FALSE | S40: =G13 -> 25 | T40: =G63 -> 0
E41: =C41*D41 -> 0 | F41: =IF($N41=TRUE,$E41/F$13,$E41*(1+(1/F$13))) -> 0 | G41: =IF($N41=TRUE,$E41/G$13,$E41*(1+(1/G$13))) -> 0 | H41: =IF($N41=TRUE,$E41/H$13,$E41*(1+(1/H$13))) -> 0 | I41: =IF($N41=TRUE,$E41/I$13,$E41*(1+(1/I$13))) -> 0 | J41: =IF($N41=TRUE,$E41/J$13,$E41*(1+(1/J$13))) -> 0 | K41: =IF($N41=TRUE,$E41/K$13,$E41*(1+(1/K$13))) -> 0 | L41: =IF($N41=TRUE,$E41/L$13,$E41*(1+(1/L$13))) -> 0 | M41: =IF($N41=TRUE,$E41/M$13,$E41*(1+(1/M$13))) -> 0 | N41: FALSE | S41: =F13 -> 10 | T41: =F63 -> 0
E42: =C42*D42 -> 0 | F42: =IF($N42=TRUE,$E42/F$13,$E42*(1+(1/F$13))) -> 0 | G42: =IF($N42=TRUE,$E42/G$13,$E42*(1+(1/G$13))) -> 0 | H42: =IF($N42=TRUE,$E42/H$13,$E42*(1+(1/H$13))) -> 0 | I42: =IF($N42=TRUE,$E42/I$13,$E42*(1+(1/I$13))) -> 0 | J42: =IF($N42=TRUE,$E42/J$13,$E42*(1+(1/J$13))) -> 0 | K42: =IF($N42=TRUE,$E42/K$13,$E42*(1+(1/K$13))) -> 0 | L42: =IF($N42=TRUE,$E42/L$13,$E42*(1+(1/L$13))) -> 0 | M42: =IF($N42=TRUE,$E42/M$13,$E42*(1+(1/M$13))) -> 0 | N42: FALSE
E43: =C43*D43 -> 0 | F43: =IF($N43=TRUE,$E43/F$13,$E43*(1+(1/F$13))) -> 0 | G43: =IF($N43=TRUE,$E43/G$13,$E43*(1+(1/G$13))) -> 0 | H43: =IF($N43=TRUE,$E43/H$13,$E43*(1+(1/H$13))) -> 0 | I43: =IF($N43=TRUE,$E43/I$13,$E43*(1+(1/I$13))) -> 0 | J43: =IF($N43=TRUE,$E43/J$13,$E43*(1+(1/J$13))) -> 0 | K43: =IF($N43=TRUE,$E43/K$13,$E43*(1+(1/K$13))) -> 0 | L43: =IF($N43=TRUE,$E43/L$13,$E43*(1+(1/L$13))) -> 0 | M43: =IF($N43=TRUE,$E43/M$13,$E43*(1+(1/M$13))) -> 0 | N43: FALSE
E44: =C44*D44 -> 0 | F44: =IF($N44=TRUE,$E44/F$13,$E44*(1+(1/F$13))) -> 0 | G44: =IF($N44=TRUE,$E44/G$13,$E44*(1+(1/G$13))) -> 0 | H44: =IF($N44=TRUE,$E44/H$13,$E44*(1+(1/H$13))) -> 0 | I44: =IF($N44=TRUE,$E44/I$13,$E44*(1+(1/I$13))) -> 0 | J44: =IF($N44=TRUE,$E44/J$13,$E44*(1+(1/J$13))) -> 0 | K44: =IF($N44=TRUE,$E44/K$13,$E44*(1+(1/K$13))) -> 0 | L44: =IF($N44=TRUE,$E44/L$13,$E44*(1+(1/L$13))) -> 0 | M44: =IF($N44=TRUE,$E44/M$13,$E44*(1+(1/M$13))) -> 0 | N44: FALSE
A45: PROCESSES/COMPONENTS | D45: SETUP $ | E45: RUN$ EA.
F46: =($D46/F$13)+$E46 -> 0 | G46: =($D46/G$13)+$E46 -> 0 | H46: =($D46/H$13)+$E46 -> 0 | I46: =($D46/I$13)+$E46 -> 0 | J46: =($D46/J$13)+$E46 -> 0 | K46: =($D46/K$13)+$E46 -> 0 | L46: =($D46/L$13)+$E46 -> 0 | M46: =($D46/M$13)+$E46 -> 0
F47: =($D47/F$13)+$E47 -> 0 | G47: =($D47/G$13)+$E47 -> 0 | H47: =($D47/H$13)+$E47 -> 0 | I47: =($D47/I$13)+$E47 -> 0 | J47: =($D47/J$13)+$E47 -> 0 | K47: =($D47/K$13)+$E47 -> 0 | L47: =($D47/L$13)+$E47 -> 0 | M47: =($D47/M$13)+$E47 -> 0
F48: =($D48/F$13)+$E48 -> 0 | G48: =($D48/G$13)+$E48 -> 0 | H48: =($D48/H$13)+$E48 -> 0 | I48: =($D48/I$13)+$E48 -> 0 | J48: =($D48/J$13)+$E48 -> 0 | K48: =($D48/K$13)+$E48 -> 0 | L48: =($D48/L$13)+$E48 -> 0 | M48: =($D48/M$13)+$E48 -> 0
F49: =($D49/F$13)+$E49 -> 0 | G49: =($D49/G$13)+$E49 -> 0 | H49: =($D49/H$13)+$E49 -> 0 | I49: =($D49/I$13)+$E49 -> 0 | J49: =($D49/J$13)+$E49 -> 0 | K49: =($D49/K$13)+$E49 -> 0 | L49: =($D49/L$13)+$E49 -> 0 | M49: =($D49/M$13)+$E49 -> 0
F50: =($D50/F$13)+$E50 -> 0 | G50: =($D50/G$13)+$E50 -> 0 | H50: =($D50/H$13)+$E50 -> 0 | I50: =($D50/I$13)+$E50 -> 0 | J50: =($D50/J$13)+$E50 -> 0 | K50: =($D50/K$13)+$E50 -> 0 | L50: =($D50/L$13)+$E50 -> 0 | M50: =($D50/M$13)+$E50 -> 0
B51: MATERIAL & HARDWARE TOTAL | F51: =SUM(F33:F44) -> 0 | G51: =SUM(G33:G44) -> 0 | H51: =SUM(H33:H44) -> 0 | I51: =SUM(I33:I44) -> 0 | J51: =SUM(J33:J44) -> 0 | K51: =SUM(K33:K44) -> 0 | L51: =SUM(L33:L44) -> 0 | M51: =SUM(M33:M44) -> 0 | N51: =IF(N13=0,0,SUM(N42:N44)) -> 0
B52: PROCESSES TOTAL | F52: =SUM(F46:F50) -> 0 | G52: =SUM(G46:G50) -> 0 | H52: =SUM(H46:H50) -> 0 | I52: =SUM(I46:I50) -> 0 | J52: =SUM(J46:J50) -> 0 | K52: =SUM(K46:K50) -> 0 | L52: =SUM(L46:L50) -> 0 | M52: =SUM(M46:M50) -> 0 | N52: =IF(N13=0,0,SUM(N46:N50)) -> 0
B53: M+L Subtotal | F53: =SUM(F30+F51+F52) -> 0 | G53: =SUM(G30+G51+G52) -> 0 | H53: =SUM(H30+H51+H52) -> 0 | I53: =SUM(I30+I51+I52) -> 0 | J53: =SUM(J30+J51+J52) -> 0 | K53: =SUM(K30+K51+K52) -> 0 | L53: =SUM(L30+L51+L52) -> 0 | M53: =SUM(M30+M51+M52) -> 0 | N53: =IF(N13=0,0,SUM(N30+N51+N52)) -> 0
E55: REFERENCE | F55: =SUM(F53+#REF!+#REF!) -> #REF! | G55: =SUM(G53+#REF!+#REF!) -> #REF! | H55: =SUM(H53+#REF!+#REF!) -> #REF! | I55: =SUM(I53+#REF!+#REF!) -> #REF! | J55: =SUM(J53+#REF!+#REF!) -> #REF! | K55: =SUM(K53+#REF!+#REF!) -> #REF! | L55: =SUM(L53+#REF!+#REF!) -> #REF! | M55: =SUM(M53+#REF!+#REF!) -> #REF! | N55: =SUM(N53+#REF!+#REF!) -> #REF!
D56: MARGIN | F56: =(F55-F53)/F55 -> #REF! | G56: =(G55-G53)/G55 -> #REF! | H56: =(H55-H53)/H55 -> #REF! | I56: =(I55-I53)/I55 -> #REF! | J56: =(J55-J53)/J55 -> #REF! | K56: =(K55-K53)/K55 -> #REF! | L56: =(L55-L53)/L55 -> #REF! | M56: =(M55-M53)/M55 -> #REF!
D57: LABOR | F57: =F30 -> 0 | G57: =G30 -> 0 | H57: =H30 -> 0 | I57: =I30 -> 0 | J57: =J30 -> 0 | K57: =K30 -> 0 | L57: =L30 -> 0 | M57: =M30 -> 0 | N57: =SUM((N30)) -> 0
C58: MAT'ls &HARDWARE | F58: =F51 -> 0 | G58: =G51 -> 0 | H58: =H51 -> 0 | I58: =I51 -> 0 | J58: =J51 -> 0 | K58: =K51 -> 0 | L58: =L51 -> 0 | M58: =M51 -> 0 | N58: =(N51) -> 0
D59: PROCESS | F59: =F52 -> 0 | G59: =G52 -> 0 | H59: =H52 -> 0 | I59: =I52 -> 0 | J59: =J52 -> 0 | K59: =K52 -> 0 | L59: =L52 -> 0 | M59: =M52 -> 0 | N59: =N52 -> 0
D60: Subtotal | F60: =SUM(F57:F59) -> 0 | G60: =SUM(G57:G59) -> 0 | H60: =SUM(H57:H59) -> 0 | I60: =SUM(I57:I59) -> 0 | J60: =SUM(J57:J59) -> 0 | K60: =SUM(K57:K59) -> 0 | L60: =SUM(L57:L59) -> 0 | M60: =SUM(M57:M59) -> 0 | N60: =SUM(N57:N59) -> 0
D61: AMORTIZED | F61: =$N$60/F13 -> 0 | G61: =$N$60/G13 -> 0 | H61: =$N$60/H13 -> 0 | I61: =$N$60/I13 -> 0 | J61: =$N$60/J13 -> 0 | K61: =$N$60/K13 -> 0 | L61: =$N$60/L13 -> 0 | M61: =$N$60/M13 -> 0
D62: Facilities | F62: 0 | G62: 0 | H62: 0 | I62: 0 | J62: 0 | K62: 0 | L62: 0 | M62: 0
D63: =B3 -> 8 | F63: =SUM(F60:F62) -> 0 | G63: =SUM(G60:G62) -> 0 | H63: =SUM(H60:H62) -> 0 | I63: =SUM(I60:I62) -> 0 | J63: =SUM(J60:J62) -> 0 | K63: =SUM(K60:K62) -> 0 | L63: =SUM(L60:L62) -> 0 | M63: =SUM(M60:M62) -> 0
A66: NRESC/TOOLING
A67: SETUPS
A68: FAIR
A69: SOURCE

Sheet Subassy 9
A2: CUSTOMER: | F2: Comments:
A3: P/N: | B3: 9 | D3: NSN #:
A4: REV: | D4: SOL #:
A5: QUOTE LOG No.: | D5: RFQ #:
A6: QTY: | B6: =F13&", "&G13&", "&H13&", "&I13&", "&J13&", "&K13&", "&L13&", "&M13 -> 10, 25, 50, 75, 100, 250, 500, 1000
A7: DATE:
A8: ESTIMATOR:
A11: MANUFACTURING OPERATIONS | F11: COST ESTIMATED QUANTITIES | N11: NRE/SET-UP
B13: SET-UP TIME | C13: RUN TIME | E13: LABOR RATE | F13: ='Top Assy'!F13 -> 10 | G13: ='Top Assy'!G13 -> 25 | H13: ='Top Assy'!H13 -> 50 | I13: ='Top Assy'!I13 -> 75 | J13: ='Top Assy'!J13 -> 100 | K13: ='Top Assy'!K13 -> 250 | L13: ='Top Assy'!L13 -> 500 | M13: ='Top Assy'!M13 -> 1000 | N13: 1
A14: Program | E14: 0 | N14: =(($B14/N$13*$E14)+($C14*$E14)) -> 0
A15: Fixtures | E15: 0 | N15: =(($B15/N$13*$E15)+($C15*$E15)) -> 0
A16: Mill/Turn | E16: 0 | F16: =(($B16/F$13*$E16)+($C16*$E16)) -> 0 | G16: =(($B16/G$13*$E16)+($C16*$E16)) -> 0 | H16: =(($B16/H$13*$E16)+($C16*$E16)) -> 0 | I16: =(($B16/I$13*$E16)+($C16*$E16)) -> 0 | J16: =(($B16/J$13*$E16)+($C16*$E16)) -> 0 | K16: =(($B16/K$13*$E16)+($C16*$E16)) -> 0 | L16: =(($B16/L$13*$E16)+($C16*$E16)) -> 0 | M16: =(($B16/M$13*$E16)+($C16*$E16)) -> 0
A17: Metals - Mills | E17: 0 | F17: =(($B17/F$13*$E17)+($C17*$E17)) -> 0 | G17: =(($B17/G$13*$E17)+($C17*$E17)) -> 0 | H17: =(($B17/H$13*$E17)+($C17*$E17)) -> 0 | I17: =(($B17/I$13*$E17)+($C17*$E17)) -> 0 | J17: =(($B17/J$13*$E17)+($C17*$E17)) -> 0 | K17: =(($B17/K$13*$E17)+($C17*$E17)) -> 0 | L17: =(($B17/L$13*$E17)+($C17*$E17)) -> 0 | M17: =(($B17/M$13*$E17)+($C17*$E17)) -> 0
A18: Metals - Lathe | E18: 0 | F18: =(($B18/F$13*$E18)+($C18*$E18)) -> 0 | G18: =(($B18/G$13*$E18)+($C18*$E18)) -> 0 | H18: =(($B18/H$13*$E18)+($C18*$E18)) -> 0 | I18: =(($B18/I$13*$E18)+($C18*$E18)) -> 0 | J18: =(($B18/J$13*$E18)+($C18*$E18)) -> 0 | K18: =(($B18/K$13*$E18)+($C18*$E18)) -> 0 | L18: =(($B18/L$13*$E18)+($C18*$E18)) -> 0 | M18: =(($B18/M$13*$E18)+($C18*$E18)) -> 0
A19: Rubber Mold | E19: 0 | F19: =(($B19/F$13*$E19)+($C19*$E19)) -> 0 | G19: =(($B19/G$13*$E19)+($C19*$E19)) -> 0 | H19: =(($B19/H$13*$E19)+($C19*$E19)) -> 0 | I19: =(($B19/I$13*$E19)+($C19*$E19)) -> 0 | J19: =(($B19/J$13*$E19)+($C19*$E19)) -> 0 | K19: =(($B19/K$13*$E19)+($C19*$E19)) -> 0 | L19: =(($B19/L$13*$E19)+($C19*$E19)) -> 0 | M19: =(($B19/M$13*$E19)+($C19*$E19)) -> 0
A20: Plastic Injection Mold | E20: 0 | F20: =(($B20/F$13*$E20)+($C20*$E20)) -> 0 | G20: =(($B20/G$13*$E20)+($C20*$E20)) -> 0 | H20: =(($B20/H$13*$E20)+($C20*$E20)) -> 0 | I20: =(($B20/I$13*$E20)+($C20*$E20)) -> 0 | J20: =(($B20/J$13*$E20)+($C20*$E20)) -> 0 | K20: =(($B20/K$13*$E20)+($C20*$E20)) -> 0 | L20: =(($B20/L$13*$E20)+($C20*$E20)) -> 0 | M20: =(($B20/M$13*$E20)+($C20*$E20)) -> 0
A21: Plastic Compression Mold | E21: 0 | F21: =(($B21/F$13*$E21)+($C21*$E21)) -> 0 | G21: =(($B21/G$13*$E21)+($C21*$E21)) -> 0 | H21: =(($B21/H$13*$E21)+($C21*$E21)) -> 0 | I21: =(($B21/I$13*$E21)+($C21*$E21)) -> 0 | J21: =(($B21/J$13*$E21)+($C21*$E21)) -> 0 | K21: =(($B21/K$13*$E21)+($C21*$E21)) -> 0 | L21: =(($B21/L$13*$E21)+($C21*$E21)) -> 0 | M21: =(($B21/M$13*$E21)+($C21*$E21)) -> 0
A22: Waterjet - Setup | E22: 0 | F22: =(($B22/F$13*$E22)+($C22*$E22)) -> 0 | G22: =(($B22/G$13*$E22)+($C22*$E22)) -> 0 | H22: =(($B22/H$13*$E22)+($C22*$E22)) -> 0 | I22: =(($B22/I$13*$E22)+($C22*$E22)) -> 0 | J22: =(($B22/J$13*$E22)+($C22*$E22)) -> 0 | K22: =(($B22/K$13*$E22)+($C22*$E22)) -> 0 | L22: =(($B22/L$13*$E22)+($C22*$E22)) -> 0 | M22: =(($B22/M$13*$E22)+($C22*$E22)) -> 0
A23: Waterjet - Operator | E23: 0 | F23: =(($B23/F$13*$E23)+($C23*$E23)) -> 0 | G23: =(($B23/G$13*$E23)+($C23*$E23)) -> 0 | H23: =(($B23/H$13*$E23)+($C23*$E23)) -> 0 | I23: =(($B23/I$13*$E23)+($C23*$E23)) -> 0 | J23: =(($B23/J$13*$E23)+($C23*$E23)) -> 0 | K23: =(($B23/K$13*$E23)+($C23*$E23)) -> 0 | L23: =(($B23/L$13*$E23)+($C23*$E23)) -> 0 | M23: =(($B23/M$13*$E23)+($C23*$E23)) -> 0
A24: Assembly, Die Punch, Deburr | E24: 0 | F24: =(($B24/F$13*$E24)+($C24*$E24)) -> 0 | G24: =(($B24/G$13*$E24)+($C24*$E24)) -> 0 | H24: =(($B24/H$13*$E24)+($C24*$E24)) -> 0 | I24: =(($B24/I$13*$E24)+($C24*$E24)) -> 0 | J24: =(($B24/J$13*$E24)+($C24*$E24)) -> 0 | K24: =(($B24/K$13*$E24)+($C24*$E24)) -> 0 | L24: =(($B24/L$13*$E24)+($C24*$E24)) -> 0 | M24: =(($B24/M$13*$E24)+($C24*$E24)) -> 0
A25: Quality Inspection | E25: 0 | F25: =(($B25/F$13*$E25)+($C25*$E25)) -> 0 | G25: =(($B25/G$13*$E25)+($C25*$E25)) -> 0 | H25: =(($B25/H$13*$E25)+($C25*$E25)) -> 0 | I25: =(($B25/I$13*$E25)+($C25*$E25)) -> 0 | J25: =(($B25/J$13*$E25)+($C25*$E25)) -> 0 | K25: =(($B25/K$13*$E25)+($C25*$E25)) -> 0 | L25: =(($B25/L$13*$E25)+($C25*$E25)) -> 0 | M25: =(($B25/M$13*$E25)+($C25*$E25)) -> 0
C26: Labor | E26: Basic LABOR | F26: =SUM(F16:F25) -> 0 | G26: =SUM(G16:G25) -> 0 | H26: =SUM(H16:H25) -> 0 | I26: =SUM(I16:I25) -> 0 | J26: =SUM(J16:J25) -> 0 | K26: =SUM(K16:K25) -> 0 | L26: =SUM(L16:L25) -> 0 | M26: =SUM(M16:M25) -> 0 | N26: =SUM(N14:N25) -> 0
B27: T. setup | C27: T.RUN | E27: hrs | F27: =(($B$28/F13)+$C$28)/60 -> 0 | G27: =(($B$28/G13)+$C$28)/60 -> 0 | H27: =(($B$28/H13)+$C$28)/60 -> 0 | I27: =(($B$28/I13)+$C$28)/60 -> 0 | J27: =(($B$28/J13)+$C$28)/60 -> 0 | K27: =(($B$28/K13)+$C$28)/60 -> 0 | L27: =(($B$28/L13)+$C$28)/60 -> 0 | M27: =(($B$28/M13)+$C$28)/60 -> 0
B28: =SUM(B16:B25) -> 0 | C28: =SUM(C16:C25) -> 0 | D28: 0 | E28: BURDEN | F28: =F26*$D$28 -> 0 | G28: =G26*$D$28 -> 0 | H28: =H26*$D$28 -> 0 | I28: =I26*$D$28 -> 0 | J28: =J26*$D$28 -> 0 | K28: =K26*$D$28 -> 0 | L28: =L26*$D$28 -> 0 | M28: =M26*$D$28 -> 0
E30: Total | F30: =F26+F28 -> 0 | G30: =G26+G28 -> 0 | H30: =H26+H28 -> 0 | I30: =I26+I28 -> 0 | J30: =J26+J28 -> 0 | K30: =K26+K28 -> 0 | L30: =L26+L28 -> 0 | M30: =M26+M28 -> 0 | N30: =N26 -> 0
A32: RAW MATERIALS & HARDWARE | B32: Matl UoM | C32: PARTS QTY | D32: UNIT PRICE | E32: MAT'l BURDEN | F32: ="Qty: "& F13 -> Qty: 10 | G32: ="Qty: "& G13 -> Qty: 25 | H32: ="Qty: "& H13 -> Qty: 50 | I32: ="Qty: "& I13 -> Qty: 75 | J32: ="Qty: "& J13 -> Qty: 100 | K32: ="Qty: "& K13 -> Qty: 250 | L32: ="Qty: "& L13 -> Qty: 500 | M32: ="Qty: "& M13 -> Qty: 1000 | N32: Amortize/ Min Buy
E33: =C33*D33 -> 0 | F33: =IF($N33=TRUE,$E33/F$13,$E33*(1+(1/F$13))) -> 0 | G33: =IF($N33=TRUE,$E33/G$13,$E33*(1+(1/G$13))) -> 0 | H33: =IF($N33=TRUE,$E33/H$13,$E33*(1+(1/H$13))) -> 0 | I33: =IF($N33=TRUE,$E33/I$13,$E33*(1+(1/I$13))) -> 0 | J33: =IF($N33=TRUE,$E33/J$13,$E33*(1+(1/J$13))) -> 0 | K33: =IF($N33=TRUE,$E33/K$13,$E33*(1+(1/K$13))) -> 0 | L33: =IF($N33=TRUE,$E33/L$13,$E33*(1+(1/L$13))) -> 0 | M33: =IF($N33=TRUE,$E33/M$13,$E33*(1+(1/M$13))) -> 0 | N33: FALSE
E34: =C34*D34 -> 0 | F34: =IF($N34=TRUE,$E34/F$13,$E34*(1+(1/F$13))) -> 0 | G34: =IF($N34=TRUE,$E34/G$13,$E34*(1+(1/G$13))) -> 0 | H34: =IF($N34=TRUE,$E34/H$13,$E34*(1+(1/H$13))) -> 0 | I34: =IF($N34=TRUE,$E34/I$13,$E34*(1+(1/I$13))) -> 0 | J34: =IF($N34=TRUE,$E34/J$13,$E34*(1+(1/J$13))) -> 0 | K34: =IF($N34=TRUE,$E34/K$13,$E34*(1+(1/K$13))) -> 0 | L34: =IF($N34=TRUE,$E34/L$13,$E34*(1+(1/L$13))) -> 0 | M34: =IF($N34=TRUE,$E34/M$13,$E34*(1+(1/M$13))) -> 0 | N34: FALSE
E35: =C35*D35 -> 0 | F35: =IF($N35=TRUE,$E35/F$13,$E35*(1+(1/F$13))) -> 0 | G35: =IF($N35=TRUE,$E35/G$13,$E35*(1+(1/G$13))) -> 0 | H35: =IF($N35=TRUE,$E35/H$13,$E35*(1+(1/H$13))) -> 0 | I35: =IF($N35=TRUE,$E35/I$13,$E35*(1+(1/I$13))) -> 0 | J35: =IF($N35=TRUE,$E35/J$13,$E35*(1+(1/J$13))) -> 0 | K35: =IF($N35=TRUE,$E35/K$13,$E35*(1+(1/K$13))) -> 0 | L35: =IF($N35=TRUE,$E35/L$13,$E35*(1+(1/L$13))) -> 0 | M35: =IF($N35=TRUE,$E35/M$13,$E35*(1+(1/M$13))) -> 0 | N35: FALSE | S35: QTY | T35: Total
E36: =C36*D36 -> 0 | F36: =IF($N36=TRUE,$E36/F$13,$E36*(1+(1/F$13))) -> 0 | G36: =IF($N36=TRUE,$E36/G$13,$E36*(1+(1/G$13))) -> 0 | H36: =IF($N36=TRUE,$E36/H$13,$E36*(1+(1/H$13))) -> 0 | I36: =IF($N36=TRUE,$E36/I$13,$E36*(1+(1/I$13))) -> 0 | J36: =IF($N36=TRUE,$E36/J$13,$E36*(1+(1/J$13))) -> 0 | K36: =IF($N36=TRUE,$E36/K$13,$E36*(1+(1/K$13))) -> 0 | L36: =IF($N36=TRUE,$E36/L$13,$E36*(1+(1/L$13))) -> 0 | M36: =IF($N36=TRUE,$E36/M$13,$E36*(1+(1/M$13))) -> 0 | N36: FALSE | S36: =M13 -> 1000 | T36: =M63 -> 0
E37: =C37*D37 -> 0 | F37: =IF($N37=TRUE,$E37/F$13,$E37*(1+(1/F$13))) -> 0 | G37: =IF($N37=TRUE,$E37/G$13,$E37*(1+(1/G$13))) -> 0 | H37: =IF($N37=TRUE,$E37/H$13,$E37*(1+(1/H$13))) -> 0 | I37: =IF($N37=TRUE,$E37/I$13,$E37*(1+(1/I$13))) -> 0 | J37: =IF($N37=TRUE,$E37/J$13,$E37*(1+(1/J$13))) -> 0 | K37: =IF($N37=TRUE,$E37/K$13,$E37*(1+(1/K$13))) -> 0 | L37: =IF($N37=TRUE,$E37/L$13,$E37*(1+(1/L$13))) -> 0 | M37: =IF($N37=TRUE,$E37/M$13,$E37*(1+(1/M$13))) -> 0 | N37: FALSE | S37: =L13 -> 500 | T37: =L63 -> 0
E38: =C38*D38 -> 0 | F38: =IF($N38=TRUE,$E38/F$13,$E38*(1+(1/F$13))) -> 0 | G38: =IF($N38=TRUE,$E38/G$13,$E38*(1+(1/G$13))) -> 0 | H38: =IF($N38=TRUE,$E38/H$13,$E38*(1+(1/H$13))) -> 0 | I38: =IF($N38=TRUE,$E38/I$13,$E38*(1+(1/I$13))) -> 0 | J38: =IF($N38=TRUE,$E38/J$13,$E38*(1+(1/J$13))) -> 0 | K38: =IF($N38=TRUE,$E38/K$13,$E38*(1+(1/K$13))) -> 0 | L38: =IF($N38=TRUE,$E38/L$13,$E38*(1+(1/L$13))) -> 0 | M38: =IF($N38=TRUE,$E38/M$13,$E38*(1+(1/M$13))) -> 0 | N38: FALSE | S38: =I13 -> 75 | T38: =I63 -> 0
E39: =C39*D39 -> 0 | F39: =IF($N39=TRUE,$E39/F$13,$E39*(1+(1/F$13))) -> 0 | G39: =IF($N39=TRUE,$E39/G$13,$E39*(1+(1/G$13))) -> 0 | H39: =IF($N39=TRUE,$E39/H$13,$E39*(1+(1/H$13))) -> 0 | I39: =IF($N39=TRUE,$E39/I$13,$E39*(1+(1/I$13))) -> 0 | J39: =IF($N39=TRUE,$E39/J$13,$E39*(1+(1/J$13))) -> 0 | K39: =IF($N39=TRUE,$E39/K$13,$E39*(1+(1/K$13))) -> 0 | L39: =IF($N39=TRUE,$E39/L$13,$E39*(1+(1/L$13))) -> 0 | M39: =IF($N39=TRUE,$E39/M$13,$E39*(1+(1/M$13))) -> 0 | N39: FALSE | S39: =H13 -> 50 | T39: =H63 -> 0
E40: =C40*D40 -> 0 | F40: =IF($N40=TRUE,$E40/F$13,$E40*(1+(1/F$13))) -> 0 | G40: =IF($N40=TRUE,$E40/G$13,$E40*(1+(1/G$13))) -> 0 | H40: =IF($N40=TRUE,$E40/H$13,$E40*(1+(1/H$13))) -> 0 | I40: =IF($N40=TRUE,$E40/I$13,$E40*(1+(1/I$13))) -> 0 | J40: =IF($N40=TRUE,$E40/J$13,$E40*(1+(1/J$13))) -> 0 | K40: =IF($N40=TRUE,$E40/K$13,$E40*(1+(1/K$13))) -> 0 | L40: =IF($N40=TRUE,$E40/L$13,$E40*(1+(1/L$13))) -> 0 | M40: =IF($N40=TRUE,$E40/M$13,$E40*(1+(1/M$13))) -> 0 | N40: FALSE | S40: =G13 -> 25 | T40: =G63 -> 0
E41: =C41*D41 -> 0 | F41: =IF($N41=TRUE,$E41/F$13,$E41*(1+(1/F$13))) -> 0 | G41: =IF($N41=TRUE,$E41/G$13,$E41*(1+(1/G$13))) -> 0 | H41: =IF($N41=TRUE,$E41/H$13,$E41*(1+(1/H$13))) -> 0 | I41: =IF($N41=TRUE,$E41/I$13,$E41*(1+(1/I$13))) -> 0 | J41: =IF($N41=TRUE,$E41/J$13,$E41*(1+(1/J$13))) -> 0 | K41: =IF($N41=TRUE,$E41/K$13,$E41*(1+(1/K$13))) -> 0 | L41: =IF($N41=TRUE,$E41/L$13,$E41*(1+(1/L$13))) -> 0 | M41: =IF($N41=TRUE,$E41/M$13,$E41*(1+(1/M$13))) -> 0 | N41: FALSE | S41: =F13 -> 10 | T41: =F63 -> 0
E42: =C42*D42 -> 0 | F42: =IF($N42=TRUE,$E42/F$13,$E42*(1+(1/F$13))) -> 0 | G42: =IF($N42=TRUE,$E42/G$13,$E42*(1+(1/G$13))) -> 0 | H42: =IF($N42=TRUE,$E42/H$13,$E42*(1+(1/H$13))) -> 0 | I42: =IF($N42=TRUE,$E42/I$13,$E42*(1+(1/I$13))) -> 0 | J42: =IF($N42=TRUE,$E42/J$13,$E42*(1+(1/J$13))) -> 0 | K42: =IF($N42=TRUE,$E42/K$13,$E42*(1+(1/K$13))) -> 0 | L42: =IF($N42=TRUE,$E42/L$13,$E42*(1+(1/L$13))) -> 0 | M42: =IF($N42=TRUE,$E42/M$13,$E42*(1+(1/M$13))) -> 0 | N42: FALSE
E43: =C43*D43 -> 0 | F43: =IF($N43=TRUE,$E43/F$13,$E43*(1+(1/F$13))) -> 0 | G43: =IF($N43=TRUE,$E43/G$13,$E43*(1+(1/G$13))) -> 0 | H43: =IF($N43=TRUE,$E43/H$13,$E43*(1+(1/H$13))) -> 0 | I43: =IF($N43=TRUE,$E43/I$13,$E43*(1+(1/I$13))) -> 0 | J43: =IF($N43=TRUE,$E43/J$13,$E43*(1+(1/J$13))) -> 0 | K43: =IF($N43=TRUE,$E43/K$13,$E43*(1+(1/K$13))) -> 0 | L43: =IF($N43=TRUE,$E43/L$13,$E43*(1+(1/L$13))) -> 0 | M43: =IF($N43=TRUE,$E43/M$13,$E43*(1+(1/M$13))) -> 0 | N43: FALSE
E44: =C44*D44 -> 0 | F44: =IF($N44=TRUE,$E44/F$13,$E44*(1+(1/F$13))) -> 0 | G44: =IF($N44=TRUE,$E44/G$13,$E44*(1+(1/G$13))) -> 0 | H44: =IF($N44=TRUE,$E44/H$13,$E44*(1+(1/H$13))) -> 0 | I44: =IF($N44=TRUE,$E44/I$13,$E44*(1+(1/I$13))) -> 0 | J44: =IF($N44=TRUE,$E44/J$13,$E44*(1+(1/J$13))) -> 0 | K44: =IF($N44=TRUE,$E44/K$13,$E44*(1+(1/K$13))) -> 0 | L44: =IF($N44=TRUE,$E44/L$13,$E44*(1+(1/L$13))) -> 0 | M44: =IF($N44=TRUE,$E44/M$13,$E44*(1+(1/M$13))) -> 0 | N44: FALSE
A45: PROCESSES/COMPONENTS | D45: SETUP $ | E45: RUN$ EA.
F46: =($D46/F$13)+$E46 -> 0 | G46: =($D46/G$13)+$E46 -> 0 | H46: =($D46/H$13)+$E46 -> 0 | I46: =($D46/I$13)+$E46 -> 0 | J46: =($D46/J$13)+$E46 -> 0 | K46: =($D46/K$13)+$E46 -> 0 | L46: =($D46/L$13)+$E46 -> 0 | M46: =($D46/M$13)+$E46 -> 0
F47: =($D47/F$13)+$E47 -> 0 | G47: =($D47/G$13)+$E47 -> 0 | H47: =($D47/H$13)+$E47 -> 0 | I47: =($D47/I$13)+$E47 -> 0 | J47: =($D47/J$13)+$E47 -> 0 | K47: =($D47/K$13)+$E47 -> 0 | L47: =($D47/L$13)+$E47 -> 0 | M47: =($D47/M$13)+$E47 -> 0
F48: =($D48/F$13)+$E48 -> 0 | G48: =($D48/G$13)+$E48 -> 0 | H48: =($D48/H$13)+$E48 -> 0 | I48: =($D48/I$13)+$E48 -> 0 | J48: =($D48/J$13)+$E48 -> 0 | K48: =($D48/K$13)+$E48 -> 0 | L48: =($D48/L$13)+$E48 -> 0 | M48: =($D48/M$13)+$E48 -> 0
F49: =($D49/F$13)+$E49 -> 0 | G49: =($D49/G$13)+$E49 -> 0 | H49: =($D49/H$13)+$E49 -> 0 | I49: =($D49/I$13)+$E49 -> 0 | J49: =($D49/J$13)+$E49 -> 0 | K49: =($D49/K$13)+$E49 -> 0 | L49: =($D49/L$13)+$E49 -> 0 | M49: =($D49/M$13)+$E49 -> 0
F50: =($D50/F$13)+$E50 -> 0 | G50: =($D50/G$13)+$E50 -> 0 | H50: =($D50/H$13)+$E50 -> 0 | I50: =($D50/I$13)+$E50 -> 0 | J50: =($D50/J$13)+$E50 -> 0 | K50: =($D50/K$13)+$E50 -> 0 | L50: =($D50/L$13)+$E50 -> 0 | M50: =($D50/M$13)+$E50 -> 0
B51: MATERIAL & HARDWARE TOTAL | F51: =SUM(F33:F44) -> 0 | G51: =SUM(G33:G44) -> 0 | H51: =SUM(H33:H44) -> 0 | I51: =SUM(I33:I44) -> 0 | J51: =SUM(J33:J44) -> 0 | K51: =SUM(K33:K44) -> 0 | L51: =SUM(L33:L44) -> 0 | M51: =SUM(M33:M44) -> 0 | N51: =IF(N13=0,0,SUM(N42:N44)) -> 0
B52: PROCESSES TOTAL | F52: =SUM(F46:F50) -> 0 | G52: =SUM(G46:G50) -> 0 | H52: =SUM(H46:H50) -> 0 | I52: =SUM(I46:I50) -> 0 | J52: =SUM(J46:J50) -> 0 | K52: =SUM(K46:K50) -> 0 | L52: =SUM(L46:L50) -> 0 | M52: =SUM(M46:M50) -> 0 | N52: =IF(N13=0,0,SUM(N46:N50)) -> 0
B53: M+L Subtotal | F53: =SUM(F30+F51+F52) -> 0 | G53: =SUM(G30+G51+G52) -> 0 | H53: =SUM(H30+H51+H52) -> 0 | I53: =SUM(I30+I51+I52) -> 0 | J53: =SUM(J30+J51+J52) -> 0 | K53: =SUM(K30+K51+K52) -> 0 | L53: =SUM(L30+L51+L52) -> 0 | M53: =SUM(M30+M51+M52) -> 0 | N53: =IF(N13=0,0,SUM(N30+N51+N52)) -> 0
E55: REFERENCE | F55: =SUM(F53+#REF!+#REF!) -> #REF! | G55: =SUM(G53+#REF!+#REF!) -> #REF! | H55: =SUM(H53+#REF!+#REF!) -> #REF! | I55: =SUM(I53+#REF!+#REF!) -> #REF! | J55: =SUM(J53+#REF!+#REF!) -> #REF! | K55: =SUM(K53+#REF!+#REF!) -> #REF! | L55: =SUM(L53+#REF!+#REF!) -> #REF! | M55: =SUM(M53+#REF!+#REF!) -> #REF! | N55: =SUM(N53+#REF!+#REF!) -> #REF!
D56: MARGIN | F56: =(F55-F53)/F55 -> #REF! | G56: =(G55-G53)/G55 -> #REF! | H56: =(H55-H53)/H55 -> #REF! | I56: =(I55-I53)/I55 -> #REF! | J56: =(J55-J53)/J55 -> #REF! | K56: =(K55-K53)/K55 -> #REF! | L56: =(L55-L53)/L55 -> #REF! | M56: =(M55-M53)/M55 -> #REF!
D57: LABOR | F57: =F30 -> 0 | G57: =G30 -> 0 | H57: =H30 -> 0 | I57: =I30 -> 0 | J57: =J30 -> 0 | K57: =K30 -> 0 | L57: =L30 -> 0 | M57: =M30 -> 0 | N57: =SUM((N30)) -> 0
C58: MAT'ls &HARDWARE | F58: =F51 -> 0 | G58: =G51 -> 0 | H58: =H51 -> 0 | I58: =I51 -> 0 | J58: =J51 -> 0 | K58: =K51 -> 0 | L58: =L51 -> 0 | M58: =M51 -> 0 | N58: =(N51) -> 0
D59: PROCESS | F59: =F52 -> 0 | G59: =G52 -> 0 | H59: =H52 -> 0 | I59: =I52 -> 0 | J59: =J52 -> 0 | K59: =K52 -> 0 | L59: =L52 -> 0 | M59: =M52 -> 0 | N59: =N52 -> 0
D60: Subtotal | F60: =SUM(F57:F59) -> 0 | G60: =SUM(G57:G59) -> 0 | H60: =SUM(H57:H59) -> 0 | I60: =SUM(I57:I59) -> 0 | J60: =SUM(J57:J59) -> 0 | K60: =SUM(K57:K59) -> 0 | L60: =SUM(L57:L59) -> 0 | M60: =SUM(M57:M59) -> 0 | N60: =SUM(N57:N59) -> 0
D61: AMORTIZED | F61: =$N$60/F13 -> 0 | G61: =$N$60/G13 -> 0 | H61: =$N$60/H13 -> 0 | I61: =$N$60/I13 -> 0 | J61: =$N$60/J13 -> 0 | K61: =$N$60/K13 -> 0 | L61: =$N$60/L13 -> 0 | M61: =$N$60/M13 -> 0
D62: Facilities | F62: 0 | G62: 0 | H62: 0 | I62: 0 | J62: 0 | K62: 0 | L62: 0 | M62: 0
D63: =B3 -> 9 | F63: =SUM(F60:F62) -> 0 | G63: =SUM(G60:G62) -> 0 | H63: =SUM(H60:H62) -> 0 | I63: =SUM(I60:I62) -> 0 | J63: =SUM(J60:J62) -> 0 | K63: =SUM(K60:K62) -> 0 | L63: =SUM(L60:L62) -> 0 | M63: =SUM(M60:M62) -> 0
A66: NRESC/TOOLING
A67: SETUPS
A68: FAIR
A69: SOURCE

Sheet Subassy 10
A2: CUSTOMER: | F2: Comments:
A3: P/N: | B3: 10 | D3: NSN #:
A4: REV: | D4: SOL #:
A5: QUOTE LOG No.: | D5: RFQ #:
A6: QTY: | B6: =F13&", "&G13&", "&H13&", "&I13&", "&J13&", "&K13&", "&L13&", "&M13 -> 10, 25, 50, 75, 100, 250, 500, 1000
A7: DATE:
A8: ESTIMATOR:
A11: MANUFACTURING OPERATIONS | F11: COST ESTIMATED QUANTITIES | N11: NRE/SET-UP
B13: SET-UP TIME | C13: RUN TIME | E13: LABOR RATE | F13: ='Top Assy'!F13 -> 10 | G13: ='Top Assy'!G13 -> 25 | H13: ='Top Assy'!H13 -> 50 | I13: ='Top Assy'!I13 -> 75 | J13: ='Top Assy'!J13 -> 100 | K13: ='Top Assy'!K13 -> 250 | L13: ='Top Assy'!L13 -> 500 | M13: ='Top Assy'!M13 -> 1000 | N13: 1
A14: Program | E14: 0 | N14: =(($B14/N$13*$E14)+($C14*$E14)) -> 0
A15: Fixtures | E15: 0 | N15: =(($B15/N$13*$E15)+($C15*$E15)) -> 0
A16: Mill/Turn | E16: 0 | F16: =(($B16/F$13*$E16)+($C16*$E16)) -> 0 | G16: =(($B16/G$13*$E16)+($C16*$E16)) -> 0 | H16: =(($B16/H$13*$E16)+($C16*$E16)) -> 0 | I16: =(($B16/I$13*$E16)+($C16*$E16)) -> 0 | J16: =(($B16/J$13*$E16)+($C16*$E16)) -> 0 | K16: =(($B16/K$13*$E16)+($C16*$E16)) -> 0 | L16: =(($B16/L$13*$E16)+($C16*$E16)) -> 0 | M16: =(($B16/M$13*$E16)+($C16*$E16)) -> 0
A17: Metals - Mills | E17: 0 | F17: =(($B17/F$13*$E17)+($C17*$E17)) -> 0 | G17: =(($B17/G$13*$E17)+($C17*$E17)) -> 0 | H17: =(($B17/H$13*$E17)+($C17*$E17)) -> 0 | I17: =(($B17/I$13*$E17)+($C17*$E17)) -> 0 | J17: =(($B17/J$13*$E17)+($C17*$E17)) -> 0 | K17: =(($B17/K$13*$E17)+($C17*$E17)) -> 0 | L17: =(($B17/L$13*$E17)+($C17*$E17)) -> 0 | M17: =(($B17/M$13*$E17)+($C17*$E17)) -> 0
A18: Metals - Lathe | E18: 0 | F18: =(($B18/F$13*$E18)+($C18*$E18)) -> 0 | G18: =(($B18/G$13*$E18)+($C18*$E18)) -> 0 | H18: =(($B18/H$13*$E18)+($C18*$E18)) -> 0 | I18: =(($B18/I$13*$E18)+($C18*$E18)) -> 0 | J18: =(($B18/J$13*$E18)+($C18*$E18)) -> 0 | K18: =(($B18/K$13*$E18)+($C18*$E18)) -> 0 | L18: =(($B18/L$13*$E18)+($C18*$E18)) -> 0 | M18: =(($B18/M$13*$E18)+($C18*$E18)) -> 0
A19: Rubber Mold | E19: 0 | F19: =(($B19/F$13*$E19)+($C19*$E19)) -> 0 | G19: =(($B19/G$13*$E19)+($C19*$E19)) -> 0 | H19: =(($B19/H$13*$E19)+($C19*$E19)) -> 0 | I19: =(($B19/I$13*$E19)+($C19*$E19)) -> 0 | J19: =(($B19/J$13*$E19)+($C19*$E19)) -> 0 | K19: =(($B19/K$13*$E19)+($C19*$E19)) -> 0 | L19: =(($B19/L$13*$E19)+($C19*$E19)) -> 0 | M19: =(($B19/M$13*$E19)+($C19*$E19)) -> 0
A20: Plastic Injection Mold | E20: 0 | F20: =(($B20/F$13*$E20)+($C20*$E20)) -> 0 | G20: =(($B20/G$13*$E20)+($C20*$E20)) -> 0 | H20: =(($B20/H$13*$E20)+($C20*$E20)) -> 0 | I20: =(($B20/I$13*$E20)+($C20*$E20)) -> 0 | J20: =(($B20/J$13*$E20)+($C20*$E20)) -> 0 | K20: =(($B20/K$13*$E20)+($C20*$E20)) -> 0 | L20: =(($B20/L$13*$E20)+($C20*$E20)) -> 0 | M20: =(($B20/M$13*$E20)+($C20*$E20)) -> 0
A21: Plastic Compression Mold | E21: 0 | F21: =(($B21/F$13*$E21)+($C21*$E21)) -> 0 | G21: =(($B21/G$13*$E21)+($C21*$E21)) -> 0 | H21: =(($B21/H$13*$E21)+($C21*$E21)) -> 0 | I21: =(($B21/I$13*$E21)+($C21*$E21)) -> 0 | J21: =(($B21/J$13*$E21)+($C21*$E21)) -> 0 | K21: =(($B21/K$13*$E21)+($C21*$E21)) -> 0 | L21: =(($B21/L$13*$E21)+($C21*$E21)) -> 0 | M21: =(($B21/M$13*$E21)+($C21*$E21)) -> 0
A22: Waterjet - Setup | E22: 0 | F22: =(($B22/F$13*$E22)+($C22*$E22)) -> 0 | G22: =(($B22/G$13*$E22)+($C22*$E22)) -> 0 | H22: =(($B22/H$13*$E22)+($C22*$E22)) -> 0 | I22: =(($B22/I$13*$E22)+($C22*$E22)) -> 0 | J22: =(($B22/J$13*$E22)+($C22*$E22)) -> 0 | K22: =(($B22/K$13*$E22)+($C22*$E22)) -> 0 | L22: =(($B22/L$13*$E22)+($C22*$E22)) -> 0 | M22: =(($B22/M$13*$E22)+($C22*$E22)) -> 0
A23: Waterjet - Operator | E23: 0 | F23: =(($B23/F$13*$E23)+($C23*$E23)) -> 0 | G23: =(($B23/G$13*$E23)+($C23*$E23)) -> 0 | H23: =(($B23/H$13*$E23)+($C23*$E23)) -> 0 | I23: =(($B23/I$13*$E23)+($C23*$E23)) -> 0 | J23: =(($B23/J$13*$E23)+($C23*$E23)) -> 0 | K23: =(($B23/K$13*$E23)+($C23*$E23)) -> 0 | L23: =(($B23/L$13*$E23)+($C23*$E23)) -> 0 | M23: =(($B23/M$13*$E23)+($C23*$E23)) -> 0
A24: Assembly, Die Punch, Deburr | E24: 0 | F24: =(($B24/F$13*$E24)+($C24*$E24)) -> 0 | G24: =(($B24/G$13*$E24)+($C24*$E24)) -> 0 | H24: =(($B24/H$13*$E24)+($C24*$E24)) -> 0 | I24: =(($B24/I$13*$E24)+($C24*$E24)) -> 0 | J24: =(($B24/J$13*$E24)+($C24*$E24)) -> 0 | K24: =(($B24/K$13*$E24)+($C24*$E24)) -> 0 | L24: =(($B24/L$13*$E24)+($C24*$E24)) -> 0 | M24: =(($B24/M$13*$E24)+($C24*$E24)) -> 0
A25: Quality Inspection | E25: 0 | F25: =(($B25/F$13*$E25)+($C25*$E25)) -> 0 | G25: =(($B25/G$13*$E25)+($C25*$E25)) -> 0 | H25: =(($B25/H$13*$E25)+($C25*$E25)) -> 0 | I25: =(($B25/I$13*$E25)+($C25*$E25)) -> 0 | J25: =(($B25/J$13*$E25)+($C25*$E25)) -> 0 | K25: =(($B25/K$13*$E25)+($C25*$E25)) -> 0 | L25: =(($B25/L$13*$E25)+($C25*$E25)) -> 0 | M25: =(($B25/M$13*$E25)+($C25*$E25)) -> 0
C26: Labor | E26: Basic LABOR | F26: =SUM(F16:F25) -> 0 | G26: =SUM(G16:G25) -> 0 | H26: =SUM(H16:H25) -> 0 | I26: =SUM(I16:I25) -> 0 | J26: =SUM(J16:J25) -> 0 | K26: =SUM(K16:K25) -> 0 | L26: =SUM(L16:L25) -> 0 | M26: =SUM(M16:M25) -> 0 | N26: =SUM(N14:N25) -> 0
B27: T. setup | C27: T.RUN | E27: hrs | F27: =(($B$28/F13)+$C$28)/60 -> 0 | G27: =(($B$28/G13)+$C$28)/60 -> 0 | H27: =(($B$28/H13)+$C$28)/60 -> 0 | I27: =(($B$28/I13)+$C$28)/60 -> 0 | J27: =(($B$28/J13)+$C$28)/60 -> 0 | K27: =(($B$28/K13)+$C$28)/60 -> 0 | L27: =(($B$28/L13)+$C$28)/60 -> 0 | M27: =(($B$28/M13)+$C$28)/60 -> 0
B28: =SUM(B16:B25) -> 0 | C28: =SUM(C16:C25) -> 0 | D28: 0 | E28: BURDEN | F28: =F26*$D$28 -> 0 | G28: =G26*$D$28 -> 0 | H28: =H26*$D$28 -> 0 | I28: =I26*$D$28 -> 0 | J28: =J26*$D$28 -> 0 | K28: =K26*$D$28 -> 0 | L28: =L26*$D$28 -> 0 | M28: =M26*$D$28 -> 0
E30: Total | F30: =F26+F28 -> 0 | G30: =G26+G28 -> 0 | H30: =H26+H28 -> 0 | I30: =I26+I28 -> 0 | J30: =J26+J28 -> 0 | K30: =K26+K28 -> 0 | L30: =L26+L28 -> 0 | M30: =M26+M28 -> 0 | N30: =N26 -> 0
A32: RAW MATERIALS & HARDWARE | B32: Matl UoM | C32: PARTS QTY | D32: UNIT PRICE | E32: MAT'l BURDEN | F32: ="Qty: "& F13 -> Qty: 10 | G32: ="Qty: "& G13 -> Qty: 25 | H32: ="Qty: "& H13 -> Qty: 50 | I32: ="Qty: "& I13 -> Qty: 75 | J32: ="Qty: "& J13 -> Qty: 100 | K32: ="Qty: "& K13 -> Qty: 250 | L32: ="Qty: "& L13 -> Qty: 500 | M32: ="Qty: "& M13 -> Qty: 1000 | N32: Amortize/ Min Buy
E33: =C33*D33 -> 0 | F33: =IF($N33=TRUE,$E33/F$13,$E33*(1+(1/F$13))) -> 0 | G33: =IF($N33=TRUE,$E33/G$13,$E33*(1+(1/G$13))) -> 0 | H33: =IF($N33=TRUE,$E33/H$13,$E33*(1+(1/H$13))) -> 0 | I33: =IF($N33=TRUE,$E33/I$13,$E33*(1+(1/I$13))) -> 0 | J33: =IF($N33=TRUE,$E33/J$13,$E33*(1+(1/J$13))) -> 0 | K33: =IF($N33=TRUE,$E33/K$13,$E33*(1+(1/K$13))) -> 0 | L33: =IF($N33=TRUE,$E33/L$13,$E33*(1+(1/L$13))) -> 0 | M33: =IF($N33=TRUE,$E33/M$13,$E33*(1+(1/M$13))) -> 0 | N33: FALSE
E34: =C34*D34 -> 0 | F34: =IF($N34=TRUE,$E34/F$13,$E34*(1+(1/F$13))) -> 0 | G34: =IF($N34=TRUE,$E34/G$13,$E34*(1+(1/G$13))) -> 0 | H34: =IF($N34=TRUE,$E34/H$13,$E34*(1+(1/H$13))) -> 0 | I34: =IF($N34=TRUE,$E34/I$13,$E34*(1+(1/I$13))) -> 0 | J34: =IF($N34=TRUE,$E34/J$13,$E34*(1+(1/J$13))) -> 0 | K34: =IF($N34=TRUE,$E34/K$13,$E34*(1+(1/K$13))) -> 0 | L34: =IF($N34=TRUE,$E34/L$13,$E34*(1+(1/L$13))) -> 0 | M34: =IF($N34=TRUE,$E34/M$13,$E34*(1+(1/M$13))) -> 0 | N34: FALSE
E35: =C35*D35 -> 0 | F35: =IF($N35=TRUE,$E35/F$13,$E35*(1+(1/F$13))) -> 0 | G35: =IF($N35=TRUE,$E35/G$13,$E35*(1+(1/G$13))) -> 0 | H35: =IF($N35=TRUE,$E35/H$13,$E35*(1+(1/H$13))) -> 0 | I35: =IF($N35=TRUE,$E35/I$13,$E35*(1+(1/I$13))) -> 0 | J35: =IF($N35=TRUE,$E35/J$13,$E35*(1+(1/J$13))) -> 0 | K35: =IF($N35=TRUE,$E35/K$13,$E35*(1+(1/K$13))) -> 0 | L35: =IF($N35=TRUE,$E35/L$13,$E35*(1+(1/L$13))) -> 0 | M35: =IF($N35=TRUE,$E35/M$13,$E35*(1+(1/M$13))) -> 0 | N35: FALSE | S35: QTY | T35: Total
E36: =C36*D36 -> 0 | F36: =IF($N36=TRUE,$E36/F$13,$E36*(1+(1/F$13))) -> 0 | G36: =IF($N36=TRUE,$E36/G$13,$E36*(1+(1/G$13))) -> 0 | H36: =IF($N36=TRUE,$E36/H$13,$E36*(1+(1/H$13))) -> 0 | I36: =IF($N36=TRUE,$E36/I$13,$E36*(1+(1/I$13))) -> 0 | J36: =IF($N36=TRUE,$E36/J$13,$E36*(1+(1/J$13))) -> 0 | K36: =IF($N36=TRUE,$E36/K$13,$E36*(1+(1/K$13))) -> 0 | L36: =IF($N36=TRUE,$E36/L$13,$E36*(1+(1/L$13))) -> 0 | M36: =IF($N36=TRUE,$E36/M$13,$E36*(1+(1/M$13))) -> 0 | N36: FALSE | S36: =M13 -> 1000 | T36: =M63 -> 0
E37: =C37*D37 -> 0 | F37: =IF($N37=TRUE,$E37/F$13,$E37*(1+(1/F$13))) -> 0 | G37: =IF($N37=TRUE,$E37/G$13,$E37*(1+(1/G$13))) -> 0 | H37: =IF($N37=TRUE,$E37/H$13,$E37*(1+(1/H$13))) -> 0 | I37: =IF($N37=TRUE,$E37/I$13,$E37*(1+(1/I$13))) -> 0 | J37: =IF($N37=TRUE,$E37/J$13,$E37*(1+(1/J$13))) -> 0 | K37: =IF($N37=TRUE,$E37/K$13,$E37*(1+(1/K$13))) -> 0 | L37: =IF($N37=TRUE,$E37/L$13,$E37*(1+(1/L$13))) -> 0 | M37: =IF($N37=TRUE,$E37/M$13,$E37*(1+(1/M$13))) -> 0 | N37: FALSE | S37: =L13 -> 500 | T37: =L63 -> 0
E38: =C38*D38 -> 0 | F38: =IF($N38=TRUE,$E38/F$13,$E38*(1+(1/F$13))) -> 0 | G38: =IF($N38=TRUE,$E38/G$13,$E38*(1+(1/G$13))) -> 0 | H38: =IF($N38=TRUE,$E38/H$13,$E38*(1+(1/H$13))) -> 0 | I38: =IF($N38=TRUE,$E38/I$13,$E38*(1+(1/I$13))) -> 0 | J38: =IF($N38=TRUE,$E38/J$13,$E38*(1+(1/J$13))) -> 0 | K38: =IF($N38=TRUE,$E38/K$13,$E38*(1+(1/K$13))) -> 0 | L38: =IF($N38=TRUE,$E38/L$13,$E38*(1+(1/L$13))) -> 0 | M38: =IF($N38=TRUE,$E38/M$13,$E38*(1+(1/M$13))) -> 0 | N38: FALSE | S38: =I13 -> 75 | T38: =I63 -> 0
E39: =C39*D39 -> 0 | F39: =IF($N39=TRUE,$E39/F$13,$E39*(1+(1/F$13))) -> 0 | G39: =IF($N39=TRUE,$E39/G$13,$E39*(1+(1/G$13))) -> 0 | H39: =IF($N39=TRUE,$E39/H$13,$E39*(1+(1/H$13))) -> 0 | I39: =IF($N39=TRUE,$E39/I$13,$E39*(1+(1/I$13))) -> 0 | J39: =IF($N39=TRUE,$E39/J$13,$E39*(1+(1/J$13))) -> 0 | K39: =IF($N39=TRUE,$E39/K$13,$E39*(1+(1/K$13))) -> 0 | L39: =IF($N39=TRUE,$E39/L$13,$E39*(1+(1/L$13))) -> 0 | M39: =IF($N39=TRUE,$E39/M$13,$E39*(1+(1/M$13))) -> 0 | N39: FALSE | S39: =H13 -> 50 | T39: =H63 -> 0
E40: =C40*D40 -> 0 | F40: =IF($N40=TRUE,$E40/F$13,$E40*(1+(1/F$13))) -> 0 | G40: =IF($N40=TRUE,$E40/G$13,$E40*(1+(1/G$13))) -> 0 | H40: =IF($N40=TRUE,$E40/H$13,$E40*(1+(1/H$13))) -> 0 | I40: =IF($N40=TRUE,$E40/I$13,$E40*(1+(1/I$13))) -> 0 | J40: =IF($N40=TRUE,$E40/J$13,$E40*(1+(1/J$13))) -> 0 | K40: =IF($N40=TRUE,$E40/K$13,$E40*(1+(1/K$13))) -> 0 | L40: =IF($N40=TRUE,$E40/L$13,$E40*(1+(1/L$13))) -> 0 | M40: =IF($N40=TRUE,$E40/M$13,$E40*(1+(1/M$13))) -> 0 | N40: FALSE | S40: =G13 -> 25 | T40: =G63 -> 0
E41: =C41*D41 -> 0 | F41: =IF($N41=TRUE,$E41/F$13,$E41*(1+(1/F$13))) -> 0 | G41: =IF($N41=TRUE,$E41/G$13,$E41*(1+(1/G$13))) -> 0 | H41: =IF($N41=TRUE,$E41/H$13,$E41*(1+(1/H$13))) -> 0 | I41: =IF($N41=TRUE,$E41/I$13,$E41*(1+(1/I$13))) -> 0 | J41: =IF($N41=TRUE,$E41/J$13,$E41*(1+(1/J$13))) -> 0 | K41: =IF($N41=TRUE,$E41/K$13,$E41*(1+(1/K$13))) -> 0 | L41: =IF($N41=TRUE,$E41/L$13,$E41*(1+(1/L$13))) -> 0 | M41: =IF($N41=TRUE,$E41/M$13,$E41*(1+(1/M$13))) -> 0 | N41: FALSE | S41: =F13 -> 10 | T41: =F63 -> 0
E42: =C42*D42 -> 0 | F42: =IF($N42=TRUE,$E42/F$13,$E42*(1+(1/F$13))) -> 0 | G42: =IF($N42=TRUE,$E42/G$13,$E42*(1+(1/G$13))) -> 0 | H42: =IF($N42=TRUE,$E42/H$13,$E42*(1+(1/H$13))) -> 0 | I42: =IF($N42=TRUE,$E42/I$13,$E42*(1+(1/I$13))) -> 0 | J42: =IF($N42=TRUE,$E42/J$13,$E42*(1+(1/J$13))) -> 0 | K42: =IF($N42=TRUE,$E42/K$13,$E42*(1+(1/K$13))) -> 0 | L42: =IF($N42=TRUE,$E42/L$13,$E42*(1+(1/L$13))) -> 0 | M42: =IF($N42=TRUE,$E42/M$13,$E42*(1+(1/M$13))) -> 0 | N42: FALSE
E43: =C43*D43 -> 0 | F43: =IF($N43=TRUE,$E43/F$13,$E43*(1+(1/F$13))) -> 0 | G43: =IF($N43=TRUE,$E43/G$13,$E43*(1+(1/G$13))) -> 0 | H43: =IF($N43=TRUE,$E43/H$13,$E43*(1+(1/H$13))) -> 0 | I43: =IF($N43=TRUE,$E43/I$13,$E43*(1+(1/I$13))) -> 0 | J43: =IF($N43=TRUE,$E43/J$13,$E43*(1+(1/J$13))) -> 0 | K43: =IF($N43=TRUE,$E43/K$13,$E43*(1+(1/K$13))) -> 0 | L43: =IF($N43=TRUE,$E43/L$13,$E43*(1+(1/L$13))) -> 0 | M43: =IF($N43=TRUE,$E43/M$13,$E43*(1+(1/M$13))) -> 0 | N43: FALSE
E44: =C44*D44 -> 0 | F44: =IF($N44=TRUE,$E44/F$13,$E44*(1+(1/F$13))) -> 0 | G44: =IF($N44=TRUE,$E44/G$13,$E44*(1+(1/G$13))) -> 0 | H44: =IF($N44=TRUE,$E44/H$13,$E44*(1+(1/H$13))) -> 0 | I44: =IF($N44=TRUE,$E44/I$13,$E44*(1+(1/I$13))) -> 0 | J44: =IF($N44=TRUE,$E44/J$13,$E44*(1+(1/J$13))) -> 0 | K44: =IF($N44=TRUE,$E44/K$13,$E44*(1+(1/K$13))) -> 0 | L44: =IF($N44=TRUE,$E44/L$13,$E44*(1+(1/L$13))) -> 0 | M44: =IF($N44=TRUE,$E44/M$13,$E44*(1+(1/M$13))) -> 0 | N44: FALSE
A45: PROCESSES/COMPONENTS | D45: SETUP $ | E45: RUN$ EA.
F46: =($D46/F$13)+$E46 -> 0 | G46: =($D46/G$13)+$E46 -> 0 | H46: =($D46/H$13)+$E46 -> 0 | I46: =($D46/I$13)+$E46 -> 0 | J46: =($D46/J$13)+$E46 -> 0 | K46: =($D46/K$13)+$E46 -> 0 | L46: =($D46/L$13)+$E46 -> 0 | M46: =($D46/M$13)+$E46 -> 0
F47: =($D47/F$13)+$E47 -> 0 | G47: =($D47/G$13)+$E47 -> 0 | H47: =($D47/H$13)+$E47 -> 0 | I47: =($D47/I$13)+$E47 -> 0 | J47: =($D47/J$13)+$E47 -> 0 | K47: =($D47/K$13)+$E47 -> 0 | L47: =($D47/L$13)+$E47 -> 0 | M47: =($D47/M$13)+$E47 -> 0
F48: =($D48/F$13)+$E48 -> 0 | G48: =($D48/G$13)+$E48 -> 0 | H48: =($D48/H$13)+$E48 -> 0 | I48: =($D48/I$13)+$E48 -> 0 | J48: =($D48/J$13)+$E48 -> 0 | K48: =($D48/K$13)+$E48 -> 0 | L48: =($D48/L$13)+$E48 -> 0 | M48: =($D48/M$13)+$E48 -> 0
F49: =($D49/F$13)+$E49 -> 0 | G49: =($D49/G$13)+$E49 -> 0 | H49: =($D49/H$13)+$E49 -> 0 | I49: =($D49/I$13)+$E49 -> 0 | J49: =($D49/J$13)+$E49 -> 0 | K49: =($D49/K$13)+$E49 -> 0 | L49: =($D49/L$13)+$E49 -> 0 | M49: =($D49/M$13)+$E49 -> 0
F50: =($D50/F$13)+$E50 -> 0 | G50: =($D50/G$13)+$E50 -> 0 | H50: =($D50/H$13)+$E50 -> 0 | I50: =($D50/I$13)+$E50 -> 0 | J50: =($D50/J$13)+$E50 -> 0 | K50: =($D50/K$13)+$E50 -> 0 | L50: =($D50/L$13)+$E50 -> 0 | M50: =($D50/M$13)+$E50 -> 0
B51: MATERIAL & HARDWARE TOTAL | F51: =SUM(F33:F44) -> 0 | G51: =SUM(G33:G44) -> 0 | H51: =SUM(H33:H44) -> 0 | I51: =SUM(I33:I44) -> 0 | J51: =SUM(J33:J44) -> 0 | K51: =SUM(K33:K44) -> 0 | L51: =SUM(L33:L44) -> 0 | M51: =SUM(M33:M44) -> 0 | N51: =IF(N13=0,0,SUM(N42:N44)) -> 0
B52: PROCESSES TOTAL | F52: =SUM(F46:F50) -> 0 | G52: =SUM(G46:G50) -> 0 | H52: =SUM(H46:H50) -> 0 | I52: =SUM(I46:I50) -> 0 | J52: =SUM(J46:J50) -> 0 | K52: =SUM(K46:K50) -> 0 | L52: =SUM(L46:L50) -> 0 | M52: =SUM(M46:M50) -> 0 | N52: =IF(N13=0,0,SUM(N46:N50)) -> 0
B53: M+L Subtotal | F53: =SUM(F30+F51+F52) -> 0 | G53: =SUM(G30+G51+G52) -> 0 | H53: =SUM(H30+H51+H52) -> 0 | I53: =SUM(I30+I51+I52) -> 0 | J53: =SUM(J30+J51+J52) -> 0 | K53: =SUM(K30+K51+K52) -> 0 | L53: =SUM(L30+L51+L52) -> 0 | M53: =SUM(M30+M51+M52) -> 0 | N53: =IF(N13=0,0,SUM(N30+N51+N52)) -> 0
E55: REFERENCE | F55: =SUM(F53+#REF!+#REF!) -> #REF! | G55: =SUM(G53+#REF!+#REF!) -> #REF! | H55: =SUM(H53+#REF!+#REF!) -> #REF! | I55: =SUM(I53+#REF!+#REF!) -> #REF! | J55: =SUM(J53+#REF!+#REF!) -> #REF! | K55: =SUM(K53+#REF!+#REF!) -> #REF! | L55: =SUM(L53+#REF!+#REF!) -> #REF! | M55: =SUM(M53+#REF!+#REF!) -> #REF! | N55: =SUM(N53+#REF!+#REF!) -> #REF!
D56: MARGIN | F56: =(F55-F53)/F55 -> #REF! | G56: =(G55-G53)/G55 -> #REF! | H56: =(H55-H53)/H55 -> #REF! | I56: =(I55-I53)/I55 -> #REF! | J56: =(J55-J53)/J55 -> #REF! | K56: =(K55-K53)/K55 -> #REF! | L56: =(L55-L53)/L55 -> #REF! | M56: =(M55-M53)/M55 -> #REF!
D57: LABOR | F57: =F30 -> 0 | G57: =G30 -> 0 | H57: =H30 -> 0 | I57: =I30 -> 0 | J57: =J30 -> 0 | K57: =K30 -> 0 | L57: =L30 -> 0 | M57: =M30 -> 0 | N57: =SUM((N30)) -> 0
C58: MAT'ls &HARDWARE | F58: =F51 -> 0 | G58: =G51 -> 0 | H58: =H51 -> 0 | I58: =I51 -> 0 | J58: =J51 -> 0 | K58: =K51 -> 0 | L58: =L51 -> 0 | M58: =M51 -> 0 | N58: =(N51) -> 0
D59: PROCESS | F59: =F52 -> 0 | G59: =G52 -> 0 | H59: =H52 -> 0 | I59: =I52 -> 0 | J59: =J52 -> 0 | K59: =K52 -> 0 | L59: =L52 -> 0 | M59: =M52 -> 0 | N59: =N52 -> 0
D60: Subtotal | F60: =SUM(F57:F59) -> 0 | G60: =SUM(G57:G59) -> 0 | H60: =SUM(H57:H59) -> 0 | I60: =SUM(I57:I59) -> 0 | J60: =SUM(J57:J59) -> 0 | K60: =SUM(K57:K59) -> 0 | L60: =SUM(L57:L59) -> 0 | M60: =SUM(M57:M59) -> 0 | N60: =SUM(N57:N59) -> 0
D61: AMORTIZED | F61: =$N$60/F13 -> 0 | G61: =$N$60/G13 -> 0 | H61: =$N$60/H13 -> 0 | I61: =$N$60/I13 -> 0 | J61: =$N$60/J13 -> 0 | K61: =$N$60/K13 -> 0 | L61: =$N$60/L13 -> 0 | M61: =$N$60/M13 -> 0
D62: Facilities | F62: 0 | G62: 0 | H62: 0 | I62: 0 | J62: 0 | K62: 0 | L62: 0 | M62: 0
D63: =B3 -> 10 | F63: =SUM(F60:F62) -> 0 | G63: =SUM(G60:G62) -> 0 | H63: =SUM(H60:H62) -> 0 | I63: =SUM(I60:I62) -> 0 | J63: =SUM(J60:J62) -> 0 | K63: =SUM(K60:K62) -> 0 | L63: =SUM(L60:L62) -> 0 | M63: =SUM(M60:M62) -> 0
A66: NRESC/TOOLING
A67: SETUPS
A68: FAIR
A69: SOURCE

Sheet Subassy 11
A2: CUSTOMER: | F2: Comments:
A3: P/N: | B3: 11 | D3: NSN #:
A4: REV: | D4: SOL #:
A5: QUOTE LOG No.: | D5: RFQ #:
A6: QTY: | B6: =F13&", "&G13&", "&H13&", "&I13&", "&J13&", "&K13&", "&L13&", "&M13 -> 10, 25, 50, 75, 100, 250, 500, 1000
A7: DATE:
A8: ESTIMATOR:
A11: MANUFACTURING OPERATIONS | F11: COST ESTIMATED QUANTITIES | N11: NRE/SET-UP
B13: SET-UP TIME | C13: RUN TIME | E13: LABOR RATE | F13: ='Top Assy'!F13 -> 10 | G13: ='Top Assy'!G13 -> 25 | H13: ='Top Assy'!H13 -> 50 | I13: ='Top Assy'!I13 -> 75 | J13: ='Top Assy'!J13 -> 100 | K13: ='Top Assy'!K13 -> 250 | L13: ='Top Assy'!L13 -> 500 | M13: ='Top Assy'!M13 -> 1000 | N13: 1
A14: Program | E14: 0 | N14: =(($B14/N$13*$E14)+($C14*$E14)) -> 0
A15: Fixtures | E15: 0 | N15: =(($B15/N$13*$E15)+($C15*$E15)) -> 0
A16: Mill/Turn | E16: 0 | F16: =(($B16/F$13*$E16)+($C16*$E16)) -> 0 | G16: =(($B16/G$13*$E16)+($C16*$E16)) -> 0 | H16: =(($B16/H$13*$E16)+($C16*$E16)) -> 0 | I16: =(($B16/I$13*$E16)+($C16*$E16)) -> 0 | J16: =(($B16/J$13*$E16)+($C16*$E16)) -> 0 | K16: =(($B16/K$13*$E16)+($C16*$E16)) -> 0 | L16: =(($B16/L$13*$E16)+($C16*$E16)) -> 0 | M16: =(($B16/M$13*$E16)+($C16*$E16)) -> 0
A17: Metals - Mills | E17: 0 | F17: =(($B17/F$13*$E17)+($C17*$E17)) -> 0 | G17: =(($B17/G$13*$E17)+($C17*$E17)) -> 0 | H17: =(($B17/H$13*$E17)+($C17*$E17)) -> 0 | I17: =(($B17/I$13*$E17)+($C17*$E17)) -> 0 | J17: =(($B17/J$13*$E17)+($C17*$E17)) -> 0 | K17: =(($B17/K$13*$E17)+($C17*$E17)) -> 0 | L17: =(($B17/L$13*$E17)+($C17*$E17)) -> 0 | M17: =(($B17/M$13*$E17)+($C17*$E17)) -> 0
A18: Metals - Lathe | E18: 0 | F18: =(($B18/F$13*$E18)+($C18*$E18)) -> 0 | G18: =(($B18/G$13*$E18)+($C18*$E18)) -> 0 | H18: =(($B18/H$13*$E18)+($C18*$E18)) -> 0 | I18: =(($B18/I$13*$E18)+($C18*$E18)) -> 0 | J18: =(($B18/J$13*$E18)+($C18*$E18)) -> 0 | K18: =(($B18/K$13*$E18)+($C18*$E18)) -> 0 | L18: =(($B18/L$13*$E18)+($C18*$E18)) -> 0 | M18: =(($B18/M$13*$E18)+($C18*$E18)) -> 0
A19: Rubber Mold | E19: 0 | F19: =(($B19/F$13*$E19)+($C19*$E19)) -> 0 | G19: =(($B19/G$13*$E19)+($C19*$E19)) -> 0 | H19: =(($B19/H$13*$E19)+($C19*$E19)) -> 0 | I19: =(($B19/I$13*$E19)+($C19*$E19)) -> 0 | J19: =(($B19/J$13*$E19)+($C19*$E19)) -> 0 | K19: =(($B19/K$13*$E19)+($C19*$E19)) -> 0 | L19: =(($B19/L$13*$E19)+($C19*$E19)) -> 0 | M19: =(($B19/M$13*$E19)+($C19*$E19)) -> 0
A20: Plastic Injection Mold | E20: 0 | F20: =(($B20/F$13*$E20)+($C20*$E20)) -> 0 | G20: =(($B20/G$13*$E20)+($C20*$E20)) -> 0 | H20: =(($B20/H$13*$E20)+($C20*$E20)) -> 0 | I20: =(($B20/I$13*$E20)+($C20*$E20)) -> 0 | J20: =(($B20/J$13*$E20)+($C20*$E20)) -> 0 | K20: =(($B20/K$13*$E20)+($C20*$E20)) -> 0 | L20: =(($B20/L$13*$E20)+($C20*$E20)) -> 0 | M20: =(($B20/M$13*$E20)+($C20*$E20)) -> 0
A21: Plastic Compression Mold | E21: 0 | F21: =(($B21/F$13*$E21)+($C21*$E21)) -> 0 | G21: =(($B21/G$13*$E21)+($C21*$E21)) -> 0 | H21: =(($B21/H$13*$E21)+($C21*$E21)) -> 0 | I21: =(($B21/I$13*$E21)+($C21*$E21)) -> 0 | J21: =(($B21/J$13*$E21)+($C21*$E21)) -> 0 | K21: =(($B21/K$13*$E21)+($C21*$E21)) -> 0 | L21: =(($B21/L$13*$E21)+($C21*$E21)) -> 0 | M21: =(($B21/M$13*$E21)+($C21*$E21)) -> 0
A22: Waterjet - Setup | E22: 0 | F22: =(($B22/F$13*$E22)+($C22*$E22)) -> 0 | G22: =(($B22/G$13*$E22)+($C22*$E22)) -> 0 | H22: =(($B22/H$13*$E22)+($C22*$E22)) -> 0 | I22: =(($B22/I$13*$E22)+($C22*$E22)) -> 0 | J22: =(($B22/J$13*$E22)+($C22*$E22)) -> 0 | K22: =(($B22/K$13*$E22)+($C22*$E22)) -> 0 | L22: =(($B22/L$13*$E22)+($C22*$E22)) -> 0 | M22: =(($B22/M$13*$E22)+($C22*$E22)) -> 0
A23: Waterjet - Operator | E23: 0 | F23: =(($B23/F$13*$E23)+($C23*$E23)) -> 0 | G23: =(($B23/G$13*$E23)+($C23*$E23)) -> 0 | H23: =(($B23/H$13*$E23)+($C23*$E23)) -> 0 | I23: =(($B23/I$13*$E23)+($C23*$E23)) -> 0 | J23: =(($B23/J$13*$E23)+($C23*$E23)) -> 0 | K23: =(($B23/K$13*$E23)+($C23*$E23)) -> 0 | L23: =(($B23/L$13*$E23)+($C23*$E23)) -> 0 | M23: =(($B23/M$13*$E23)+($C23*$E23)) -> 0
A24: Assembly, Die Punch, Deburr | E24: 0 | F24: =(($B24/F$13*$E24)+($C24*$E24)) -> 0 | G24: =(($B24/G$13*$E24)+($C24*$E24)) -> 0 | H24: =(($B24/H$13*$E24)+($C24*$E24)) -> 0 | I24: =(($B24/I$13*$E24)+($C24*$E24)) -> 0 | J24: =(($B24/J$13*$E24)+($C24*$E24)) -> 0 | K24: =(($B24/K$13*$E24)+($C24*$E24)) -> 0 | L24: =(($B24/L$13*$E24)+($C24*$E24)) -> 0 | M24: =(($B24/M$13*$E24)+($C24*$E24)) -> 0
A25: Quality Inspection | E25: 0 | F25: =(($B25/F$13*$E25)+($C25*$E25)) -> 0 | G25: =(($B25/G$13*$E25)+($C25*$E25)) -> 0 | H25: =(($B25/H$13*$E25)+($C25*$E25)) -> 0 | I25: =(($B25/I$13*$E25)+($C25*$E25)) -> 0 | J25: =(($B25/J$13*$E25)+($C25*$E25)) -> 0 | K25: =(($B25/K$13*$E25)+($C25*$E25)) -> 0 | L25: =(($B25/L$13*$E25)+($C25*$E25)) -> 0 | M25: =(($B25/M$13*$E25)+($C25*$E25)) -> 0
